Workbook

Sheet Read Me
A1: Southern Water Corp. Financial Analysis
N4: Juti
A11: In this unit, you've learned about the fundamentals of financial analysis spanning revenues, expenses and profitability.
A12: In this case study, we'll seek to unpack these concepts, combining the financial analysis skills you've learned and have you apply this through your budding Excel capabilities!
A13: This case study will emphasise both your use of the SUMIFS Formula as well as your charting capabilities, where you'll use these charts for a PowerPoint presentation you'll create at the end of this analysis!
A14: Good luck and let's get started!
A16: What do the tab colours in this workbook mean?
A17: Throughout the Case Study, we've split this into three sections. As you cover the relevant financial concepts, you'll apply what you've learned in the exercise tabs. The order of completion is below: 1) Revenue Sub Unit - Revenue Analysis 2) Expense Sub Unit - Expense Analysis 3) Profitability Sub Unit - Profitability (EBIT) Analysis
A18: Unpacking the Data Repository Table
A19: The data repository table might look scary at first, but all the data is logically grouped in a manner where the table can be read left-to-right.
A20: We've included an example below to break down how you can interpret this information.
A32: Definitions
A33: We've included a high-level breakdown that explains the different columns you will deal with in the data repository table. Please read through this and familiarise yourself with what these columns mean.
A35: Account Type | B35: This column provides information on whether the dataset is referencing Financial Actuals (Money Spent) or Water Actuals (Volume of Water Produced).
A36: Value Drivers | B36: This is a pre-filled column mapping each Accounting Centre Code and Accounting Centre Code Element to either a Revenue Generating Activity (Revenues) or Cost Generating Activity (Expenses).
A37: Unit | B37: There are three desalination units or plants (facilities) owned by Southern Water Corp. These are the Kootha, Surjek and Jutik desalination units. The Unit column indicates, for that row of data, which Unit it applies towards.
A38: Month | B38: This represents the month that data was calculated for.
A39: Month (Number) | B39: This represents the month in numerical form.
A40: Accounting Code Centre | B40: Every row is mapped to an Accounting Code Centre. Based off the Accounting Code Centre (ACC) and the textual description, we know that all ACC's that mention Sales, are Profit Centres, and all ACC's that mention Costs, are Cost Centres. In Financial Accounting, Revenue Generating Activities are mapped to Profit Centres (i.e. They generate profit), whilst Cost Generating Activities are mapped to Cost Centres (i.e. They generate costs).
A41: Accounting Code Centre Element | B41: An Accounting Code Centre Element (ACCE) is made up of 'elements' which tie into the Accounting Code Centre.
A42: Unit of Measure | B42: Every Row of Data has a Unit of Measure (UoM) associated with this. E.g. Financial data is measured in dollars, whilst Water Production data is measure in Giga-Litres.
A43: Row Data | B43: This is the unique value that is stored for every row entry.
A46: Value Driver Trees
A47: Below we've included the Value Driver Trees for Revenues, Expenses and Profitability Analysis, to better help you understand how the dataset is all connected. Use this if you're feeling unsure of how to calculate Revenues, Expenses or Profitability.

Sheet Data Repository Table
A1: Account Type | B1: Value Drivers | C1: Unit | D1: Month | E1: Month (Number) | F1: Accounting Code Centre | G1: Accounting Code Centre Element | H1: Unit of Measure | I1: Row Data
A2: Financial Actual | B2: Revenue | C2: Kootha | D2: 41456 | E2: =MONTH(D2) -> 7 | F2: 001 Private Water Hedge Sales | G2: W-Transact (0211) - Soft | H2: $ | I2: 1473589
A3: Financial Actual | B3: Revenue | C3: Kootha | D3: 41487 | E3: =MONTH(D3) -> 8 | F3: 001 Private Water Hedge Sales | G3: W-Transact (0211) - Soft | H3: $ | I3: 1419296.1
A4: Financial Actual | B4: Revenue | C4: Kootha | D4: 41518 | E4: =MONTH(D4) -> 9 | F4: 001 Private Water Hedge Sales | G4: W-Transact (0211) - Soft | H4: $ | I4: 1310673.2
A5: Financial Actual | B5: Revenue | C5: Kootha | D5: 41548 | E5: =MONTH(D5) -> 10 | F5: 001 Private Water Hedge Sales | G5: W-Transact (0211) - Soft | H5: $ | I5: 1301024.7
A6: Financial Actual | B6: Revenue | C6: Kootha | D6: 41579 | E6: =MONTH(D6) -> 11 | F6: 001 Private Water Hedge Sales | G6: W-Transact (0211) - Soft | H6: $ | I6: 1373822.9
A7: Financial Actual | B7: Revenue | C7: Kootha | D7: 41609 | E7: =MONTH(D7) -> 12 | F7: 001 Private Water Hedge Sales | G7: W-Transact (0211) - Soft | H7: $ | I7: 1340623
A8: Financial Actual | B8: Revenue | C8: Kootha | D8: 41640 | E8: =MONTH(D8) -> 1 | F8: 001 Private Water Hedge Sales | G8: W-Transact (0211) - Soft | H8: $ | I8: 1948962.6
A9: Financial Actual | B9: Revenue | C9: Kootha | D9: 41671 | E9: =MONTH(D9) -> 2 | F9: 001 Private Water Hedge Sales | G9: W-Transact (0211) - Soft | H9: $ | I9: 1725161.7
A10: Financial Actual | B10: Revenue | C10: Kootha | D10: 41699 | E10: =MONTH(D10) -> 3 | F10: 001 Private Water Hedge Sales | G10: W-Transact (0211) - Soft | H10: $ | I10: 1818208.6
A11: Financial Actual | B11: Revenue | C11: Kootha | D11: 41730 | E11: =MONTH(D11) -> 4 | F11: 001 Private Water Hedge Sales | G11: W-Transact (0211) - Soft | H11: $ | I11: 1328501.7
A12: Financial Actual | B12: Revenue | C12: Kootha | D12: 41760 | E12: =MONTH(D12) -> 5 | F12: 001 Private Water Hedge Sales | G12: W-Transact (0211) - Soft | H12: $ | I12: 1344117.3
A13: Financial Actual | B13: Revenue | C13: Kootha | D13: 41791 | E13: =MONTH(D13) -> 6 | F13: 001 Private Water Hedge Sales | G13: W-Transact (0211) - Soft | H13: $ | I13: 1291609.1
... A373: Financial Actual | B373: Expenses | C373: Surjek | D373: 41791 | E373: =MONTH(D373) -> 6 | F373: Labour Costs | G373: Labour-Costs (001) | H373: $ | I373: 1891504.3
A374: Financial Actual | B374: Expenses | C374: Jutik | D374: 41456 | E374: 7 | F374: Chemical Costs | G374: Chem-Exp (001) | H374: $ | I374: 1625596.3
A375: Financial Actual | B375: Expenses | C375: Jutik | D375: 41487 | E375: 8 | F375: Chemical Costs | G375: Chem-Exp (001) | H375: $ | I375: 1295067.8
A376: Financial Actual | B376: Expenses | C376: Jutik | D376: 41518 | E376: 9 | F376: Chemical Costs | G376: Chem-Exp (001) | H376: $ | I376: 1750624.9
A377: Financial Actual | B377: Expenses | C377: Jutik | D377: 41548 | E377: 10 | F377: Chemical Costs | G377: Chem-Exp (001) | H377: $ | I377: 1472529.4
A378: Financial Actual | B378: Expenses | C378: Jutik | D378: 41579 | E378: 11 | F378: Chemical Costs | G378: Chem-Exp (001) | H378: $ | I378: 1252200.5
A379: Financial Actual | B379: Expenses | C379: Jutik | D379: 41609 | E379: 12 | F379: Chemical Costs | G379: Chem-Exp (001) | H379: $ | I379: 1406782.7
A380: Financial Actual | B380: Expenses | C380: Jutik | D380: 41640 | E380: 1 | F380: Chemical Costs | G380: Chem-Exp (001) | H380: $ | I380: 1877449.5
A381: Financial Actual | B381: Expenses | C381: Jutik | D381: 41671 | E381: 2 | F381: Chemical Costs | G381: Chem-Exp (001) | H381: $ | I381: 1912219.2
A382: Financial Actual | B382: Expenses | C382: Jutik | D382: 41699 | E382: 3 | F382: Chemical Costs | G382: Chem-Exp (001) | H382: $ | I382: 2266625.2
A383: Financial Actual | B383: Expenses | C383: Jutik | D383: 41730 | E383: 4 | F383: Chemical Costs | G383: Chem-Exp (001) | H383: $ | I383: 2234200.6
A384: Financial Actual | B384: Expenses | C384: Jutik | D384: 41760 | E384: 5 | F384: Chemical Costs | G384: Chem-Exp (001) | H384: $ | I384: 2593715.6
A385: Financial Actual | B385: Expenses | C385: Jutik | D385: 41791 | E385: 6 | F385: Chemical Costs | G385: Chem-Exp (001) | H385: $ | I385: 2274807.8
... A505: Water Production Actuals | B505: None | C505: Jutik | D505: 41791 | E505: 6 | F505: None | G505: None | H505: Giga-Litre | I505: 220.38033

Sheet Revenue Analysis
A1: Revenue Analysis - Part I
A2: In Financial Data Analysis, Revenue Analysis speaks primarily to understanding which product(s) generate the most revenues and whether we can identify any aspect of seasonality towards these trends or not.
A3: The importance of this is that we are able to clearly understand which product(s) generate the most revenues and least revenues and this forms the first part of our puzzle.
A4: If a product generates a lot of revenues, but the expenses are greater than the revenues - this isn't a good news story.
A5: However, if the product generates a lot of revenues, and the expenses are well below the revenues - we may have a product which is performing well.
A6: Let's take a look at how Southern Water Corps Revenue Analysis looks like by calculating the Revenues for each of the products and asking ourselves - what does the data tell us?
A7: Let's get started!
A8: Q1. For each of the three Southern Water Corp. Desalination Plants, they produce desalinated water which is then consumed via private, public or residential usage. Please calculate the monthly revenues for Kootha, Surjek and Jutik and put this in the table below.
A9: Hint: You'll be utilizing the SUMIFS function here to assist you with the exercise. Remember the Syntax follows: =SUMIFS(Sum_Range, Criteria_Range_1, Criteria…)
A10: Unit | B10: Value Driver | C10: Accounting Code Centre | D10: Accounting Code Centre Element | E10: 41456 | F10: 41487 | G10: 41518 | H10: 41548 | I10: 41579 | J10: 41609 | K10: 41640 | L10: 41671 | M10: 41699 | N10: 41730 | O10: 41760 | P10: 41791
Q11: Total
A12: Kootha | B12: Revenue | C12: 001 Private Water Hedge Sales | D12: W-Transact (0211) - Soft | E12: =SUMIFS('Data Repository Table'!$I:$I,'Data Repository Table'!$C:$C,'Revenue Analysis'!$A12,'Data Repository Table'!$B:$B,'Revenue Analysis'!$B12,'Data Repository Table'!$F:$F,'Revenue Analysis'!$C12,'Data Repository Table'!$G:$G,'Revenue Analysis'!$D12,'Data Repository Table'!$D:$D,'Revenue Analysis'!E$10) -> 1473589 | F12: =SUMIFS('Data Repository Table'!$I:$I,'Data Repository Table'!$C:$C,'Revenue Analysis'!$A12,'Data Repository Table'!$B:$B,'Revenue Analysis'!$B12,'Data Repository Table'!$F:$F,'Revenue Analysis'!$C12,'Data Repository Table'!$G:$G,'Revenue Analysis'!$D12,'Data Repository Table'!$D:$D,'Revenue Analysis'!F$10) -> 1419296.1 | G12: =SUMIFS('Data Repository Table'!$I:$I,'Data Repository Table'!$C:$C,'Revenue Analysis'!$A12,'Data Repository Table'!$B:$B,'Revenue Analysis'!$B12,'Data Repository Table'!$F:$F,'Revenue Analysis'!$C12,'Data Repository Table'!$G:$G,'Revenue Analysis'!$D12,'Data Repository Table'!$D:$D,'Revenue Analysis'!G$10) -> 1310673.2 | H12: =SUMIFS('Data Repository Table'!$I:$I,'Data Repository Table'!$C:$C,'Revenue Analysis'!$A12,'Data Repository Table'!$B:$B,'Revenue Analysis'!$B12,'Data Repository Table'!$F:$F,'Revenue Analysis'!$C12,'Data Repository Table'!$G:$G,'Revenue Analysis'!$D12,'Data Repository Table'!$D:$D,'Revenue Analysis'!H$10) -> 1301024.7 | I12: =SUMIFS('Data Repository Table'!$I:$I,'Data Repository Table'!$C:$C,'Revenue Analysis'!$A12,'Data Repository Table'!$B:$B,'Revenue Analysis'!$B12,'Data Repository Table'!$F:$F,'Revenue Analysis'!$C12,'Data Repository Table'!$G:$G,'Revenue Analysis'!$D12,'Data Repository Table'!$D:$D,'Revenue Analysis'!I$10) -> 1373822.9 | J12: =SUMIFS('Data Repository Table'!$I:$I,'Data Repository Table'!$C:$C,'Revenue Analysis'!$A12,'Data Repository Table'!$B:$B,'Revenue Analysis'!$B12,'Data Repository Table'!$F:$F,'Revenue Analysis'!$C12,'Data Repository Table'!$G:$G,'Revenue Analysis'!$D12,'Data Repository Table'!$D:$D,'Revenue Analysis'!J$10) -> 1340623 | K12: =SUMIFS('Data Repository Table'!$I:$I,'Data Repository Table'!$C:$C,'Revenue Analysis'!$A12,'Data Repository Table'!$B:$B,'Revenue Analysis'!$B12,'Data Repository Table'!$F:$F,'Revenue Analysis'!$C12,'Data Repository Table'!$G:$G,'Revenue Analysis'!$D12,'Data Repository Table'!$D:$D,'Revenue Analysis'!K$10) -> 1948962.6 | L12: =SUMIFS('Data Repository Table'!$I:$I,'Data Repository Table'!$C:$C,'Revenue Analysis'!$A12,'Data Repository Table'!$B:$B,'Revenue Analysis'!$B12,'Data Repository Table'!$F:$F,'Revenue Analysis'!$C12,'Data Repository Table'!$G:$G,'Revenue Analysis'!$D12,'Data Repository Table'!$D:$D,'Revenue Analysis'!L$10) -> 1725161.7 | ... P12: =SUMIFS('Data Repository Table'!$I:$I,'Data Repository Table'!$C:$C,'Revenue Analysis'!$A12,'Data Repository Table'!$B:$B,'Revenue Analysis'!$B12,'Data Repository Table'!$F:$F,'Revenue Analysis'!$C12,'Data Repository Table'!$G:$G,'Revenue Analysis'!$D12,'Data Repository Table'!$D:$D,'Revenue Analysis'!P$10) -> 1291609.1 | Q12: =SUM(E12:P12) -> 17675590
A13: Kootha | B13: Revenue | C13: 001 Private Water Hedge Sales | D13: W-Transact (0212) - Hard | E13: =SUMIFS('Data Repository Table'!$I:$I,'Data Repository Table'!$C:$C,'Revenue Analysis'!$A13,'Data Repository Table'!$B:$B,'Revenue Analysis'!$B13,'Data Repository Table'!$F:$F,'Revenue Analysis'!$C13,'Data Repository Table'!$G:$G,'Revenue Analysis'!$D13,'Data Repository Table'!$D:$D,'Revenue Analysis'!E$10) -> 1620948 | F13: =SUMIFS('Data Repository Table'!$I:$I,'Data Repository Table'!$C:$C,'Revenue Analysis'!$A13,'Data Repository Table'!$B:$B,'Revenue Analysis'!$B13,'Data Repository Table'!$F:$F,'Revenue Analysis'!$C13,'Data Repository Table'!$G:$G,'Revenue Analysis'!$D13,'Data Repository Table'!$D:$D,'Revenue Analysis'!F$10) -> 1561225.7 | G13: =SUMIFS('Data Repository Table'!$I:$I,'Data Repository Table'!$C:$C,'Revenue Analysis'!$A13,'Data Repository Table'!$B:$B,'Revenue Analysis'!$B13,'Data Repository Table'!$F:$F,'Revenue Analysis'!$C13,'Data Repository Table'!$G:$G,'Revenue Analysis'!$D13,'Data Repository Table'!$D:$D,'Revenue Analysis'!G$10) -> 1441740.5 | H13: =SUMIFS('Data Repository Table'!$I:$I,'Data Repository Table'!$C:$C,'Revenue Analysis'!$A13,'Data Repository Table'!$B:$B,'Revenue Analysis'!$B13,'Data Repository Table'!$F:$F,'Revenue Analysis'!$C13,'Data Repository Table'!$G:$G,'Revenue Analysis'!$D13,'Data Repository Table'!$D:$D,'Revenue Analysis'!H$10) -> 1431127.2 | I13: =SUMIFS('Data Repository Table'!$I:$I,'Data Repository Table'!$C:$C,'Revenue Analysis'!$A13,'Data Repository Table'!$B:$B,'Revenue Analysis'!$B13,'Data Repository Table'!$F:$F,'Revenue Analysis'!$C13,'Data Repository Table'!$G:$G,'Revenue Analysis'!$D13,'Data Repository Table'!$D:$D,'Revenue Analysis'!I$10) -> 1511205.1 | J13: =SUMIFS('Data Repository Table'!$I:$I,'Data Repository Table'!$C:$C,'Revenue Analysis'!$A13,'Data Repository Table'!$B:$B,'Revenue Analysis'!$B13,'Data Repository Table'!$F:$F,'Revenue Analysis'!$C13,'Data Repository Table'!$G:$G,'Revenue Analysis'!$D13,'Data Repository Table'!$D:$D,'Revenue Analysis'!J$10) -> 1474685.3 | K13: =SUMIFS('Data Repository Table'!$I:$I,'Data Repository Table'!$C:$C,'Revenue Analysis'!$A13,'Data Repository Table'!$B:$B,'Revenue Analysis'!$B13,'Data Repository Table'!$F:$F,'Revenue Analysis'!$C13,'Data Repository Table'!$G:$G,'Revenue Analysis'!$D13,'Data Repository Table'!$D:$D,'Revenue Analysis'!K$10) -> 2143858.8 | L13: =SUMIFS('Data Repository Table'!$I:$I,'Data Repository Table'!$C:$C,'Revenue Analysis'!$A13,'Data Repository Table'!$B:$B,'Revenue Analysis'!$B13,'Data Repository Table'!$F:$F,'Revenue Analysis'!$C13,'Data Repository Table'!$G:$G,'Revenue Analysis'!$D13,'Data Repository Table'!$D:$D,'Revenue Analysis'!L$10) -> 1897677.9 | ... P13: =SUMIFS('Data Repository Table'!$I:$I,'Data Repository Table'!$C:$C,'Revenue Analysis'!$A13,'Data Repository Table'!$B:$B,'Revenue Analysis'!$B13,'Data Repository Table'!$F:$F,'Revenue Analysis'!$C13,'Data Repository Table'!$G:$G,'Revenue Analysis'!$D13,'Data Repository Table'!$D:$D,'Revenue Analysis'!P$10) -> 1420770 | Q13: =SUM(E13:P13) -> 19443149
A14: Kootha | B14: Revenue | C14: 002 Public Sales | D14: W-Transact (0211) - Soft | E14: =SUMIFS('Data Repository Table'!$I:$I,'Data Repository Table'!$C:$C,'Revenue Analysis'!$A14,'Data Repository Table'!$B:$B,'Revenue Analysis'!$B14,'Data Repository Table'!$F:$F,'Revenue Analysis'!$C14,'Data Repository Table'!$G:$G,'Revenue Analysis'!$D14,'Data Repository Table'!$D:$D,'Revenue Analysis'!E$10) -> 567331.78 | F14: =SUMIFS('Data Repository Table'!$I:$I,'Data Repository Table'!$C:$C,'Revenue Analysis'!$A14,'Data Repository Table'!$B:$B,'Revenue Analysis'!$B14,'Data Repository Table'!$F:$F,'Revenue Analysis'!$C14,'Data Repository Table'!$G:$G,'Revenue Analysis'!$D14,'Data Repository Table'!$D:$D,'Revenue Analysis'!F$10) -> 546429 | G14: =SUMIFS('Data Repository Table'!$I:$I,'Data Repository Table'!$C:$C,'Revenue Analysis'!$A14,'Data Repository Table'!$B:$B,'Revenue Analysis'!$B14,'Data Repository Table'!$F:$F,'Revenue Analysis'!$C14,'Data Repository Table'!$G:$G,'Revenue Analysis'!$D14,'Data Repository Table'!$D:$D,'Revenue Analysis'!G$10) -> 504609.19 | H14: =SUMIFS('Data Repository Table'!$I:$I,'Data Repository Table'!$C:$C,'Revenue Analysis'!$A14,'Data Repository Table'!$B:$B,'Revenue Analysis'!$B14,'Data Repository Table'!$F:$F,'Revenue Analysis'!$C14,'Data Repository Table'!$G:$G,'Revenue Analysis'!$D14,'Data Repository Table'!$D:$D,'Revenue Analysis'!H$10) -> 500894.52 | I14: =SUMIFS('Data Repository Table'!$I:$I,'Data Repository Table'!$C:$C,'Revenue Analysis'!$A14,'Data Repository Table'!$B:$B,'Revenue Analysis'!$B14,'Data Repository Table'!$F:$F,'Revenue Analysis'!$C14,'Data Repository Table'!$G:$G,'Revenue Analysis'!$D14,'Data Repository Table'!$D:$D,'Revenue Analysis'!I$10) -> 528921.8 | J14: =SUMIFS('Data Repository Table'!$I:$I,'Data Repository Table'!$C:$C,'Revenue Analysis'!$A14,'Data Repository Table'!$B:$B,'Revenue Analysis'!$B14,'Data Repository Table'!$F:$F,'Revenue Analysis'!$C14,'Data Repository Table'!$G:$G,'Revenue Analysis'!$D14,'Data Repository Table'!$D:$D,'Revenue Analysis'!J$10) -> 516139.87 | K14: =SUMIFS('Data Repository Table'!$I:$I,'Data Repository Table'!$C:$C,'Revenue Analysis'!$A14,'Data Repository Table'!$B:$B,'Revenue Analysis'!$B14,'Data Repository Table'!$F:$F,'Revenue Analysis'!$C14,'Data Repository Table'!$G:$G,'Revenue Analysis'!$D14,'Data Repository Table'!$D:$D,'Revenue Analysis'!K$10) -> 750350.58 | L14: =SUMIFS('Data Repository Table'!$I:$I,'Data Repository Table'!$C:$C,'Revenue Analysis'!$A14,'Data Repository Table'!$B:$B,'Revenue Analysis'!$B14,'Data Repository Table'!$F:$F,'Revenue Analysis'!$C14,'Data Repository Table'!$G:$G,'Revenue Analysis'!$D14,'Data Repository Table'!$D:$D,'Revenue Analysis'!L$10) -> 664187.25 | ... P14: =SUMIFS('Data Repository Table'!$I:$I,'Data Repository Table'!$C:$C,'Revenue Analysis'!$A14,'Data Repository Table'!$B:$B,'Revenue Analysis'!$B14,'Data Repository Table'!$F:$F,'Revenue Analysis'!$C14,'Data Repository Table'!$G:$G,'Revenue Analysis'!$D14,'Data Repository Table'!$D:$D,'Revenue Analysis'!P$10) -> 497269.52 | Q14: =SUM(E14:P14) -> 6805102.1
A15: Kootha | B15: Revenue | C15: 002 Public Sales | D15: W-Transact (0212) - Hard | E15: =SUMIFS('Data Repository Table'!$I:$I,'Data Repository Table'!$C:$C,'Revenue Analysis'!$A15,'Data Repository Table'!$B:$B,'Revenue Analysis'!$B15,'Data Repository Table'!$F:$F,'Revenue Analysis'!$C15,'Data Repository Table'!$G:$G,'Revenue Analysis'!$D15,'Data Repository Table'!$D:$D,'Revenue Analysis'!E$10) -> 955954.05 | F15: =SUMIFS('Data Repository Table'!$I:$I,'Data Repository Table'!$C:$C,'Revenue Analysis'!$A15,'Data Repository Table'!$B:$B,'Revenue Analysis'!$B15,'Data Repository Table'!$F:$F,'Revenue Analysis'!$C15,'Data Repository Table'!$G:$G,'Revenue Analysis'!$D15,'Data Repository Table'!$D:$D,'Revenue Analysis'!F$10) -> 920732.86 | G15: =SUMIFS('Data Repository Table'!$I:$I,'Data Repository Table'!$C:$C,'Revenue Analysis'!$A15,'Data Repository Table'!$B:$B,'Revenue Analysis'!$B15,'Data Repository Table'!$F:$F,'Revenue Analysis'!$C15,'Data Repository Table'!$G:$G,'Revenue Analysis'!$D15,'Data Repository Table'!$D:$D,'Revenue Analysis'!G$10) -> 850266.48 | H15: =SUMIFS('Data Repository Table'!$I:$I,'Data Repository Table'!$C:$C,'Revenue Analysis'!$A15,'Data Repository Table'!$B:$B,'Revenue Analysis'!$B15,'Data Repository Table'!$F:$F,'Revenue Analysis'!$C15,'Data Repository Table'!$G:$G,'Revenue Analysis'!$D15,'Data Repository Table'!$D:$D,'Revenue Analysis'!H$10) -> 844007.27 | I15: =SUMIFS('Data Repository Table'!$I:$I,'Data Repository Table'!$C:$C,'Revenue Analysis'!$A15,'Data Repository Table'!$B:$B,'Revenue Analysis'!$B15,'Data Repository Table'!$F:$F,'Revenue Analysis'!$C15,'Data Repository Table'!$G:$G,'Revenue Analysis'!$D15,'Data Repository Table'!$D:$D,'Revenue Analysis'!I$10) -> 891233.24 | J15: =SUMIFS('Data Repository Table'!$I:$I,'Data Repository Table'!$C:$C,'Revenue Analysis'!$A15,'Data Repository Table'!$B:$B,'Revenue Analysis'!$B15,'Data Repository Table'!$F:$F,'Revenue Analysis'!$C15,'Data Repository Table'!$G:$G,'Revenue Analysis'!$D15,'Data Repository Table'!$D:$D,'Revenue Analysis'!J$10) -> 869695.68 | K15: =SUMIFS('Data Repository Table'!$I:$I,'Data Repository Table'!$C:$C,'Revenue Analysis'!$A15,'Data Repository Table'!$B:$B,'Revenue Analysis'!$B15,'Data Repository Table'!$F:$F,'Revenue Analysis'!$C15,'Data Repository Table'!$G:$G,'Revenue Analysis'!$D15,'Data Repository Table'!$D:$D,'Revenue Analysis'!K$10) -> 1264340.7 | L15: =SUMIFS('Data Repository Table'!$I:$I,'Data Repository Table'!$C:$C,'Revenue Analysis'!$A15,'Data Repository Table'!$B:$B,'Revenue Analysis'!$B15,'Data Repository Table'!$F:$F,'Revenue Analysis'!$C15,'Data Repository Table'!$G:$G,'Revenue Analysis'!$D15,'Data Repository Table'!$D:$D,'Revenue Analysis'!L$10) -> 1119155.5 | ... P15: =SUMIFS('Data Repository Table'!$I:$I,'Data Repository Table'!$C:$C,'Revenue Analysis'!$A15,'Data Repository Table'!$B:$B,'Revenue Analysis'!$B15,'Data Repository Table'!$F:$F,'Revenue Analysis'!$C15,'Data Repository Table'!$G:$G,'Revenue Analysis'!$D15,'Data Repository Table'!$D:$D,'Revenue Analysis'!P$10) -> 837899.14 | Q15: =SUM(E15:P15) -> 11466597
A16: Kootha | B16: Revenue | C16: 003 Residential Sales | D16: W-Transact (0211) - Soft | E16: =SUMIFS('Data Repository Table'!$I:$I,'Data Repository Table'!$C:$C,'Revenue Analysis'!$A16,'Data Repository Table'!$B:$B,'Revenue Analysis'!$B16,'Data Repository Table'!$F:$F,'Revenue Analysis'!$C16,'Data Repository Table'!$G:$G,'Revenue Analysis'!$D16,'Data Repository Table'!$D:$D,'Revenue Analysis'!E$10) -> 1296758.4 | F16: =SUMIFS('Data Repository Table'!$I:$I,'Data Repository Table'!$C:$C,'Revenue Analysis'!$A16,'Data Repository Table'!$B:$B,'Revenue Analysis'!$B16,'Data Repository Table'!$F:$F,'Revenue Analysis'!$C16,'Data Repository Table'!$G:$G,'Revenue Analysis'!$D16,'Data Repository Table'!$D:$D,'Revenue Analysis'!F$10) -> 1248980.6 | G16: =SUMIFS('Data Repository Table'!$I:$I,'Data Repository Table'!$C:$C,'Revenue Analysis'!$A16,'Data Repository Table'!$B:$B,'Revenue Analysis'!$B16,'Data Repository Table'!$F:$F,'Revenue Analysis'!$C16,'Data Repository Table'!$G:$G,'Revenue Analysis'!$D16,'Data Repository Table'!$D:$D,'Revenue Analysis'!G$10) -> 1153392.4 | H16: =SUMIFS('Data Repository Table'!$I:$I,'Data Repository Table'!$C:$C,'Revenue Analysis'!$A16,'Data Repository Table'!$B:$B,'Revenue Analysis'!$B16,'Data Repository Table'!$F:$F,'Revenue Analysis'!$C16,'Data Repository Table'!$G:$G,'Revenue Analysis'!$D16,'Data Repository Table'!$D:$D,'Revenue Analysis'!H$10) -> 1144901.8 | I16: =SUMIFS('Data Repository Table'!$I:$I,'Data Repository Table'!$C:$C,'Revenue Analysis'!$A16,'Data Repository Table'!$B:$B,'Revenue Analysis'!$B16,'Data Repository Table'!$F:$F,'Revenue Analysis'!$C16,'Data Repository Table'!$G:$G,'Revenue Analysis'!$D16,'Data Repository Table'!$D:$D,'Revenue Analysis'!I$10) -> 1208964.1 | J16: =SUMIFS('Data Repository Table'!$I:$I,'Data Repository Table'!$C:$C,'Revenue Analysis'!$A16,'Data Repository Table'!$B:$B,'Revenue Analysis'!$B16,'Data Repository Table'!$F:$F,'Revenue Analysis'!$C16,'Data Repository Table'!$G:$G,'Revenue Analysis'!$D16,'Data Repository Table'!$D:$D,'Revenue Analysis'!J$10) -> 1179748.3 | K16: =SUMIFS('Data Repository Table'!$I:$I,'Data Repository Table'!$C:$C,'Revenue Analysis'!$A16,'Data Repository Table'!$B:$B,'Revenue Analysis'!$B16,'Data Repository Table'!$F:$F,'Revenue Analysis'!$C16,'Data Repository Table'!$G:$G,'Revenue Analysis'!$D16,'Data Repository Table'!$D:$D,'Revenue Analysis'!K$10) -> 1715087 | L16: =SUMIFS('Data Repository Table'!$I:$I,'Data Repository Table'!$C:$C,'Revenue Analysis'!$A16,'Data Repository Table'!$B:$B,'Revenue Analysis'!$B16,'Data Repository Table'!$F:$F,'Revenue Analysis'!$C16,'Data Repository Table'!$G:$G,'Revenue Analysis'!$D16,'Data Repository Table'!$D:$D,'Revenue Analysis'!L$10) -> 1518142.3 | ... P16: =SUMIFS('Data Repository Table'!$I:$I,'Data Repository Table'!$C:$C,'Revenue Analysis'!$A16,'Data Repository Table'!$B:$B,'Revenue Analysis'!$B16,'Data Repository Table'!$F:$F,'Revenue Analysis'!$C16,'Data Repository Table'!$G:$G,'Revenue Analysis'!$D16,'Data Repository Table'!$D:$D,'Revenue Analysis'!P$10) -> 1136616 | Q16: =SUM(E16:P16) -> 15554519
A18: Surjek | B18: Revenue | C18: 001 Private Water Hedge Sales | D18: W-Transact (0211) - Soft | E18: =SUMIFS('Data Repository Table'!$I:$I,'Data Repository Table'!$C:$C,'Revenue Analysis'!$A18,'Data Repository Table'!$B:$B,'Revenue Analysis'!$B18,'Data Repository Table'!$F:$F,'Revenue Analysis'!$C18,'Data Repository Table'!$G:$G,'Revenue Analysis'!$D18,'Data Repository Table'!$D:$D,'Revenue Analysis'!E$10) -> 2406673.7 | F18: =SUMIFS('Data Repository Table'!$I:$I,'Data Repository Table'!$C:$C,'Revenue Analysis'!$A18,'Data Repository Table'!$B:$B,'Revenue Analysis'!$B18,'Data Repository Table'!$F:$F,'Revenue Analysis'!$C18,'Data Repository Table'!$G:$G,'Revenue Analysis'!$D18,'Data Repository Table'!$D:$D,'Revenue Analysis'!F$10) -> 2028377 | G18: =SUMIFS('Data Repository Table'!$I:$I,'Data Repository Table'!$C:$C,'Revenue Analysis'!$A18,'Data Repository Table'!$B:$B,'Revenue Analysis'!$B18,'Data Repository Table'!$F:$F,'Revenue Analysis'!$C18,'Data Repository Table'!$G:$G,'Revenue Analysis'!$D18,'Data Repository Table'!$D:$D,'Revenue Analysis'!G$10) -> 2241097.2 | H18: =SUMIFS('Data Repository Table'!$I:$I,'Data Repository Table'!$C:$C,'Revenue Analysis'!$A18,'Data Repository Table'!$B:$B,'Revenue Analysis'!$B18,'Data Repository Table'!$F:$F,'Revenue Analysis'!$C18,'Data Repository Table'!$G:$G,'Revenue Analysis'!$D18,'Data Repository Table'!$D:$D,'Revenue Analysis'!H$10) -> 2104393.5 | I18: =SUMIFS('Data Repository Table'!$I:$I,'Data Repository Table'!$C:$C,'Revenue Analysis'!$A18,'Data Repository Table'!$B:$B,'Revenue Analysis'!$B18,'Data Repository Table'!$F:$F,'Revenue Analysis'!$C18,'Data Repository Table'!$G:$G,'Revenue Analysis'!$D18,'Data Repository Table'!$D:$D,'Revenue Analysis'!I$10) -> 1921236.2 | J18: =SUMIFS('Data Repository Table'!$I:$I,'Data Repository Table'!$C:$C,'Revenue Analysis'!$A18,'Data Repository Table'!$B:$B,'Revenue Analysis'!$B18,'Data Repository Table'!$F:$F,'Revenue Analysis'!$C18,'Data Repository Table'!$G:$G,'Revenue Analysis'!$D18,'Data Repository Table'!$D:$D,'Revenue Analysis'!J$10) -> 2161522.2 | K18: =SUMIFS('Data Repository Table'!$I:$I,'Data Repository Table'!$C:$C,'Revenue Analysis'!$A18,'Data Repository Table'!$B:$B,'Revenue Analysis'!$B18,'Data Repository Table'!$F:$F,'Revenue Analysis'!$C18,'Data Repository Table'!$G:$G,'Revenue Analysis'!$D18,'Data Repository Table'!$D:$D,'Revenue Analysis'!K$10) -> 3104730.2 | L18: =SUMIFS('Data Repository Table'!$I:$I,'Data Repository Table'!$C:$C,'Revenue Analysis'!$A18,'Data Repository Table'!$B:$B,'Revenue Analysis'!$B18,'Data Repository Table'!$F:$F,'Revenue Analysis'!$C18,'Data Repository Table'!$G:$G,'Revenue Analysis'!$D18,'Data Repository Table'!$D:$D,'Revenue Analysis'!L$10) -> 2116798.7 | ... P18: =SUMIFS('Data Repository Table'!$I:$I,'Data Repository Table'!$C:$C,'Revenue Analysis'!$A18,'Data Repository Table'!$B:$B,'Revenue Analysis'!$B18,'Data Repository Table'!$F:$F,'Revenue Analysis'!$C18,'Data Repository Table'!$G:$G,'Revenue Analysis'!$D18,'Data Repository Table'!$D:$D,'Revenue Analysis'!P$10) -> 2245023.2 | Q18: =SUM(E18:P18) -> 27349354
A19: Surjek | B19: Revenue | C19: 001 Private Water Hedge Sales | D19: W-Transact (0212) - Hard | E19: =SUMIFS('Data Repository Table'!$I:$I,'Data Repository Table'!$C:$C,'Revenue Analysis'!$A19,'Data Repository Table'!$B:$B,'Revenue Analysis'!$B19,'Data Repository Table'!$F:$F,'Revenue Analysis'!$C19,'Data Repository Table'!$G:$G,'Revenue Analysis'!$D19,'Data Repository Table'!$D:$D,'Revenue Analysis'!E$10) -> 4813347.5 | F19: =SUMIFS('Data Repository Table'!$I:$I,'Data Repository Table'!$C:$C,'Revenue Analysis'!$A19,'Data Repository Table'!$B:$B,'Revenue Analysis'!$B19,'Data Repository Table'!$F:$F,'Revenue Analysis'!$C19,'Data Repository Table'!$G:$G,'Revenue Analysis'!$D19,'Data Repository Table'!$D:$D,'Revenue Analysis'!F$10) -> 4056754 | G19: =SUMIFS('Data Repository Table'!$I:$I,'Data Repository Table'!$C:$C,'Revenue Analysis'!$A19,'Data Repository Table'!$B:$B,'Revenue Analysis'!$B19,'Data Repository Table'!$F:$F,'Revenue Analysis'!$C19,'Data Repository Table'!$G:$G,'Revenue Analysis'!$D19,'Data Repository Table'!$D:$D,'Revenue Analysis'!G$10) -> 4482194.5 | H19: =SUMIFS('Data Repository Table'!$I:$I,'Data Repository Table'!$C:$C,'Revenue Analysis'!$A19,'Data Repository Table'!$B:$B,'Revenue Analysis'!$B19,'Data Repository Table'!$F:$F,'Revenue Analysis'!$C19,'Data Repository Table'!$G:$G,'Revenue Analysis'!$D19,'Data Repository Table'!$D:$D,'Revenue Analysis'!H$10) -> 4208787 | I19: =SUMIFS('Data Repository Table'!$I:$I,'Data Repository Table'!$C:$C,'Revenue Analysis'!$A19,'Data Repository Table'!$B:$B,'Revenue Analysis'!$B19,'Data Repository Table'!$F:$F,'Revenue Analysis'!$C19,'Data Repository Table'!$G:$G,'Revenue Analysis'!$D19,'Data Repository Table'!$D:$D,'Revenue Analysis'!I$10) -> 3842472.4 | J19: =SUMIFS('Data Repository Table'!$I:$I,'Data Repository Table'!$C:$C,'Revenue Analysis'!$A19,'Data Repository Table'!$B:$B,'Revenue Analysis'!$B19,'Data Repository Table'!$F:$F,'Revenue Analysis'!$C19,'Data Repository Table'!$G:$G,'Revenue Analysis'!$D19,'Data Repository Table'!$D:$D,'Revenue Analysis'!J$10) -> 4323044.3 | K19: =SUMIFS('Data Repository Table'!$I:$I,'Data Repository Table'!$C:$C,'Revenue Analysis'!$A19,'Data Repository Table'!$B:$B,'Revenue Analysis'!$B19,'Data Repository Table'!$F:$F,'Revenue Analysis'!$C19,'Data Repository Table'!$G:$G,'Revenue Analysis'!$D19,'Data Repository Table'!$D:$D,'Revenue Analysis'!K$10) -> 6209460.5 | L19: =SUMIFS('Data Repository Table'!$I:$I,'Data Repository Table'!$C:$C,'Revenue Analysis'!$A19,'Data Repository Table'!$B:$B,'Revenue Analysis'!$B19,'Data Repository Table'!$F:$F,'Revenue Analysis'!$C19,'Data Repository Table'!$G:$G,'Revenue Analysis'!$D19,'Data Repository Table'!$D:$D,'Revenue Analysis'!L$10) -> 4633597.4 | ... P19: =SUMIFS('Data Repository Table'!$I:$I,'Data Repository Table'!$C:$C,'Revenue Analysis'!$A19,'Data Repository Table'!$B:$B,'Revenue Analysis'!$B19,'Data Repository Table'!$F:$F,'Revenue Analysis'!$C19,'Data Repository Table'!$G:$G,'Revenue Analysis'!$D19,'Data Repository Table'!$D:$D,'Revenue Analysis'!P$10) -> 4490046.5 | Q19: =SUM(E19:P19) -> 55098708
A20: Surjek | B20: Revenue | C20: 002 Public Sales | D20: W-Transact (0211) - Soft | E20: =SUMIFS('Data Repository Table'!$I:$I,'Data Repository Table'!$C:$C,'Revenue Analysis'!$A20,'Data Repository Table'!$B:$B,'Revenue Analysis'!$B20,'Data Repository Table'!$F:$F,'Revenue Analysis'!$C20,'Data Repository Table'!$G:$G,'Revenue Analysis'!$D20,'Data Repository Table'!$D:$D,'Revenue Analysis'!E$10) -> 2117872.9 | F20: =SUMIFS('Data Repository Table'!$I:$I,'Data Repository Table'!$C:$C,'Revenue Analysis'!$A20,'Data Repository Table'!$B:$B,'Revenue Analysis'!$B20,'Data Repository Table'!$F:$F,'Revenue Analysis'!$C20,'Data Repository Table'!$G:$G,'Revenue Analysis'!$D20,'Data Repository Table'!$D:$D,'Revenue Analysis'!F$10) -> 1784971.8 | G20: =SUMIFS('Data Repository Table'!$I:$I,'Data Repository Table'!$C:$C,'Revenue Analysis'!$A20,'Data Repository Table'!$B:$B,'Revenue Analysis'!$B20,'Data Repository Table'!$F:$F,'Revenue Analysis'!$C20,'Data Repository Table'!$G:$G,'Revenue Analysis'!$D20,'Data Repository Table'!$D:$D,'Revenue Analysis'!G$10) -> 1972165.6 | H20: =SUMIFS('Data Repository Table'!$I:$I,'Data Repository Table'!$C:$C,'Revenue Analysis'!$A20,'Data Repository Table'!$B:$B,'Revenue Analysis'!$B20,'Data Repository Table'!$F:$F,'Revenue Analysis'!$C20,'Data Repository Table'!$G:$G,'Revenue Analysis'!$D20,'Data Repository Table'!$D:$D,'Revenue Analysis'!H$10) -> 1851866.3 | I20: =SUMIFS('Data Repository Table'!$I:$I,'Data Repository Table'!$C:$C,'Revenue Analysis'!$A20,'Data Repository Table'!$B:$B,'Revenue Analysis'!$B20,'Data Repository Table'!$F:$F,'Revenue Analysis'!$C20,'Data Repository Table'!$G:$G,'Revenue Analysis'!$D20,'Data Repository Table'!$D:$D,'Revenue Analysis'!I$10) -> 1690687.9 | J20: =SUMIFS('Data Repository Table'!$I:$I,'Data Repository Table'!$C:$C,'Revenue Analysis'!$A20,'Data Repository Table'!$B:$B,'Revenue Analysis'!$B20,'Data Repository Table'!$F:$F,'Revenue Analysis'!$C20,'Data Repository Table'!$G:$G,'Revenue Analysis'!$D20,'Data Repository Table'!$D:$D,'Revenue Analysis'!J$10) -> 1902139.5 | K20: =SUMIFS('Data Repository Table'!$I:$I,'Data Repository Table'!$C:$C,'Revenue Analysis'!$A20,'Data Repository Table'!$B:$B,'Revenue Analysis'!$B20,'Data Repository Table'!$F:$F,'Revenue Analysis'!$C20,'Data Repository Table'!$G:$G,'Revenue Analysis'!$D20,'Data Repository Table'!$D:$D,'Revenue Analysis'!K$10) -> 2732162.6 | L20: =SUMIFS('Data Repository Table'!$I:$I,'Data Repository Table'!$C:$C,'Revenue Analysis'!$A20,'Data Repository Table'!$B:$B,'Revenue Analysis'!$B20,'Data Repository Table'!$F:$F,'Revenue Analysis'!$C20,'Data Repository Table'!$G:$G,'Revenue Analysis'!$D20,'Data Repository Table'!$D:$D,'Revenue Analysis'!L$10) -> 2478782.9 | ... P20: =SUMIFS('Data Repository Table'!$I:$I,'Data Repository Table'!$C:$C,'Revenue Analysis'!$A20,'Data Repository Table'!$B:$B,'Revenue Analysis'!$B20,'Data Repository Table'!$F:$F,'Revenue Analysis'!$C20,'Data Repository Table'!$G:$G,'Revenue Analysis'!$D20,'Data Repository Table'!$D:$D,'Revenue Analysis'!P$10) -> 1975620.4 | Q20: =SUM(E20:P20) -> 24683432
A21: Surjek | B21: Revenue | C21: 002 Public Sales | D21: W-Transact (0212) - Hard | E21: =SUMIFS('Data Repository Table'!$I:$I,'Data Repository Table'!$C:$C,'Revenue Analysis'!$A21,'Data Repository Table'!$B:$B,'Revenue Analysis'!$B21,'Data Repository Table'!$F:$F,'Revenue Analysis'!$C21,'Data Repository Table'!$G:$G,'Revenue Analysis'!$D21,'Data Repository Table'!$D:$D,'Revenue Analysis'!E$10) -> 3850678 | F21: =SUMIFS('Data Repository Table'!$I:$I,'Data Repository Table'!$C:$C,'Revenue Analysis'!$A21,'Data Repository Table'!$B:$B,'Revenue Analysis'!$B21,'Data Repository Table'!$F:$F,'Revenue Analysis'!$C21,'Data Repository Table'!$G:$G,'Revenue Analysis'!$D21,'Data Repository Table'!$D:$D,'Revenue Analysis'!F$10) -> 3245403.2 | G21: =SUMIFS('Data Repository Table'!$I:$I,'Data Repository Table'!$C:$C,'Revenue Analysis'!$A21,'Data Repository Table'!$B:$B,'Revenue Analysis'!$B21,'Data Repository Table'!$F:$F,'Revenue Analysis'!$C21,'Data Repository Table'!$G:$G,'Revenue Analysis'!$D21,'Data Repository Table'!$D:$D,'Revenue Analysis'!G$10) -> 3585755.6 | H21: =SUMIFS('Data Repository Table'!$I:$I,'Data Repository Table'!$C:$C,'Revenue Analysis'!$A21,'Data Repository Table'!$B:$B,'Revenue Analysis'!$B21,'Data Repository Table'!$F:$F,'Revenue Analysis'!$C21,'Data Repository Table'!$G:$G,'Revenue Analysis'!$D21,'Data Repository Table'!$D:$D,'Revenue Analysis'!H$10) -> 3367029.6 | I21: =SUMIFS('Data Repository Table'!$I:$I,'Data Repository Table'!$C:$C,'Revenue Analysis'!$A21,'Data Repository Table'!$B:$B,'Revenue Analysis'!$B21,'Data Repository Table'!$F:$F,'Revenue Analysis'!$C21,'Data Repository Table'!$G:$G,'Revenue Analysis'!$D21,'Data Repository Table'!$D:$D,'Revenue Analysis'!I$10) -> 3073978 | J21: =SUMIFS('Data Repository Table'!$I:$I,'Data Repository Table'!$C:$C,'Revenue Analysis'!$A21,'Data Repository Table'!$B:$B,'Revenue Analysis'!$B21,'Data Repository Table'!$F:$F,'Revenue Analysis'!$C21,'Data Repository Table'!$G:$G,'Revenue Analysis'!$D21,'Data Repository Table'!$D:$D,'Revenue Analysis'!J$10) -> 3458435.5 | K21: =SUMIFS('Data Repository Table'!$I:$I,'Data Repository Table'!$C:$C,'Revenue Analysis'!$A21,'Data Repository Table'!$B:$B,'Revenue Analysis'!$B21,'Data Repository Table'!$F:$F,'Revenue Analysis'!$C21,'Data Repository Table'!$G:$G,'Revenue Analysis'!$D21,'Data Repository Table'!$D:$D,'Revenue Analysis'!K$10) -> 4967568.4 | L21: =SUMIFS('Data Repository Table'!$I:$I,'Data Repository Table'!$C:$C,'Revenue Analysis'!$A21,'Data Repository Table'!$B:$B,'Revenue Analysis'!$B21,'Data Repository Table'!$F:$F,'Revenue Analysis'!$C21,'Data Repository Table'!$G:$G,'Revenue Analysis'!$D21,'Data Repository Table'!$D:$D,'Revenue Analysis'!L$10) -> 4506877.9 | ... P21: =SUMIFS('Data Repository Table'!$I:$I,'Data Repository Table'!$C:$C,'Revenue Analysis'!$A21,'Data Repository Table'!$B:$B,'Revenue Analysis'!$B21,'Data Repository Table'!$F:$F,'Revenue Analysis'!$C21,'Data Repository Table'!$G:$G,'Revenue Analysis'!$D21,'Data Repository Table'!$D:$D,'Revenue Analysis'!P$10) -> 3592037.2 | Q21: =SUM(E21:P21) -> 45878966
A22: Surjek | B22: Revenue | C22: 003 Residential Sales | D22: W-Transact (0211) - Soft | E22: =SUMIFS('Data Repository Table'!$I:$I,'Data Repository Table'!$C:$C,'Revenue Analysis'!$A22,'Data Repository Table'!$B:$B,'Revenue Analysis'!$B22,'Data Repository Table'!$F:$F,'Revenue Analysis'!$C22,'Data Repository Table'!$G:$G,'Revenue Analysis'!$D22,'Data Repository Table'!$D:$D,'Revenue Analysis'!E$10) -> 4139478.8 | F22: =SUMIFS('Data Repository Table'!$I:$I,'Data Repository Table'!$C:$C,'Revenue Analysis'!$A22,'Data Repository Table'!$B:$B,'Revenue Analysis'!$B22,'Data Repository Table'!$F:$F,'Revenue Analysis'!$C22,'Data Repository Table'!$G:$G,'Revenue Analysis'!$D22,'Data Repository Table'!$D:$D,'Revenue Analysis'!F$10) -> 3488808.4 | G22: =SUMIFS('Data Repository Table'!$I:$I,'Data Repository Table'!$C:$C,'Revenue Analysis'!$A22,'Data Repository Table'!$B:$B,'Revenue Analysis'!$B22,'Data Repository Table'!$F:$F,'Revenue Analysis'!$C22,'Data Repository Table'!$G:$G,'Revenue Analysis'!$D22,'Data Repository Table'!$D:$D,'Revenue Analysis'!G$10) -> 3854687.3 | H22: =SUMIFS('Data Repository Table'!$I:$I,'Data Repository Table'!$C:$C,'Revenue Analysis'!$A22,'Data Repository Table'!$B:$B,'Revenue Analysis'!$B22,'Data Repository Table'!$F:$F,'Revenue Analysis'!$C22,'Data Repository Table'!$G:$G,'Revenue Analysis'!$D22,'Data Repository Table'!$D:$D,'Revenue Analysis'!H$10) -> 3619556.8 | I22: =SUMIFS('Data Repository Table'!$I:$I,'Data Repository Table'!$C:$C,'Revenue Analysis'!$A22,'Data Repository Table'!$B:$B,'Revenue Analysis'!$B22,'Data Repository Table'!$F:$F,'Revenue Analysis'!$C22,'Data Repository Table'!$G:$G,'Revenue Analysis'!$D22,'Data Repository Table'!$D:$D,'Revenue Analysis'!I$10) -> 3304526.3 | J22: =SUMIFS('Data Repository Table'!$I:$I,'Data Repository Table'!$C:$C,'Revenue Analysis'!$A22,'Data Repository Table'!$B:$B,'Revenue Analysis'!$B22,'Data Repository Table'!$F:$F,'Revenue Analysis'!$C22,'Data Repository Table'!$G:$G,'Revenue Analysis'!$D22,'Data Repository Table'!$D:$D,'Revenue Analysis'!J$10) -> 3717818.1 | K22: =SUMIFS('Data Repository Table'!$I:$I,'Data Repository Table'!$C:$C,'Revenue Analysis'!$A22,'Data Repository Table'!$B:$B,'Revenue Analysis'!$B22,'Data Repository Table'!$F:$F,'Revenue Analysis'!$C22,'Data Repository Table'!$G:$G,'Revenue Analysis'!$D22,'Data Repository Table'!$D:$D,'Revenue Analysis'!K$10) -> 5340136 | L22: =SUMIFS('Data Repository Table'!$I:$I,'Data Repository Table'!$C:$C,'Revenue Analysis'!$A22,'Data Repository Table'!$B:$B,'Revenue Analysis'!$B22,'Data Repository Table'!$F:$F,'Revenue Analysis'!$C22,'Data Repository Table'!$G:$G,'Revenue Analysis'!$D22,'Data Repository Table'!$D:$D,'Revenue Analysis'!L$10) -> 4844893.8 | ... P22: =SUMIFS('Data Repository Table'!$I:$I,'Data Repository Table'!$C:$C,'Revenue Analysis'!$A22,'Data Repository Table'!$B:$B,'Revenue Analysis'!$B22,'Data Repository Table'!$F:$F,'Revenue Analysis'!$C22,'Data Repository Table'!$G:$G,'Revenue Analysis'!$D22,'Data Repository Table'!$D:$D,'Revenue Analysis'!P$10) -> 3861440 | Q22: =SUM(E22:P22) -> 49244889
A24: Jutik | B24: Revenue | C24: 001 Private Water Hedge Sales | D24: W-Transact (0211) - Soft | E24: =SUMIFS('Data Repository Table'!$I:$I,'Data Repository Table'!$C:$C,'Revenue Analysis'!$A24,'Data Repository Table'!$B:$B,'Revenue Analysis'!$B24,'Data Repository Table'!$F:$F,'Revenue Analysis'!$C24,'Data Repository Table'!$G:$G,'Revenue Analysis'!$D24,'Data Repository Table'!$D:$D,'Revenue Analysis'!E$10) -> 1766228.7 | F24: =SUMIFS('Data Repository Table'!$I:$I,'Data Repository Table'!$C:$C,'Revenue Analysis'!$A24,'Data Repository Table'!$B:$B,'Revenue Analysis'!$B24,'Data Repository Table'!$F:$F,'Revenue Analysis'!$C24,'Data Repository Table'!$G:$G,'Revenue Analysis'!$D24,'Data Repository Table'!$D:$D,'Revenue Analysis'!F$10) -> 1951422.8 | G24: =SUMIFS('Data Repository Table'!$I:$I,'Data Repository Table'!$C:$C,'Revenue Analysis'!$A24,'Data Repository Table'!$B:$B,'Revenue Analysis'!$B24,'Data Repository Table'!$F:$F,'Revenue Analysis'!$C24,'Data Repository Table'!$G:$G,'Revenue Analysis'!$D24,'Data Repository Table'!$D:$D,'Revenue Analysis'!G$10) -> 1699371.2 | H24: =SUMIFS('Data Repository Table'!$I:$I,'Data Repository Table'!$C:$C,'Revenue Analysis'!$A24,'Data Repository Table'!$B:$B,'Revenue Analysis'!$B24,'Data Repository Table'!$F:$F,'Revenue Analysis'!$C24,'Data Repository Table'!$G:$G,'Revenue Analysis'!$D24,'Data Repository Table'!$D:$D,'Revenue Analysis'!H$10) -> 1502189.2 | I24: =SUMIFS('Data Repository Table'!$I:$I,'Data Repository Table'!$C:$C,'Revenue Analysis'!$A24,'Data Repository Table'!$B:$B,'Revenue Analysis'!$B24,'Data Repository Table'!$F:$F,'Revenue Analysis'!$C24,'Data Repository Table'!$G:$G,'Revenue Analysis'!$D24,'Data Repository Table'!$D:$D,'Revenue Analysis'!I$10) -> 1650239.5 | J24: =SUMIFS('Data Repository Table'!$I:$I,'Data Repository Table'!$C:$C,'Revenue Analysis'!$A24,'Data Repository Table'!$B:$B,'Revenue Analysis'!$B24,'Data Repository Table'!$F:$F,'Revenue Analysis'!$C24,'Data Repository Table'!$G:$G,'Revenue Analysis'!$D24,'Data Repository Table'!$D:$D,'Revenue Analysis'!J$10) -> 1406546.1 | K24: =SUMIFS('Data Repository Table'!$I:$I,'Data Repository Table'!$C:$C,'Revenue Analysis'!$A24,'Data Repository Table'!$B:$B,'Revenue Analysis'!$B24,'Data Repository Table'!$F:$F,'Revenue Analysis'!$C24,'Data Repository Table'!$G:$G,'Revenue Analysis'!$D24,'Data Repository Table'!$D:$D,'Revenue Analysis'!K$10) -> 2151540.2 | L24: =SUMIFS('Data Repository Table'!$I:$I,'Data Repository Table'!$C:$C,'Revenue Analysis'!$A24,'Data Repository Table'!$B:$B,'Revenue Analysis'!$B24,'Data Repository Table'!$F:$F,'Revenue Analysis'!$C24,'Data Repository Table'!$G:$G,'Revenue Analysis'!$D24,'Data Repository Table'!$D:$D,'Revenue Analysis'!L$10) -> 2191228.2 | ... P24: =SUMIFS('Data Repository Table'!$I:$I,'Data Repository Table'!$C:$C,'Revenue Analysis'!$A24,'Data Repository Table'!$B:$B,'Revenue Analysis'!$B24,'Data Repository Table'!$F:$F,'Revenue Analysis'!$C24,'Data Repository Table'!$G:$G,'Revenue Analysis'!$D24,'Data Repository Table'!$D:$D,'Revenue Analysis'!P$10) -> 2197266.9 | Q24: =SUM(E24:P24) -> 22620170
A25: Jutik | B25: Revenue | C25: 001 Private Water Hedge Sales | D25: W-Transact (0212) - Hard | E25: =SUMIFS('Data Repository Table'!$I:$I,'Data Repository Table'!$C:$C,'Revenue Analysis'!$A25,'Data Repository Table'!$B:$B,'Revenue Analysis'!$B25,'Data Repository Table'!$F:$F,'Revenue Analysis'!$C25,'Data Repository Table'!$G:$G,'Revenue Analysis'!$D25,'Data Repository Table'!$D:$D,'Revenue Analysis'!E$10) -> 3532457.4 | F25: =SUMIFS('Data Repository Table'!$I:$I,'Data Repository Table'!$C:$C,'Revenue Analysis'!$A25,'Data Repository Table'!$B:$B,'Revenue Analysis'!$B25,'Data Repository Table'!$F:$F,'Revenue Analysis'!$C25,'Data Repository Table'!$G:$G,'Revenue Analysis'!$D25,'Data Repository Table'!$D:$D,'Revenue Analysis'!F$10) -> 3902845.5 | G25: =SUMIFS('Data Repository Table'!$I:$I,'Data Repository Table'!$C:$C,'Revenue Analysis'!$A25,'Data Repository Table'!$B:$B,'Revenue Analysis'!$B25,'Data Repository Table'!$F:$F,'Revenue Analysis'!$C25,'Data Repository Table'!$G:$G,'Revenue Analysis'!$D25,'Data Repository Table'!$D:$D,'Revenue Analysis'!G$10) -> 3398742.5 | H25: =SUMIFS('Data Repository Table'!$I:$I,'Data Repository Table'!$C:$C,'Revenue Analysis'!$A25,'Data Repository Table'!$B:$B,'Revenue Analysis'!$B25,'Data Repository Table'!$F:$F,'Revenue Analysis'!$C25,'Data Repository Table'!$G:$G,'Revenue Analysis'!$D25,'Data Repository Table'!$D:$D,'Revenue Analysis'!H$10) -> 3004378.4 | I25: =SUMIFS('Data Repository Table'!$I:$I,'Data Repository Table'!$C:$C,'Revenue Analysis'!$A25,'Data Repository Table'!$B:$B,'Revenue Analysis'!$B25,'Data Repository Table'!$F:$F,'Revenue Analysis'!$C25,'Data Repository Table'!$G:$G,'Revenue Analysis'!$D25,'Data Repository Table'!$D:$D,'Revenue Analysis'!I$10) -> 3300479 | J25: =SUMIFS('Data Repository Table'!$I:$I,'Data Repository Table'!$C:$C,'Revenue Analysis'!$A25,'Data Repository Table'!$B:$B,'Revenue Analysis'!$B25,'Data Repository Table'!$F:$F,'Revenue Analysis'!$C25,'Data Repository Table'!$G:$G,'Revenue Analysis'!$D25,'Data Repository Table'!$D:$D,'Revenue Analysis'!J$10) -> 2813092.2 | K25: =SUMIFS('Data Repository Table'!$I:$I,'Data Repository Table'!$C:$C,'Revenue Analysis'!$A25,'Data Repository Table'!$B:$B,'Revenue Analysis'!$B25,'Data Repository Table'!$F:$F,'Revenue Analysis'!$C25,'Data Repository Table'!$G:$G,'Revenue Analysis'!$D25,'Data Repository Table'!$D:$D,'Revenue Analysis'!K$10) -> 4303080.4 | L25: =SUMIFS('Data Repository Table'!$I:$I,'Data Repository Table'!$C:$C,'Revenue Analysis'!$A25,'Data Repository Table'!$B:$B,'Revenue Analysis'!$B25,'Data Repository Table'!$F:$F,'Revenue Analysis'!$C25,'Data Repository Table'!$G:$G,'Revenue Analysis'!$D25,'Data Repository Table'!$D:$D,'Revenue Analysis'!L$10) -> 4382456.5 | ... P25: =SUMIFS('Data Repository Table'!$I:$I,'Data Repository Table'!$C:$C,'Revenue Analysis'!$A25,'Data Repository Table'!$B:$B,'Revenue Analysis'!$B25,'Data Repository Table'!$F:$F,'Revenue Analysis'!$C25,'Data Repository Table'!$G:$G,'Revenue Analysis'!$D25,'Data Repository Table'!$D:$D,'Revenue Analysis'!P$10) -> 4394533.8 | Q25: =SUM(E25:P25) -> 45240340
... A28: Jutik | B28: Revenue | C28: 003 Residential Sales | D28: W-Transact (0211) - Soft | E28: =SUMIFS('Data Repository Table'!$I:$I,'Data Repository Table'!$C:$C,'Revenue Analysis'!$A28,'Data Repository Table'!$B:$B,'Revenue Analysis'!$B28,'Data Repository Table'!$F:$F,'Revenue Analysis'!$C28,'Data Repository Table'!$G:$G,'Revenue Analysis'!$D28,'Data Repository Table'!$D:$D,'Revenue Analysis'!E$10) -> 3037913.4 | F28: =SUMIFS('Data Repository Table'!$I:$I,'Data Repository Table'!$C:$C,'Revenue Analysis'!$A28,'Data Repository Table'!$B:$B,'Revenue Analysis'!$B28,'Data Repository Table'!$F:$F,'Revenue Analysis'!$C28,'Data Repository Table'!$G:$G,'Revenue Analysis'!$D28,'Data Repository Table'!$D:$D,'Revenue Analysis'!F$10) -> 3356447.1 | G28: =SUMIFS('Data Repository Table'!$I:$I,'Data Repository Table'!$C:$C,'Revenue Analysis'!$A28,'Data Repository Table'!$B:$B,'Revenue Analysis'!$B28,'Data Repository Table'!$F:$F,'Revenue Analysis'!$C28,'Data Repository Table'!$G:$G,'Revenue Analysis'!$D28,'Data Repository Table'!$D:$D,'Revenue Analysis'!G$10) -> 2922918.5 | H28: =SUMIFS('Data Repository Table'!$I:$I,'Data Repository Table'!$C:$C,'Revenue Analysis'!$A28,'Data Repository Table'!$B:$B,'Revenue Analysis'!$B28,'Data Repository Table'!$F:$F,'Revenue Analysis'!$C28,'Data Repository Table'!$G:$G,'Revenue Analysis'!$D28,'Data Repository Table'!$D:$D,'Revenue Analysis'!H$10) -> 2583765.4 | I28: =SUMIFS('Data Repository Table'!$I:$I,'Data Repository Table'!$C:$C,'Revenue Analysis'!$A28,'Data Repository Table'!$B:$B,'Revenue Analysis'!$B28,'Data Repository Table'!$F:$F,'Revenue Analysis'!$C28,'Data Repository Table'!$G:$G,'Revenue Analysis'!$D28,'Data Repository Table'!$D:$D,'Revenue Analysis'!I$10) -> 2838412 | J28: =SUMIFS('Data Repository Table'!$I:$I,'Data Repository Table'!$C:$C,'Revenue Analysis'!$A28,'Data Repository Table'!$B:$B,'Revenue Analysis'!$B28,'Data Repository Table'!$F:$F,'Revenue Analysis'!$C28,'Data Repository Table'!$G:$G,'Revenue Analysis'!$D28,'Data Repository Table'!$D:$D,'Revenue Analysis'!J$10) -> 2419259.3 | K28: =SUMIFS('Data Repository Table'!$I:$I,'Data Repository Table'!$C:$C,'Revenue Analysis'!$A28,'Data Repository Table'!$B:$B,'Revenue Analysis'!$B28,'Data Repository Table'!$F:$F,'Revenue Analysis'!$C28,'Data Repository Table'!$G:$G,'Revenue Analysis'!$D28,'Data Repository Table'!$D:$D,'Revenue Analysis'!K$10) -> 3700649.1 | L28: =SUMIFS('Data Repository Table'!$I:$I,'Data Repository Table'!$C:$C,'Revenue Analysis'!$A28,'Data Repository Table'!$B:$B,'Revenue Analysis'!$B28,'Data Repository Table'!$F:$F,'Revenue Analysis'!$C28,'Data Repository Table'!$G:$G,'Revenue Analysis'!$D28,'Data Repository Table'!$D:$D,'Revenue Analysis'!L$10) -> 3768912.5 | ... P28: =SUMIFS('Data Repository Table'!$I:$I,'Data Repository Table'!$C:$C,'Revenue Analysis'!$A28,'Data Repository Table'!$B:$B,'Revenue Analysis'!$B28,'Data Repository Table'!$F:$F,'Revenue Analysis'!$C28,'Data Repository Table'!$G:$G,'Revenue Analysis'!$D28,'Data Repository Table'!$D:$D,'Revenue Analysis'!P$10) -> 3079299.1 | Q28: =SUM(E28:P28) -> 37706693
A30: You've now calculated the Revenues for each of the three desalination plants (Kootha, Surjek and Jutik). This has given you a micro-view of the trends, but let's take a look at the macro-revenue trends and view all this information aggregated together. In the next question, you're aggregating the revenues at the Accounting Code Centre Level, where in the previous question, we went all the way to the Accounting Code Centre Element Level.
A31: Q2. Just as you did for Q1 above, calculate the monthly revenues for Kootha, Surjek and Jutik at the Accounting Code Centre Level and put this in the table below.
A32: Unit | B32: Value Driver | C32: Accounting Code Centre | E32: 41456 | F32: 41487 | G32: 41518 | H32: 41548 | I32: 41579 | J32: 41609 | K32: 41640 | L32: 41671 | M32: 41699 | N32: 41730 | O32: 41760 | P32: 41791
Q33: Total
A34: Kootha | B34: Revenue | C34: 001 Private Water Hedge Sales | E34: =SUMIFS('Data Repository Table'!$I:$I,'Data Repository Table'!$C:$C,'Revenue Analysis'!$A34,'Data Repository Table'!$B:$B,'Revenue Analysis'!$B34,'Data Repository Table'!$F:$F,'Revenue Analysis'!$C34,'Data Repository Table'!$D:$D,'Revenue Analysis'!E$32) -> 3094537 | F34: =SUMIFS('Data Repository Table'!$I:$I,'Data Repository Table'!$C:$C,'Revenue Analysis'!$A34,'Data Repository Table'!$B:$B,'Revenue Analysis'!$B34,'Data Repository Table'!$F:$F,'Revenue Analysis'!$C34,'Data Repository Table'!$D:$D,'Revenue Analysis'!F$32) -> 2980521.8 | G34: =SUMIFS('Data Repository Table'!$I:$I,'Data Repository Table'!$C:$C,'Revenue Analysis'!$A34,'Data Repository Table'!$B:$B,'Revenue Analysis'!$B34,'Data Repository Table'!$F:$F,'Revenue Analysis'!$C34,'Data Repository Table'!$D:$D,'Revenue Analysis'!G$32) -> 2752413.7 | H34: =SUMIFS('Data Repository Table'!$I:$I,'Data Repository Table'!$C:$C,'Revenue Analysis'!$A34,'Data Repository Table'!$B:$B,'Revenue Analysis'!$B34,'Data Repository Table'!$F:$F,'Revenue Analysis'!$C34,'Data Repository Table'!$D:$D,'Revenue Analysis'!H$32) -> 2732151.9 | I34: =SUMIFS('Data Repository Table'!$I:$I,'Data Repository Table'!$C:$C,'Revenue Analysis'!$A34,'Data Repository Table'!$B:$B,'Revenue Analysis'!$B34,'Data Repository Table'!$F:$F,'Revenue Analysis'!$C34,'Data Repository Table'!$D:$D,'Revenue Analysis'!I$32) -> 2885028 | J34: =SUMIFS('Data Repository Table'!$I:$I,'Data Repository Table'!$C:$C,'Revenue Analysis'!$A34,'Data Repository Table'!$B:$B,'Revenue Analysis'!$B34,'Data Repository Table'!$F:$F,'Revenue Analysis'!$C34,'Data Repository Table'!$D:$D,'Revenue Analysis'!J$32) -> 2815308.4 | K34: =SUMIFS('Data Repository Table'!$I:$I,'Data Repository Table'!$C:$C,'Revenue Analysis'!$A34,'Data Repository Table'!$B:$B,'Revenue Analysis'!$B34,'Data Repository Table'!$F:$F,'Revenue Analysis'!$C34,'Data Repository Table'!$D:$D,'Revenue Analysis'!K$32) -> 4092821.4 | L34: =SUMIFS('Data Repository Table'!$I:$I,'Data Repository Table'!$C:$C,'Revenue Analysis'!$A34,'Data Repository Table'!$B:$B,'Revenue Analysis'!$B34,'Data Repository Table'!$F:$F,'Revenue Analysis'!$C34,'Data Repository Table'!$D:$D,'Revenue Analysis'!L$32) -> 3622839.6 | ... P34: =SUMIFS('Data Repository Table'!$I:$I,'Data Repository Table'!$C:$C,'Revenue Analysis'!$A34,'Data Repository Table'!$B:$B,'Revenue Analysis'!$B34,'Data Repository Table'!$F:$F,'Revenue Analysis'!$C34,'Data Repository Table'!$D:$D,'Revenue Analysis'!P$32) -> 2712379.2 | Q34: =SUM(E34:P34) -> 37118739
A35: Kootha | B35: Revenue | C35: 002 Public Sales | E35: =SUMIFS('Data Repository Table'!$I:$I,'Data Repository Table'!$C:$C,'Revenue Analysis'!$A35,'Data Repository Table'!$B:$B,'Revenue Analysis'!$B35,'Data Repository Table'!$F:$F,'Revenue Analysis'!$C35,'Data Repository Table'!$D:$D,'Revenue Analysis'!E$32) -> 1523285.8 | F35: =SUMIFS('Data Repository Table'!$I:$I,'Data Repository Table'!$C:$C,'Revenue Analysis'!$A35,'Data Repository Table'!$B:$B,'Revenue Analysis'!$B35,'Data Repository Table'!$F:$F,'Revenue Analysis'!$C35,'Data Repository Table'!$D:$D,'Revenue Analysis'!F$32) -> 1467161.9 | G35: =SUMIFS('Data Repository Table'!$I:$I,'Data Repository Table'!$C:$C,'Revenue Analysis'!$A35,'Data Repository Table'!$B:$B,'Revenue Analysis'!$B35,'Data Repository Table'!$F:$F,'Revenue Analysis'!$C35,'Data Repository Table'!$D:$D,'Revenue Analysis'!G$32) -> 1354875.7 | H35: =SUMIFS('Data Repository Table'!$I:$I,'Data Repository Table'!$C:$C,'Revenue Analysis'!$A35,'Data Repository Table'!$B:$B,'Revenue Analysis'!$B35,'Data Repository Table'!$F:$F,'Revenue Analysis'!$C35,'Data Repository Table'!$D:$D,'Revenue Analysis'!H$32) -> 1344901.8 | I35: =SUMIFS('Data Repository Table'!$I:$I,'Data Repository Table'!$C:$C,'Revenue Analysis'!$A35,'Data Repository Table'!$B:$B,'Revenue Analysis'!$B35,'Data Repository Table'!$F:$F,'Revenue Analysis'!$C35,'Data Repository Table'!$D:$D,'Revenue Analysis'!I$32) -> 1420155 | J35: =SUMIFS('Data Repository Table'!$I:$I,'Data Repository Table'!$C:$C,'Revenue Analysis'!$A35,'Data Repository Table'!$B:$B,'Revenue Analysis'!$B35,'Data Repository Table'!$F:$F,'Revenue Analysis'!$C35,'Data Repository Table'!$D:$D,'Revenue Analysis'!J$32) -> 1385835.5 | K35: =SUMIFS('Data Repository Table'!$I:$I,'Data Repository Table'!$C:$C,'Revenue Analysis'!$A35,'Data Repository Table'!$B:$B,'Revenue Analysis'!$B35,'Data Repository Table'!$F:$F,'Revenue Analysis'!$C35,'Data Repository Table'!$D:$D,'Revenue Analysis'!K$32) -> 2014691.3 | L35: =SUMIFS('Data Repository Table'!$I:$I,'Data Repository Table'!$C:$C,'Revenue Analysis'!$A35,'Data Repository Table'!$B:$B,'Revenue Analysis'!$B35,'Data Repository Table'!$F:$F,'Revenue Analysis'!$C35,'Data Repository Table'!$D:$D,'Revenue Analysis'!L$32) -> 1783342.8 | ... P35: =SUMIFS('Data Repository Table'!$I:$I,'Data Repository Table'!$C:$C,'Revenue Analysis'!$A35,'Data Repository Table'!$B:$B,'Revenue Analysis'!$B35,'Data Repository Table'!$F:$F,'Revenue Analysis'!$C35,'Data Repository Table'!$D:$D,'Revenue Analysis'!P$32) -> 1335168.7 | Q35: =SUM(E35:P35) -> 18271699
A36: Kootha | B36: Revenue | C36: 003 Residential Sales | E36: =SUMIFS('Data Repository Table'!$I:$I,'Data Repository Table'!$C:$C,'Revenue Analysis'!$A36,'Data Repository Table'!$B:$B,'Revenue Analysis'!$B36,'Data Repository Table'!$F:$F,'Revenue Analysis'!$C36,'Data Repository Table'!$D:$D,'Revenue Analysis'!E$32) -> 1296758.4 | F36: =SUMIFS('Data Repository Table'!$I:$I,'Data Repository Table'!$C:$C,'Revenue Analysis'!$A36,'Data Repository Table'!$B:$B,'Revenue Analysis'!$B36,'Data Repository Table'!$F:$F,'Revenue Analysis'!$C36,'Data Repository Table'!$D:$D,'Revenue Analysis'!F$32) -> 1248980.6 | G36: =SUMIFS('Data Repository Table'!$I:$I,'Data Repository Table'!$C:$C,'Revenue Analysis'!$A36,'Data Repository Table'!$B:$B,'Revenue Analysis'!$B36,'Data Repository Table'!$F:$F,'Revenue Analysis'!$C36,'Data Repository Table'!$D:$D,'Revenue Analysis'!G$32) -> 1153392.4 | H36: =SUMIFS('Data Repository Table'!$I:$I,'Data Repository Table'!$C:$C,'Revenue Analysis'!$A36,'Data Repository Table'!$B:$B,'Revenue Analysis'!$B36,'Data Repository Table'!$F:$F,'Revenue Analysis'!$C36,'Data Repository Table'!$D:$D,'Revenue Analysis'!H$32) -> 1144901.8 | I36: =SUMIFS('Data Repository Table'!$I:$I,'Data Repository Table'!$C:$C,'Revenue Analysis'!$A36,'Data Repository Table'!$B:$B,'Revenue Analysis'!$B36,'Data Repository Table'!$F:$F,'Revenue Analysis'!$C36,'Data Repository Table'!$D:$D,'Revenue Analysis'!I$32) -> 1208964.1 | J36: =SUMIFS('Data Repository Table'!$I:$I,'Data Repository Table'!$C:$C,'Revenue Analysis'!$A36,'Data Repository Table'!$B:$B,'Revenue Analysis'!$B36,'Data Repository Table'!$F:$F,'Revenue Analysis'!$C36,'Data Repository Table'!$D:$D,'Revenue Analysis'!J$32) -> 1179748.3 | K36: =SUMIFS('Data Repository Table'!$I:$I,'Data Repository Table'!$C:$C,'Revenue Analysis'!$A36,'Data Repository Table'!$B:$B,'Revenue Analysis'!$B36,'Data Repository Table'!$F:$F,'Revenue Analysis'!$C36,'Data Repository Table'!$D:$D,'Revenue Analysis'!K$32) -> 1715087 | L36: =SUMIFS('Data Repository Table'!$I:$I,'Data Repository Table'!$C:$C,'Revenue Analysis'!$A36,'Data Repository Table'!$B:$B,'Revenue Analysis'!$B36,'Data Repository Table'!$F:$F,'Revenue Analysis'!$C36,'Data Repository Table'!$D:$D,'Revenue Analysis'!L$32) -> 1518142.3 | ... P36: =SUMIFS('Data Repository Table'!$I:$I,'Data Repository Table'!$C:$C,'Revenue Analysis'!$A36,'Data Repository Table'!$B:$B,'Revenue Analysis'!$B36,'Data Repository Table'!$F:$F,'Revenue Analysis'!$C36,'Data Repository Table'!$D:$D,'Revenue Analysis'!P$32) -> 1136616 | Q36: =SUM(E36:P36) -> 15554519
A37: Surjek | B37: Revenue | C37: 001 Private Water Hedge Sales | E37: =SUMIFS('Data Repository Table'!$I:$I,'Data Repository Table'!$C:$C,'Revenue Analysis'!$A37,'Data Repository Table'!$B:$B,'Revenue Analysis'!$B37,'Data Repository Table'!$F:$F,'Revenue Analysis'!$C37,'Data Repository Table'!$D:$D,'Revenue Analysis'!E$32) -> 7220021.2 | F37: =SUMIFS('Data Repository Table'!$I:$I,'Data Repository Table'!$C:$C,'Revenue Analysis'!$A37,'Data Repository Table'!$B:$B,'Revenue Analysis'!$B37,'Data Repository Table'!$F:$F,'Revenue Analysis'!$C37,'Data Repository Table'!$D:$D,'Revenue Analysis'!F$32) -> 6085131 | G37: =SUMIFS('Data Repository Table'!$I:$I,'Data Repository Table'!$C:$C,'Revenue Analysis'!$A37,'Data Repository Table'!$B:$B,'Revenue Analysis'!$B37,'Data Repository Table'!$F:$F,'Revenue Analysis'!$C37,'Data Repository Table'!$D:$D,'Revenue Analysis'!G$32) -> 6723291.7 | H37: =SUMIFS('Data Repository Table'!$I:$I,'Data Repository Table'!$C:$C,'Revenue Analysis'!$A37,'Data Repository Table'!$B:$B,'Revenue Analysis'!$B37,'Data Repository Table'!$F:$F,'Revenue Analysis'!$C37,'Data Repository Table'!$D:$D,'Revenue Analysis'!H$32) -> 6313180.5 | I37: =SUMIFS('Data Repository Table'!$I:$I,'Data Repository Table'!$C:$C,'Revenue Analysis'!$A37,'Data Repository Table'!$B:$B,'Revenue Analysis'!$B37,'Data Repository Table'!$F:$F,'Revenue Analysis'!$C37,'Data Repository Table'!$D:$D,'Revenue Analysis'!I$32) -> 5763708.7 | J37: =SUMIFS('Data Repository Table'!$I:$I,'Data Repository Table'!$C:$C,'Revenue Analysis'!$A37,'Data Repository Table'!$B:$B,'Revenue Analysis'!$B37,'Data Repository Table'!$F:$F,'Revenue Analysis'!$C37,'Data Repository Table'!$D:$D,'Revenue Analysis'!J$32) -> 6484566.5 | K37: =SUMIFS('Data Repository Table'!$I:$I,'Data Repository Table'!$C:$C,'Revenue Analysis'!$A37,'Data Repository Table'!$B:$B,'Revenue Analysis'!$B37,'Data Repository Table'!$F:$F,'Revenue Analysis'!$C37,'Data Repository Table'!$D:$D,'Revenue Analysis'!K$32) -> 9314190.7 | L37: =SUMIFS('Data Repository Table'!$I:$I,'Data Repository Table'!$C:$C,'Revenue Analysis'!$A37,'Data Repository Table'!$B:$B,'Revenue Analysis'!$B37,'Data Repository Table'!$F:$F,'Revenue Analysis'!$C37,'Data Repository Table'!$D:$D,'Revenue Analysis'!L$32) -> 6750396.1 | ... P37: =SUMIFS('Data Repository Table'!$I:$I,'Data Repository Table'!$C:$C,'Revenue Analysis'!$A37,'Data Repository Table'!$B:$B,'Revenue Analysis'!$B37,'Data Repository Table'!$F:$F,'Revenue Analysis'!$C37,'Data Repository Table'!$D:$D,'Revenue Analysis'!P$32) -> 6735069.7 | Q37: =SUM(E37:P37) -> 82448062
A38: Surjek | B38: Revenue | C38: 002 Public Sales | E38: =SUMIFS('Data Repository Table'!$I:$I,'Data Repository Table'!$C:$C,'Revenue Analysis'!$A38,'Data Repository Table'!$B:$B,'Revenue Analysis'!$B38,'Data Repository Table'!$F:$F,'Revenue Analysis'!$C38,'Data Repository Table'!$D:$D,'Revenue Analysis'!E$32) -> 5968550.9 | F38: =SUMIFS('Data Repository Table'!$I:$I,'Data Repository Table'!$C:$C,'Revenue Analysis'!$A38,'Data Repository Table'!$B:$B,'Revenue Analysis'!$B38,'Data Repository Table'!$F:$F,'Revenue Analysis'!$C38,'Data Repository Table'!$D:$D,'Revenue Analysis'!F$32) -> 5030375 | G38: =SUMIFS('Data Repository Table'!$I:$I,'Data Repository Table'!$C:$C,'Revenue Analysis'!$A38,'Data Repository Table'!$B:$B,'Revenue Analysis'!$B38,'Data Repository Table'!$F:$F,'Revenue Analysis'!$C38,'Data Repository Table'!$D:$D,'Revenue Analysis'!G$32) -> 5557921.2 | H38: =SUMIFS('Data Repository Table'!$I:$I,'Data Repository Table'!$C:$C,'Revenue Analysis'!$A38,'Data Repository Table'!$B:$B,'Revenue Analysis'!$B38,'Data Repository Table'!$F:$F,'Revenue Analysis'!$C38,'Data Repository Table'!$D:$D,'Revenue Analysis'!H$32) -> 5218895.9 | I38: =SUMIFS('Data Repository Table'!$I:$I,'Data Repository Table'!$C:$C,'Revenue Analysis'!$A38,'Data Repository Table'!$B:$B,'Revenue Analysis'!$B38,'Data Repository Table'!$F:$F,'Revenue Analysis'!$C38,'Data Repository Table'!$D:$D,'Revenue Analysis'!I$32) -> 4764665.8 | J38: =SUMIFS('Data Repository Table'!$I:$I,'Data Repository Table'!$C:$C,'Revenue Analysis'!$A38,'Data Repository Table'!$B:$B,'Revenue Analysis'!$B38,'Data Repository Table'!$F:$F,'Revenue Analysis'!$C38,'Data Repository Table'!$D:$D,'Revenue Analysis'!J$32) -> 5360575 | K38: =SUMIFS('Data Repository Table'!$I:$I,'Data Repository Table'!$C:$C,'Revenue Analysis'!$A38,'Data Repository Table'!$B:$B,'Revenue Analysis'!$B38,'Data Repository Table'!$F:$F,'Revenue Analysis'!$C38,'Data Repository Table'!$D:$D,'Revenue Analysis'!K$32) -> 7699731 | L38: =SUMIFS('Data Repository Table'!$I:$I,'Data Repository Table'!$C:$C,'Revenue Analysis'!$A38,'Data Repository Table'!$B:$B,'Revenue Analysis'!$B38,'Data Repository Table'!$F:$F,'Revenue Analysis'!$C38,'Data Repository Table'!$D:$D,'Revenue Analysis'!L$32) -> 6985660.8 | ... P38: =SUMIFS('Data Repository Table'!$I:$I,'Data Repository Table'!$C:$C,'Revenue Analysis'!$A38,'Data Repository Table'!$B:$B,'Revenue Analysis'!$B38,'Data Repository Table'!$F:$F,'Revenue Analysis'!$C38,'Data Repository Table'!$D:$D,'Revenue Analysis'!P$32) -> 5567657.6 | Q38: =SUM(E38:P38) -> 70562398
A39: Surjek | B39: Revenue | C39: 003 Residential Sales | E39: =SUMIFS('Data Repository Table'!$I:$I,'Data Repository Table'!$C:$C,'Revenue Analysis'!$A39,'Data Repository Table'!$B:$B,'Revenue Analysis'!$B39,'Data Repository Table'!$F:$F,'Revenue Analysis'!$C39,'Data Repository Table'!$D:$D,'Revenue Analysis'!E$32) -> 4139478.8 | F39: =SUMIFS('Data Repository Table'!$I:$I,'Data Repository Table'!$C:$C,'Revenue Analysis'!$A39,'Data Repository Table'!$B:$B,'Revenue Analysis'!$B39,'Data Repository Table'!$F:$F,'Revenue Analysis'!$C39,'Data Repository Table'!$D:$D,'Revenue Analysis'!F$32) -> 3488808.4 | G39: =SUMIFS('Data Repository Table'!$I:$I,'Data Repository Table'!$C:$C,'Revenue Analysis'!$A39,'Data Repository Table'!$B:$B,'Revenue Analysis'!$B39,'Data Repository Table'!$F:$F,'Revenue Analysis'!$C39,'Data Repository Table'!$D:$D,'Revenue Analysis'!G$32) -> 3854687.3 | H39: =SUMIFS('Data Repository Table'!$I:$I,'Data Repository Table'!$C:$C,'Revenue Analysis'!$A39,'Data Repository Table'!$B:$B,'Revenue Analysis'!$B39,'Data Repository Table'!$F:$F,'Revenue Analysis'!$C39,'Data Repository Table'!$D:$D,'Revenue Analysis'!H$32) -> 3619556.8 | I39: =SUMIFS('Data Repository Table'!$I:$I,'Data Repository Table'!$C:$C,'Revenue Analysis'!$A39,'Data Repository Table'!$B:$B,'Revenue Analysis'!$B39,'Data Repository Table'!$F:$F,'Revenue Analysis'!$C39,'Data Repository Table'!$D:$D,'Revenue Analysis'!I$32) -> 3304526.3 | J39: =SUMIFS('Data Repository Table'!$I:$I,'Data Repository Table'!$C:$C,'Revenue Analysis'!$A39,'Data Repository Table'!$B:$B,'Revenue Analysis'!$B39,'Data Repository Table'!$F:$F,'Revenue Analysis'!$C39,'Data Repository Table'!$D:$D,'Revenue Analysis'!J$32) -> 3717818.1 | K39: =SUMIFS('Data Repository Table'!$I:$I,'Data Repository Table'!$C:$C,'Revenue Analysis'!$A39,'Data Repository Table'!$B:$B,'Revenue Analysis'!$B39,'Data Repository Table'!$F:$F,'Revenue Analysis'!$C39,'Data Repository Table'!$D:$D,'Revenue Analysis'!K$32) -> 5340136 | L39: =SUMIFS('Data Repository Table'!$I:$I,'Data Repository Table'!$C:$C,'Revenue Analysis'!$A39,'Data Repository Table'!$B:$B,'Revenue Analysis'!$B39,'Data Repository Table'!$F:$F,'Revenue Analysis'!$C39,'Data Repository Table'!$D:$D,'Revenue Analysis'!L$32) -> 4844893.8 | ... P39: =SUMIFS('Data Repository Table'!$I:$I,'Data Repository Table'!$C:$C,'Revenue Analysis'!$A39,'Data Repository Table'!$B:$B,'Revenue Analysis'!$B39,'Data Repository Table'!$F:$F,'Revenue Analysis'!$C39,'Data Repository Table'!$D:$D,'Revenue Analysis'!P$32) -> 3861440 | Q39: =SUM(E39:P39) -> 49244889
A40: Jutik | B40: Revenue | C40: 001 Private Water Hedge Sales | E40: =SUMIFS('Data Repository Table'!$I:$I,'Data Repository Table'!$C:$C,'Revenue Analysis'!$A40,'Data Repository Table'!$B:$B,'Revenue Analysis'!$B40,'Data Repository Table'!$F:$F,'Revenue Analysis'!$C40,'Data Repository Table'!$D:$D,'Revenue Analysis'!E$32) -> 5298686.2 | F40: =SUMIFS('Data Repository Table'!$I:$I,'Data Repository Table'!$C:$C,'Revenue Analysis'!$A40,'Data Repository Table'!$B:$B,'Revenue Analysis'!$B40,'Data Repository Table'!$F:$F,'Revenue Analysis'!$C40,'Data Repository Table'!$D:$D,'Revenue Analysis'!F$32) -> 5854268.3 | G40: =SUMIFS('Data Repository Table'!$I:$I,'Data Repository Table'!$C:$C,'Revenue Analysis'!$A40,'Data Repository Table'!$B:$B,'Revenue Analysis'!$B40,'Data Repository Table'!$F:$F,'Revenue Analysis'!$C40,'Data Repository Table'!$D:$D,'Revenue Analysis'!G$32) -> 5098113.7 | H40: =SUMIFS('Data Repository Table'!$I:$I,'Data Repository Table'!$C:$C,'Revenue Analysis'!$A40,'Data Repository Table'!$B:$B,'Revenue Analysis'!$B40,'Data Repository Table'!$F:$F,'Revenue Analysis'!$C40,'Data Repository Table'!$D:$D,'Revenue Analysis'!H$32) -> 4506567.6 | I40: =SUMIFS('Data Repository Table'!$I:$I,'Data Repository Table'!$C:$C,'Revenue Analysis'!$A40,'Data Repository Table'!$B:$B,'Revenue Analysis'!$B40,'Data Repository Table'!$F:$F,'Revenue Analysis'!$C40,'Data Repository Table'!$D:$D,'Revenue Analysis'!I$32) -> 4950718.5 | J40: =SUMIFS('Data Repository Table'!$I:$I,'Data Repository Table'!$C:$C,'Revenue Analysis'!$A40,'Data Repository Table'!$B:$B,'Revenue Analysis'!$B40,'Data Repository Table'!$F:$F,'Revenue Analysis'!$C40,'Data Repository Table'!$D:$D,'Revenue Analysis'!J$32) -> 4219638.3 | K40: =SUMIFS('Data Repository Table'!$I:$I,'Data Repository Table'!$C:$C,'Revenue Analysis'!$A40,'Data Repository Table'!$B:$B,'Revenue Analysis'!$B40,'Data Repository Table'!$F:$F,'Revenue Analysis'!$C40,'Data Repository Table'!$D:$D,'Revenue Analysis'!K$32) -> 6454620.6 | L40: =SUMIFS('Data Repository Table'!$I:$I,'Data Repository Table'!$C:$C,'Revenue Analysis'!$A40,'Data Repository Table'!$B:$B,'Revenue Analysis'!$B40,'Data Repository Table'!$F:$F,'Revenue Analysis'!$C40,'Data Repository Table'!$D:$D,'Revenue Analysis'!L$32) -> 6573684.7 | ... P40: =SUMIFS('Data Repository Table'!$I:$I,'Data Repository Table'!$C:$C,'Revenue Analysis'!$A40,'Data Repository Table'!$B:$B,'Revenue Analysis'!$B40,'Data Repository Table'!$F:$F,'Revenue Analysis'!$C40,'Data Repository Table'!$D:$D,'Revenue Analysis'!P$32) -> 6591800.8 | Q40: =SUM(E40:P40) -> 67860511
A41: Jutik | B41: Revenue | C41: 002 Public Sales | E41: =SUMIFS('Data Repository Table'!$I:$I,'Data Repository Table'!$C:$C,'Revenue Analysis'!$A41,'Data Repository Table'!$B:$B,'Revenue Analysis'!$B41,'Data Repository Table'!$F:$F,'Revenue Analysis'!$C41,'Data Repository Table'!$D:$D,'Revenue Analysis'!E$32) -> 4380247.2 | F41: =SUMIFS('Data Repository Table'!$I:$I,'Data Repository Table'!$C:$C,'Revenue Analysis'!$A41,'Data Repository Table'!$B:$B,'Revenue Analysis'!$B41,'Data Repository Table'!$F:$F,'Revenue Analysis'!$C41,'Data Repository Table'!$D:$D,'Revenue Analysis'!F$32) -> 3839528.4 | G41: =SUMIFS('Data Repository Table'!$I:$I,'Data Repository Table'!$C:$C,'Revenue Analysis'!$A41,'Data Repository Table'!$B:$B,'Revenue Analysis'!$B41,'Data Repository Table'!$F:$F,'Revenue Analysis'!$C41,'Data Repository Table'!$D:$D,'Revenue Analysis'!G$32) -> 5214440.7 | H41: =SUMIFS('Data Repository Table'!$I:$I,'Data Repository Table'!$C:$C,'Revenue Analysis'!$A41,'Data Repository Table'!$B:$B,'Revenue Analysis'!$B41,'Data Repository Table'!$F:$F,'Revenue Analysis'!$C41,'Data Repository Table'!$D:$D,'Revenue Analysis'!H$32) -> 4725429.2 | I41: =SUMIFS('Data Repository Table'!$I:$I,'Data Repository Table'!$C:$C,'Revenue Analysis'!$A41,'Data Repository Table'!$B:$B,'Revenue Analysis'!$B41,'Data Repository Table'!$F:$F,'Revenue Analysis'!$C41,'Data Repository Table'!$D:$D,'Revenue Analysis'!I$32) -> 4092594 | J41: =SUMIFS('Data Repository Table'!$I:$I,'Data Repository Table'!$C:$C,'Revenue Analysis'!$A41,'Data Repository Table'!$B:$B,'Revenue Analysis'!$B41,'Data Repository Table'!$F:$F,'Revenue Analysis'!$C41,'Data Repository Table'!$D:$D,'Revenue Analysis'!J$32) -> 4488234.3 | K41: =SUMIFS('Data Repository Table'!$I:$I,'Data Repository Table'!$C:$C,'Revenue Analysis'!$A41,'Data Repository Table'!$B:$B,'Revenue Analysis'!$B41,'Data Repository Table'!$F:$F,'Revenue Analysis'!$C41,'Data Repository Table'!$D:$D,'Revenue Analysis'!K$32) -> 5335819.7 | L41: =SUMIFS('Data Repository Table'!$I:$I,'Data Repository Table'!$C:$C,'Revenue Analysis'!$A41,'Data Repository Table'!$B:$B,'Revenue Analysis'!$B41,'Data Repository Table'!$F:$F,'Revenue Analysis'!$C41,'Data Repository Table'!$D:$D,'Revenue Analysis'!L$32) -> 5434246 | ... P41: =SUMIFS('Data Repository Table'!$I:$I,'Data Repository Table'!$C:$C,'Revenue Analysis'!$A41,'Data Repository Table'!$B:$B,'Revenue Analysis'!$B41,'Data Repository Table'!$F:$F,'Revenue Analysis'!$C41,'Data Repository Table'!$D:$D,'Revenue Analysis'!P$32) -> 5449222 | Q41: =SUM(E41:P41) -> 58098022
A42: Jutik | B42: Revenue | C42: 003 Residential Sales | E42: =SUMIFS('Data Repository Table'!$I:$I,'Data Repository Table'!$C:$C,'Revenue Analysis'!$A42,'Data Repository Table'!$B:$B,'Revenue Analysis'!$B42,'Data Repository Table'!$F:$F,'Revenue Analysis'!$C42,'Data Repository Table'!$D:$D,'Revenue Analysis'!E$32) -> 3037913.4 | F42: =SUMIFS('Data Repository Table'!$I:$I,'Data Repository Table'!$C:$C,'Revenue Analysis'!$A42,'Data Repository Table'!$B:$B,'Revenue Analysis'!$B42,'Data Repository Table'!$F:$F,'Revenue Analysis'!$C42,'Data Repository Table'!$D:$D,'Revenue Analysis'!F$32) -> 3356447.1 | G42: =SUMIFS('Data Repository Table'!$I:$I,'Data Repository Table'!$C:$C,'Revenue Analysis'!$A42,'Data Repository Table'!$B:$B,'Revenue Analysis'!$B42,'Data Repository Table'!$F:$F,'Revenue Analysis'!$C42,'Data Repository Table'!$D:$D,'Revenue Analysis'!G$32) -> 2922918.5 | H42: =SUMIFS('Data Repository Table'!$I:$I,'Data Repository Table'!$C:$C,'Revenue Analysis'!$A42,'Data Repository Table'!$B:$B,'Revenue Analysis'!$B42,'Data Repository Table'!$F:$F,'Revenue Analysis'!$C42,'Data Repository Table'!$D:$D,'Revenue Analysis'!H$32) -> 2583765.4 | I42: =SUMIFS('Data Repository Table'!$I:$I,'Data Repository Table'!$C:$C,'Revenue Analysis'!$A42,'Data Repository Table'!$B:$B,'Revenue Analysis'!$B42,'Data Repository Table'!$F:$F,'Revenue Analysis'!$C42,'Data Repository Table'!$D:$D,'Revenue Analysis'!I$32) -> 2838412 | J42: =SUMIFS('Data Repository Table'!$I:$I,'Data Repository Table'!$C:$C,'Revenue Analysis'!$A42,'Data Repository Table'!$B:$B,'Revenue Analysis'!$B42,'Data Repository Table'!$F:$F,'Revenue Analysis'!$C42,'Data Repository Table'!$D:$D,'Revenue Analysis'!J$32) -> 2419259.3 | K42: =SUMIFS('Data Repository Table'!$I:$I,'Data Repository Table'!$C:$C,'Revenue Analysis'!$A42,'Data Repository Table'!$B:$B,'Revenue Analysis'!$B42,'Data Repository Table'!$F:$F,'Revenue Analysis'!$C42,'Data Repository Table'!$D:$D,'Revenue Analysis'!K$32) -> 3700649.1 | L42: =SUMIFS('Data Repository Table'!$I:$I,'Data Repository Table'!$C:$C,'Revenue Analysis'!$A42,'Data Repository Table'!$B:$B,'Revenue Analysis'!$B42,'Data Repository Table'!$F:$F,'Revenue Analysis'!$C42,'Data Repository Table'!$D:$D,'Revenue Analysis'!L$32) -> 3768912.5 | ... P42: =SUMIFS('Data Repository Table'!$I:$I,'Data Repository Table'!$C:$C,'Revenue Analysis'!$A42,'Data Repository Table'!$B:$B,'Revenue Analysis'!$B42,'Data Repository Table'!$F:$F,'Revenue Analysis'!$C42,'Data Repository Table'!$D:$D,'Revenue Analysis'!P$32) -> 3079299.1 | Q42: =SUM(E42:P42) -> 37706693
A44: Having performed some basic time series analysis where we've analyzed the data at a monthly level; it's time to visualize this using some charts.
A45: Whilst tables are an excellent way to visualize data, charts are more intuitive and allow us to identify specific trends that aren't as apparent in tabular form.
A46: Q3. Create one line chart for each unit (Kootha, Surjek, Jutik) depicting the sales for 001 Private Water Hedge Sales, 002 Public Sales and 003 Residential Sales from the July-13 to Jun-14 period. Do you notice any period where sales are particularly high?
A47: Hint: We recommend using line charts to best illustrate the sales for each unit, segmented by customer type (i.e. Private / Public / Residential )
Q49: Answer: Yes! Sales appear high on January-14.
A60: In the previous exercise we've picked up some trends from observing the monthly revenues trended over a twelve month period.
A61: Specifically, it's clear that one of the Unit(s) generates the majority of the revenues for Southern Water Corp.
A62: However, it's important for us to understand the contribution each customer segment provides from a % standpoint as well as a dollar stand point.
A63: Let's close out the Revenue Analysis with the below question.
A64: Q4. Calculate the overall % contribution of each customer segment for each of the three (3) units listed below and create two (2) stacked column chart showing the contributions that each customer segment provides per unit on a dollar basis, and a percentage basis.
B65: Revenue
B66: 001 Private Water Hedge Sales | C66: 002 Public Sales | D66: 003 Residential Sales | E66: Total
A67: Kootha | B67: =SUMIFS('Data Repository Table'!$I:$I,'Data Repository Table'!$C:$C,'Revenue Analysis'!$A67,'Data Repository Table'!$B:$B,'Revenue Analysis'!$B34,'Data Repository Table'!$F:$F,'Revenue Analysis'!B$66) -> 37118739 | C67: =SUMIFS('Data Repository Table'!$I:$I,'Data Repository Table'!$C:$C,'Revenue Analysis'!$A67,'Data Repository Table'!$B:$B,'Revenue Analysis'!$B34,'Data Repository Table'!$F:$F,'Revenue Analysis'!C$66) -> 18271699 | D67: =SUMIFS('Data Repository Table'!$I:$I,'Data Repository Table'!$C:$C,'Revenue Analysis'!$A67,'Data Repository Table'!$B:$B,'Revenue Analysis'!$B34,'Data Repository Table'!$F:$F,'Revenue Analysis'!D$66) -> 15554519 | E67: =SUM(B67:D67) -> 70944957
A68: Surjek | B68: =SUMIFS('Data Repository Table'!$I:$I,'Data Repository Table'!$C:$C,'Revenue Analysis'!$A68,'Data Repository Table'!$B:$B,'Revenue Analysis'!$B34,'Data Repository Table'!$F:$F,'Revenue Analysis'!B$66) -> 82448062 | C68: =SUMIFS('Data Repository Table'!$I:$I,'Data Repository Table'!$C:$C,'Revenue Analysis'!$A68,'Data Repository Table'!$B:$B,'Revenue Analysis'!$B34,'Data Repository Table'!$F:$F,'Revenue Analysis'!C$66) -> 70562398 | D68: =SUMIFS('Data Repository Table'!$I:$I,'Data Repository Table'!$C:$C,'Revenue Analysis'!$A68,'Data Repository Table'!$B:$B,'Revenue Analysis'!$B34,'Data Repository Table'!$F:$F,'Revenue Analysis'!D$66) -> 49244889 | E68: =SUM(B68:D68) -> 2.0225535e+08
A69: Jutik | B69: =SUMIFS('Data Repository Table'!$I:$I,'Data Repository Table'!$C:$C,'Revenue Analysis'!$A69,'Data Repository Table'!$B:$B,'Revenue Analysis'!$B34,'Data Repository Table'!$F:$F,'Revenue Analysis'!B$66) -> 67860511 | C69: =SUMIFS('Data Repository Table'!$I:$I,'Data Repository Table'!$C:$C,'Revenue Analysis'!$A69,'Data Repository Table'!$B:$B,'Revenue Analysis'!$B34,'Data Repository Table'!$F:$F,'Revenue Analysis'!C$66) -> 58098022 | D69: =SUMIFS('Data Repository Table'!$I:$I,'Data Repository Table'!$C:$C,'Revenue Analysis'!$A69,'Data Repository Table'!$B:$B,'Revenue Analysis'!$B34,'Data Repository Table'!$F:$F,'Revenue Analysis'!D$66) -> 37706693 | E69: =SUM(B69:D69) -> 1.6366523e+08
B71: 001 Private Water Hedge Sales | C71: 002 Public Sales | D71: 003 Residential Sales | E71: Total
A72: Kootha | B72: =B67/E67 -> 0.52320475 | C72: =C67/E67 -> 0.25754754 | D72: =D67/E67 -> 0.21924771 | E72: =SUM(B72:D72) -> 1
A73: Surjek | B73: =B68/E68 -> 0.40764342 | C73: =C68/E68 -> 0.34887778 | D73: =D68/E68 -> 0.2434788 | E73: =SUM(B73:D73) -> 1
A74: Jutik | B74: =B69/E69 -> 0.41462999 | C74: =C69/E69 -> 0.35498086 | D74: =D69/E69 -> 0.23038915 | E74: =SUM(B74:D74) -> 1

Sheet Expenses Analysis
A1: Expenses Analysis - Part II
A2: Expense Analysis speaks primarily to understanding which product(s) are the most expensive to operate and maintain.
A3: Think about this as your personal budget; You want to know exactly where your money is being spent.
A4: As we mentioned in the last section; we've calculated the revenues and know which of our products generate the most revenues at a Unit Level (Kootha, Surjek, Jutik). But it is equally important for us to understand what is our expenses at a unit level. If our expenses outweigh our revenues - this is not a good outcome.If a product generates a lot of revenues, but the expenses are greater than the revenues - this isn't a good news story.
A6: Now let's take a look at how Southern Water Corps Expenses look like by calculating the Expenses for each of the Units and asking ourselves - what does the data tell us?
A7: Note: You may notice some trends with respect to higher costs for those units which produce a specific type of water.
A8: Let's get started!
A10: Q5. For each of the three Southern Water Corp. Desalination Plants, they produce desalinated water which is then consumed via private, public or residential usage. These costs are then aggregated at a Unit Level, separated into Chemical Costs, Facility Costs, Operational Maintenance Costs and Labour Costs. Please calculate the monthly expenses for Kootha, Surjek and Jutik and put this in the table below.
A11: Note: You can reference the Expenses Value Driver Tree in the Read Me tab if you need assistance.
A12: Unit | B12: Value Driver | C12: Accounting Code Centre | D12: Accounting Code Centre Element | F12: 41456 | G12: 41487 | H12: 41518 | I12: 41548 | J12: 41579 | K12: 41609 | L12: 41640 | M12: 41671 | N12: 41699 | O12: 41730 | P12: 41760 | Q12: 41791 | R12: Total
A15: Kootha | B15: Expenses | C15: Chemical Costs | D15: Chem-Exp (001) | F15: =SUMIFS('Data Repository Table'!$I:$I,'Data Repository Table'!$C:$C,'Expenses Analysis'!$A15,'Data Repository Table'!$B:$B,'Expenses Analysis'!$B15,'Data Repository Table'!$F:$F,'Expenses Analysis'!$C15,'Data Repository Table'!$G:$G,'Expenses Analysis'!$D15,'Data Repository Table'!$D:$D,'Expenses Analysis'!F$12) -> 593751.84 | G15: =SUMIFS('Data Repository Table'!$I:$I,'Data Repository Table'!$C:$C,'Expenses Analysis'!$A15,'Data Repository Table'!$B:$B,'Expenses Analysis'!$B15,'Data Repository Table'!$F:$F,'Expenses Analysis'!$C15,'Data Repository Table'!$G:$G,'Expenses Analysis'!$D15,'Data Repository Table'!$D:$D,'Expenses Analysis'!G$12) -> 820393.03 | H15: =SUMIFS('Data Repository Table'!$I:$I,'Data Repository Table'!$C:$C,'Expenses Analysis'!$A15,'Data Repository Table'!$B:$B,'Expenses Analysis'!$B15,'Data Repository Table'!$F:$F,'Expenses Analysis'!$C15,'Data Repository Table'!$G:$G,'Expenses Analysis'!$D15,'Data Repository Table'!$D:$D,'Expenses Analysis'!H$12) -> 642291.58 | I15: =SUMIFS('Data Repository Table'!$I:$I,'Data Repository Table'!$C:$C,'Expenses Analysis'!$A15,'Data Repository Table'!$B:$B,'Expenses Analysis'!$B15,'Data Repository Table'!$F:$F,'Expenses Analysis'!$C15,'Data Repository Table'!$G:$G,'Expenses Analysis'!$D15,'Data Repository Table'!$D:$D,'Expenses Analysis'!I$12) -> 609639.97 | J15: =SUMIFS('Data Repository Table'!$I:$I,'Data Repository Table'!$C:$C,'Expenses Analysis'!$A15,'Data Repository Table'!$B:$B,'Expenses Analysis'!$B15,'Data Repository Table'!$F:$F,'Expenses Analysis'!$C15,'Data Repository Table'!$G:$G,'Expenses Analysis'!$D15,'Data Repository Table'!$D:$D,'Expenses Analysis'!J$12) -> 626073.17 | K15: =SUMIFS('Data Repository Table'!$I:$I,'Data Repository Table'!$C:$C,'Expenses Analysis'!$A15,'Data Repository Table'!$B:$B,'Expenses Analysis'!$B15,'Data Repository Table'!$F:$F,'Expenses Analysis'!$C15,'Data Repository Table'!$G:$G,'Expenses Analysis'!$D15,'Data Repository Table'!$D:$D,'Expenses Analysis'!K$12) -> 602153.38 | L15: =SUMIFS('Data Repository Table'!$I:$I,'Data Repository Table'!$C:$C,'Expenses Analysis'!$A15,'Data Repository Table'!$B:$B,'Expenses Analysis'!$B15,'Data Repository Table'!$F:$F,'Expenses Analysis'!$C15,'Data Repository Table'!$G:$G,'Expenses Analysis'!$D15,'Data Repository Table'!$D:$D,'Expenses Analysis'!L$12) -> 1146144 | M15: =SUMIFS('Data Repository Table'!$I:$I,'Data Repository Table'!$C:$C,'Expenses Analysis'!$A15,'Data Repository Table'!$B:$B,'Expenses Analysis'!$B15,'Data Repository Table'!$F:$F,'Expenses Analysis'!$C15,'Data Repository Table'!$G:$G,'Expenses Analysis'!$D15,'Data Repository Table'!$D:$D,'Expenses Analysis'!M$12) -> 964931.84 | ... Q15: =SUMIFS('Data Repository Table'!$I:$I,'Data Repository Table'!$C:$C,'Expenses Analysis'!$A15,'Data Repository Table'!$B:$B,'Expenses Analysis'!$B15,'Data Repository Table'!$F:$F,'Expenses Analysis'!$C15,'Data Repository Table'!$G:$G,'Expenses Analysis'!$D15,'Data Repository Table'!$D:$D,'Expenses Analysis'!Q$12) -> 1168045.2 | R15: =SUM(F15:Q15) -> 10125518
A16: Kootha | B16: Expenses | C16: Facility Costs | D16: Utility-Exp (002) - Heating | F16: =SUMIFS('Data Repository Table'!$I:$I,'Data Repository Table'!$C:$C,'Expenses Analysis'!$A16,'Data Repository Table'!$B:$B,'Expenses Analysis'!$B16,'Data Repository Table'!$F:$F,'Expenses Analysis'!$C16,'Data Repository Table'!$G:$G,'Expenses Analysis'!$D16,'Data Repository Table'!$D:$D,'Expenses Analysis'!F$12) -> 276807.38 | G16: =SUMIFS('Data Repository Table'!$I:$I,'Data Repository Table'!$C:$C,'Expenses Analysis'!$A16,'Data Repository Table'!$B:$B,'Expenses Analysis'!$B16,'Data Repository Table'!$F:$F,'Expenses Analysis'!$C16,'Data Repository Table'!$G:$G,'Expenses Analysis'!$D16,'Data Repository Table'!$D:$D,'Expenses Analysis'!G$12) -> 382467.61 | H16: =SUMIFS('Data Repository Table'!$I:$I,'Data Repository Table'!$C:$C,'Expenses Analysis'!$A16,'Data Repository Table'!$B:$B,'Expenses Analysis'!$B16,'Data Repository Table'!$F:$F,'Expenses Analysis'!$C16,'Data Repository Table'!$G:$G,'Expenses Analysis'!$D16,'Data Repository Table'!$D:$D,'Expenses Analysis'!H$12) -> 299436.64 | I16: =SUMIFS('Data Repository Table'!$I:$I,'Data Repository Table'!$C:$C,'Expenses Analysis'!$A16,'Data Repository Table'!$B:$B,'Expenses Analysis'!$B16,'Data Repository Table'!$F:$F,'Expenses Analysis'!$C16,'Data Repository Table'!$G:$G,'Expenses Analysis'!$D16,'Data Repository Table'!$D:$D,'Expenses Analysis'!I$12) -> 284214.44 | J16: =SUMIFS('Data Repository Table'!$I:$I,'Data Repository Table'!$C:$C,'Expenses Analysis'!$A16,'Data Repository Table'!$B:$B,'Expenses Analysis'!$B16,'Data Repository Table'!$F:$F,'Expenses Analysis'!$C16,'Data Repository Table'!$G:$G,'Expenses Analysis'!$D16,'Data Repository Table'!$D:$D,'Expenses Analysis'!J$12) -> 291875.6 | K16: =SUMIFS('Data Repository Table'!$I:$I,'Data Repository Table'!$C:$C,'Expenses Analysis'!$A16,'Data Repository Table'!$B:$B,'Expenses Analysis'!$B16,'Data Repository Table'!$F:$F,'Expenses Analysis'!$C16,'Data Repository Table'!$G:$G,'Expenses Analysis'!$D16,'Data Repository Table'!$D:$D,'Expenses Analysis'!K$12) -> 280724.19 | L16: =SUMIFS('Data Repository Table'!$I:$I,'Data Repository Table'!$C:$C,'Expenses Analysis'!$A16,'Data Repository Table'!$B:$B,'Expenses Analysis'!$B16,'Data Repository Table'!$F:$F,'Expenses Analysis'!$C16,'Data Repository Table'!$G:$G,'Expenses Analysis'!$D16,'Data Repository Table'!$D:$D,'Expenses Analysis'!L$12) -> 534332.86 | M16: =SUMIFS('Data Repository Table'!$I:$I,'Data Repository Table'!$C:$C,'Expenses Analysis'!$A16,'Data Repository Table'!$B:$B,'Expenses Analysis'!$B16,'Data Repository Table'!$F:$F,'Expenses Analysis'!$C16,'Data Repository Table'!$G:$G,'Expenses Analysis'!$D16,'Data Repository Table'!$D:$D,'Expenses Analysis'!M$12) -> 449851.67 | ... Q16: =SUMIFS('Data Repository Table'!$I:$I,'Data Repository Table'!$C:$C,'Expenses Analysis'!$A16,'Data Repository Table'!$B:$B,'Expenses Analysis'!$B16,'Data Repository Table'!$F:$F,'Expenses Analysis'!$C16,'Data Repository Table'!$G:$G,'Expenses Analysis'!$D16,'Data Repository Table'!$D:$D,'Expenses Analysis'!Q$12) -> 544543.23 | R16: =SUM(F16:Q16) -> 4720521.2
A17: Kootha | B17: Expenses | C17: Facility Costs | D17: Utility-Exp (002) - Electricity | F17: =SUMIFS('Data Repository Table'!$I:$I,'Data Repository Table'!$C:$C,'Expenses Analysis'!$A17,'Data Repository Table'!$B:$B,'Expenses Analysis'!$B17,'Data Repository Table'!$F:$F,'Expenses Analysis'!$C17,'Data Repository Table'!$G:$G,'Expenses Analysis'!$D17,'Data Repository Table'!$D:$D,'Expenses Analysis'!F$12) -> 415211.08 | G17: =SUMIFS('Data Repository Table'!$I:$I,'Data Repository Table'!$C:$C,'Expenses Analysis'!$A17,'Data Repository Table'!$B:$B,'Expenses Analysis'!$B17,'Data Repository Table'!$F:$F,'Expenses Analysis'!$C17,'Data Repository Table'!$G:$G,'Expenses Analysis'!$D17,'Data Repository Table'!$D:$D,'Expenses Analysis'!G$12) -> 573701.42 | H17: =SUMIFS('Data Repository Table'!$I:$I,'Data Repository Table'!$C:$C,'Expenses Analysis'!$A17,'Data Repository Table'!$B:$B,'Expenses Analysis'!$B17,'Data Repository Table'!$F:$F,'Expenses Analysis'!$C17,'Data Repository Table'!$G:$G,'Expenses Analysis'!$D17,'Data Repository Table'!$D:$D,'Expenses Analysis'!H$12) -> 449154.95 | I17: =SUMIFS('Data Repository Table'!$I:$I,'Data Repository Table'!$C:$C,'Expenses Analysis'!$A17,'Data Repository Table'!$B:$B,'Expenses Analysis'!$B17,'Data Repository Table'!$F:$F,'Expenses Analysis'!$C17,'Data Repository Table'!$G:$G,'Expenses Analysis'!$D17,'Data Repository Table'!$D:$D,'Expenses Analysis'!I$12) -> 426321.66 | J17: =SUMIFS('Data Repository Table'!$I:$I,'Data Repository Table'!$C:$C,'Expenses Analysis'!$A17,'Data Repository Table'!$B:$B,'Expenses Analysis'!$B17,'Data Repository Table'!$F:$F,'Expenses Analysis'!$C17,'Data Repository Table'!$G:$G,'Expenses Analysis'!$D17,'Data Repository Table'!$D:$D,'Expenses Analysis'!J$12) -> 437813.4 | K17: =SUMIFS('Data Repository Table'!$I:$I,'Data Repository Table'!$C:$C,'Expenses Analysis'!$A17,'Data Repository Table'!$B:$B,'Expenses Analysis'!$B17,'Data Repository Table'!$F:$F,'Expenses Analysis'!$C17,'Data Repository Table'!$G:$G,'Expenses Analysis'!$D17,'Data Repository Table'!$D:$D,'Expenses Analysis'!K$12) -> 421086.28 | L17: =SUMIFS('Data Repository Table'!$I:$I,'Data Repository Table'!$C:$C,'Expenses Analysis'!$A17,'Data Repository Table'!$B:$B,'Expenses Analysis'!$B17,'Data Repository Table'!$F:$F,'Expenses Analysis'!$C17,'Data Repository Table'!$G:$G,'Expenses Analysis'!$D17,'Data Repository Table'!$D:$D,'Expenses Analysis'!L$12) -> 801499.29 | M17: =SUMIFS('Data Repository Table'!$I:$I,'Data Repository Table'!$C:$C,'Expenses Analysis'!$A17,'Data Repository Table'!$B:$B,'Expenses Analysis'!$B17,'Data Repository Table'!$F:$F,'Expenses Analysis'!$C17,'Data Repository Table'!$G:$G,'Expenses Analysis'!$D17,'Data Repository Table'!$D:$D,'Expenses Analysis'!M$12) -> 674777.51 | ... Q17: =SUMIFS('Data Repository Table'!$I:$I,'Data Repository Table'!$C:$C,'Expenses Analysis'!$A17,'Data Repository Table'!$B:$B,'Expenses Analysis'!$B17,'Data Repository Table'!$F:$F,'Expenses Analysis'!$C17,'Data Repository Table'!$G:$G,'Expenses Analysis'!$D17,'Data Repository Table'!$D:$D,'Expenses Analysis'!Q$12) -> 816814.84 | R17: =SUM(F17:Q17) -> 7080781.8
A18: Kootha | B18: Expenses | C18: Operational Maintenance Costs | D18: Plant Maintenance (001) | F18: =SUMIFS('Data Repository Table'!$I:$I,'Data Repository Table'!$C:$C,'Expenses Analysis'!$A18,'Data Repository Table'!$B:$B,'Expenses Analysis'!$B18,'Data Repository Table'!$F:$F,'Expenses Analysis'!$C18,'Data Repository Table'!$G:$G,'Expenses Analysis'!$D18,'Data Repository Table'!$D:$D,'Expenses Analysis'!F$12) -> 360688.41 | G18: =SUMIFS('Data Repository Table'!$I:$I,'Data Repository Table'!$C:$C,'Expenses Analysis'!$A18,'Data Repository Table'!$B:$B,'Expenses Analysis'!$B18,'Data Repository Table'!$F:$F,'Expenses Analysis'!$C18,'Data Repository Table'!$G:$G,'Expenses Analysis'!$D18,'Data Repository Table'!$D:$D,'Expenses Analysis'!G$12) -> 498366.89 | H18: =SUMIFS('Data Repository Table'!$I:$I,'Data Repository Table'!$C:$C,'Expenses Analysis'!$A18,'Data Repository Table'!$B:$B,'Expenses Analysis'!$B18,'Data Repository Table'!$F:$F,'Expenses Analysis'!$C18,'Data Repository Table'!$G:$G,'Expenses Analysis'!$D18,'Data Repository Table'!$D:$D,'Expenses Analysis'!H$12) -> 390175.01 | I18: =SUMIFS('Data Repository Table'!$I:$I,'Data Repository Table'!$C:$C,'Expenses Analysis'!$A18,'Data Repository Table'!$B:$B,'Expenses Analysis'!$B18,'Data Repository Table'!$F:$F,'Expenses Analysis'!$C18,'Data Repository Table'!$G:$G,'Expenses Analysis'!$D18,'Data Repository Table'!$D:$D,'Expenses Analysis'!I$12) -> 370340.03 | J18: =SUMIFS('Data Repository Table'!$I:$I,'Data Repository Table'!$C:$C,'Expenses Analysis'!$A18,'Data Repository Table'!$B:$B,'Expenses Analysis'!$B18,'Data Repository Table'!$F:$F,'Expenses Analysis'!$C18,'Data Repository Table'!$G:$G,'Expenses Analysis'!$D18,'Data Repository Table'!$D:$D,'Expenses Analysis'!J$12) -> 380322.76 | K18: =SUMIFS('Data Repository Table'!$I:$I,'Data Repository Table'!$C:$C,'Expenses Analysis'!$A18,'Data Repository Table'!$B:$B,'Expenses Analysis'!$B18,'Data Repository Table'!$F:$F,'Expenses Analysis'!$C18,'Data Repository Table'!$G:$G,'Expenses Analysis'!$D18,'Data Repository Table'!$D:$D,'Expenses Analysis'!K$12) -> 365792.12 | L18: =SUMIFS('Data Repository Table'!$I:$I,'Data Repository Table'!$C:$C,'Expenses Analysis'!$A18,'Data Repository Table'!$B:$B,'Expenses Analysis'!$B18,'Data Repository Table'!$F:$F,'Expenses Analysis'!$C18,'Data Repository Table'!$G:$G,'Expenses Analysis'!$D18,'Data Repository Table'!$D:$D,'Expenses Analysis'!L$12) -> 459526.26 | M18: =SUMIFS('Data Repository Table'!$I:$I,'Data Repository Table'!$C:$C,'Expenses Analysis'!$A18,'Data Repository Table'!$B:$B,'Expenses Analysis'!$B18,'Data Repository Table'!$F:$F,'Expenses Analysis'!$C18,'Data Repository Table'!$G:$G,'Expenses Analysis'!$D18,'Data Repository Table'!$D:$D,'Expenses Analysis'!M$12) -> 386872.44 | ... Q18: =SUMIFS('Data Repository Table'!$I:$I,'Data Repository Table'!$C:$C,'Expenses Analysis'!$A18,'Data Repository Table'!$B:$B,'Expenses Analysis'!$B18,'Data Repository Table'!$F:$F,'Expenses Analysis'!$C18,'Data Repository Table'!$G:$G,'Expenses Analysis'!$D18,'Data Repository Table'!$D:$D,'Expenses Analysis'!Q$12) -> 468307.18 | R18: =SUM(F18:Q18) -> 4863981.2
A19: Kootha | B19: Expenses | C19: Operational Maintenance Costs | D19: Plant Outages (002) | F19: =SUMIFS('Data Repository Table'!$I:$I,'Data Repository Table'!$C:$C,'Expenses Analysis'!$A19,'Data Repository Table'!$B:$B,'Expenses Analysis'!$B19,'Data Repository Table'!$F:$F,'Expenses Analysis'!$C19,'Data Repository Table'!$G:$G,'Expenses Analysis'!$D19,'Data Repository Table'!$D:$D,'Expenses Analysis'!F$12) -> 226478.77 | G19: =SUMIFS('Data Repository Table'!$I:$I,'Data Repository Table'!$C:$C,'Expenses Analysis'!$A19,'Data Repository Table'!$B:$B,'Expenses Analysis'!$B19,'Data Repository Table'!$F:$F,'Expenses Analysis'!$C19,'Data Repository Table'!$G:$G,'Expenses Analysis'!$D19,'Data Repository Table'!$D:$D,'Expenses Analysis'!G$12) -> 312928.05 | H19: =SUMIFS('Data Repository Table'!$I:$I,'Data Repository Table'!$C:$C,'Expenses Analysis'!$A19,'Data Repository Table'!$B:$B,'Expenses Analysis'!$B19,'Data Repository Table'!$F:$F,'Expenses Analysis'!$C19,'Data Repository Table'!$G:$G,'Expenses Analysis'!$D19,'Data Repository Table'!$D:$D,'Expenses Analysis'!H$12) -> 244993.61 | I19: =SUMIFS('Data Repository Table'!$I:$I,'Data Repository Table'!$C:$C,'Expenses Analysis'!$A19,'Data Repository Table'!$B:$B,'Expenses Analysis'!$B19,'Data Repository Table'!$F:$F,'Expenses Analysis'!$C19,'Data Repository Table'!$G:$G,'Expenses Analysis'!$D19,'Data Repository Table'!$D:$D,'Expenses Analysis'!I$12) -> 232539.09 | J19: =SUMIFS('Data Repository Table'!$I:$I,'Data Repository Table'!$C:$C,'Expenses Analysis'!$A19,'Data Repository Table'!$B:$B,'Expenses Analysis'!$B19,'Data Repository Table'!$F:$F,'Expenses Analysis'!$C19,'Data Repository Table'!$G:$G,'Expenses Analysis'!$D19,'Data Repository Table'!$D:$D,'Expenses Analysis'!J$12) -> 238807.31 | K19: =SUMIFS('Data Repository Table'!$I:$I,'Data Repository Table'!$C:$C,'Expenses Analysis'!$A19,'Data Repository Table'!$B:$B,'Expenses Analysis'!$B19,'Data Repository Table'!$F:$F,'Expenses Analysis'!$C19,'Data Repository Table'!$G:$G,'Expenses Analysis'!$D19,'Data Repository Table'!$D:$D,'Expenses Analysis'!K$12) -> 229683.42 | L19: =SUMIFS('Data Repository Table'!$I:$I,'Data Repository Table'!$C:$C,'Expenses Analysis'!$A19,'Data Repository Table'!$B:$B,'Expenses Analysis'!$B19,'Data Repository Table'!$F:$F,'Expenses Analysis'!$C19,'Data Repository Table'!$G:$G,'Expenses Analysis'!$D19,'Data Repository Table'!$D:$D,'Expenses Analysis'!L$12) -> 288539.74 | M19: =SUMIFS('Data Repository Table'!$I:$I,'Data Repository Table'!$C:$C,'Expenses Analysis'!$A19,'Data Repository Table'!$B:$B,'Expenses Analysis'!$B19,'Data Repository Table'!$F:$F,'Expenses Analysis'!$C19,'Data Repository Table'!$G:$G,'Expenses Analysis'!$D19,'Data Repository Table'!$D:$D,'Expenses Analysis'!M$12) -> 242919.9 | ... Q19: =SUMIFS('Data Repository Table'!$I:$I,'Data Repository Table'!$C:$C,'Expenses Analysis'!$A19,'Data Repository Table'!$B:$B,'Expenses Analysis'!$B19,'Data Repository Table'!$F:$F,'Expenses Analysis'!$C19,'Data Repository Table'!$G:$G,'Expenses Analysis'!$D19,'Data Repository Table'!$D:$D,'Expenses Analysis'!Q$12) -> 294053.34 | R19: =SUM(F19:Q19) -> 3054127.7
A20: Kootha | B20: Expenses | C20: Operational Maintenance Costs | D20: Plant Op. Costs (003) | F20: =SUMIFS('Data Repository Table'!$I:$I,'Data Repository Table'!$C:$C,'Expenses Analysis'!$A20,'Data Repository Table'!$B:$B,'Expenses Analysis'!$B20,'Data Repository Table'!$F:$F,'Expenses Analysis'!$C20,'Data Repository Table'!$G:$G,'Expenses Analysis'!$D20,'Data Repository Table'!$D:$D,'Expenses Analysis'!F$12) -> 255837.13 | G20: =SUMIFS('Data Repository Table'!$I:$I,'Data Repository Table'!$C:$C,'Expenses Analysis'!$A20,'Data Repository Table'!$B:$B,'Expenses Analysis'!$B20,'Data Repository Table'!$F:$F,'Expenses Analysis'!$C20,'Data Repository Table'!$G:$G,'Expenses Analysis'!$D20,'Data Repository Table'!$D:$D,'Expenses Analysis'!G$12) -> 353492.8 | H20: =SUMIFS('Data Repository Table'!$I:$I,'Data Repository Table'!$C:$C,'Expenses Analysis'!$A20,'Data Repository Table'!$B:$B,'Expenses Analysis'!$B20,'Data Repository Table'!$F:$F,'Expenses Analysis'!$C20,'Data Repository Table'!$G:$G,'Expenses Analysis'!$D20,'Data Repository Table'!$D:$D,'Expenses Analysis'!H$12) -> 276752.04 | I20: =SUMIFS('Data Repository Table'!$I:$I,'Data Repository Table'!$C:$C,'Expenses Analysis'!$A20,'Data Repository Table'!$B:$B,'Expenses Analysis'!$B20,'Data Repository Table'!$F:$F,'Expenses Analysis'!$C20,'Data Repository Table'!$G:$G,'Expenses Analysis'!$D20,'Data Repository Table'!$D:$D,'Expenses Analysis'!I$12) -> 262683.04 | J20: =SUMIFS('Data Repository Table'!$I:$I,'Data Repository Table'!$C:$C,'Expenses Analysis'!$A20,'Data Repository Table'!$B:$B,'Expenses Analysis'!$B20,'Data Repository Table'!$F:$F,'Expenses Analysis'!$C20,'Data Repository Table'!$G:$G,'Expenses Analysis'!$D20,'Data Repository Table'!$D:$D,'Expenses Analysis'!J$12) -> 269763.82 | K20: =SUMIFS('Data Repository Table'!$I:$I,'Data Repository Table'!$C:$C,'Expenses Analysis'!$A20,'Data Repository Table'!$B:$B,'Expenses Analysis'!$B20,'Data Repository Table'!$F:$F,'Expenses Analysis'!$C20,'Data Repository Table'!$G:$G,'Expenses Analysis'!$D20,'Data Repository Table'!$D:$D,'Expenses Analysis'!K$12) -> 259457.2 | L20: =SUMIFS('Data Repository Table'!$I:$I,'Data Repository Table'!$C:$C,'Expenses Analysis'!$A20,'Data Repository Table'!$B:$B,'Expenses Analysis'!$B20,'Data Repository Table'!$F:$F,'Expenses Analysis'!$C20,'Data Repository Table'!$G:$G,'Expenses Analysis'!$D20,'Data Repository Table'!$D:$D,'Expenses Analysis'!L$12) -> 325943.04 | M20: =SUMIFS('Data Repository Table'!$I:$I,'Data Repository Table'!$C:$C,'Expenses Analysis'!$A20,'Data Repository Table'!$B:$B,'Expenses Analysis'!$B20,'Data Repository Table'!$F:$F,'Expenses Analysis'!$C20,'Data Repository Table'!$G:$G,'Expenses Analysis'!$D20,'Data Repository Table'!$D:$D,'Expenses Analysis'!M$12) -> 274409.52 | ... Q20: =SUMIFS('Data Repository Table'!$I:$I,'Data Repository Table'!$C:$C,'Expenses Analysis'!$A20,'Data Repository Table'!$B:$B,'Expenses Analysis'!$B20,'Data Repository Table'!$F:$F,'Expenses Analysis'!$C20,'Data Repository Table'!$G:$G,'Expenses Analysis'!$D20,'Data Repository Table'!$D:$D,'Expenses Analysis'!Q$12) -> 332171.37 | R20: =SUM(F20:Q20) -> 3450033.2
A21: Kootha | B21: Expenses | C21: Operational Maintenance Costs | D21: Plant Admin Costs (004) | F21: =SUMIFS('Data Repository Table'!$I:$I,'Data Repository Table'!$C:$C,'Expenses Analysis'!$A21,'Data Repository Table'!$B:$B,'Expenses Analysis'!$B21,'Data Repository Table'!$F:$F,'Expenses Analysis'!$C21,'Data Repository Table'!$G:$G,'Expenses Analysis'!$D21,'Data Repository Table'!$D:$D,'Expenses Analysis'!F$12) -> 176150.15 | G21: =SUMIFS('Data Repository Table'!$I:$I,'Data Repository Table'!$C:$C,'Expenses Analysis'!$A21,'Data Repository Table'!$B:$B,'Expenses Analysis'!$B21,'Data Repository Table'!$F:$F,'Expenses Analysis'!$C21,'Data Repository Table'!$G:$G,'Expenses Analysis'!$D21,'Data Repository Table'!$D:$D,'Expenses Analysis'!G$12) -> 243388.48 | H21: =SUMIFS('Data Repository Table'!$I:$I,'Data Repository Table'!$C:$C,'Expenses Analysis'!$A21,'Data Repository Table'!$B:$B,'Expenses Analysis'!$B21,'Data Repository Table'!$F:$F,'Expenses Analysis'!$C21,'Data Repository Table'!$G:$G,'Expenses Analysis'!$D21,'Data Repository Table'!$D:$D,'Expenses Analysis'!H$12) -> 190550.59 | I21: =SUMIFS('Data Repository Table'!$I:$I,'Data Repository Table'!$C:$C,'Expenses Analysis'!$A21,'Data Repository Table'!$B:$B,'Expenses Analysis'!$B21,'Data Repository Table'!$F:$F,'Expenses Analysis'!$C21,'Data Repository Table'!$G:$G,'Expenses Analysis'!$D21,'Data Repository Table'!$D:$D,'Expenses Analysis'!I$12) -> 180863.73 | J21: =SUMIFS('Data Repository Table'!$I:$I,'Data Repository Table'!$C:$C,'Expenses Analysis'!$A21,'Data Repository Table'!$B:$B,'Expenses Analysis'!$B21,'Data Repository Table'!$F:$F,'Expenses Analysis'!$C21,'Data Repository Table'!$G:$G,'Expenses Analysis'!$D21,'Data Repository Table'!$D:$D,'Expenses Analysis'!J$12) -> 185739.02 | K21: =SUMIFS('Data Repository Table'!$I:$I,'Data Repository Table'!$C:$C,'Expenses Analysis'!$A21,'Data Repository Table'!$B:$B,'Expenses Analysis'!$B21,'Data Repository Table'!$F:$F,'Expenses Analysis'!$C21,'Data Repository Table'!$G:$G,'Expenses Analysis'!$D21,'Data Repository Table'!$D:$D,'Expenses Analysis'!K$12) -> 178642.66 | L21: =SUMIFS('Data Repository Table'!$I:$I,'Data Repository Table'!$C:$C,'Expenses Analysis'!$A21,'Data Repository Table'!$B:$B,'Expenses Analysis'!$B21,'Data Repository Table'!$F:$F,'Expenses Analysis'!$C21,'Data Repository Table'!$G:$G,'Expenses Analysis'!$D21,'Data Repository Table'!$D:$D,'Expenses Analysis'!L$12) -> 224419.8 | M21: =SUMIFS('Data Repository Table'!$I:$I,'Data Repository Table'!$C:$C,'Expenses Analysis'!$A21,'Data Repository Table'!$B:$B,'Expenses Analysis'!$B21,'Data Repository Table'!$F:$F,'Expenses Analysis'!$C21,'Data Repository Table'!$G:$G,'Expenses Analysis'!$D21,'Data Repository Table'!$D:$D,'Expenses Analysis'!M$12) -> 188937.7 | ... Q21: =SUMIFS('Data Repository Table'!$I:$I,'Data Repository Table'!$C:$C,'Expenses Analysis'!$A21,'Data Repository Table'!$B:$B,'Expenses Analysis'!$B21,'Data Repository Table'!$F:$F,'Expenses Analysis'!$C21,'Data Repository Table'!$G:$G,'Expenses Analysis'!$D21,'Data Repository Table'!$D:$D,'Expenses Analysis'!Q$12) -> 228708.16 | R21: =SUM(F21:Q21) -> 2375432.7
A22: Kootha | B22: Expenses | C22: Labour Costs | D22: Labour-Costs (001) | F22: =SUMIFS('Data Repository Table'!$I:$I,'Data Repository Table'!$C:$C,'Expenses Analysis'!$A22,'Data Repository Table'!$B:$B,'Expenses Analysis'!$B22,'Data Repository Table'!$F:$F,'Expenses Analysis'!$C22,'Data Repository Table'!$G:$G,'Expenses Analysis'!$D22,'Data Repository Table'!$D:$D,'Expenses Analysis'!F$12) -> 1153364.1 | G22: =SUMIFS('Data Repository Table'!$I:$I,'Data Repository Table'!$C:$C,'Expenses Analysis'!$A22,'Data Repository Table'!$B:$B,'Expenses Analysis'!$B22,'Data Repository Table'!$F:$F,'Expenses Analysis'!$C22,'Data Repository Table'!$G:$G,'Expenses Analysis'!$D22,'Data Repository Table'!$D:$D,'Expenses Analysis'!G$12) -> 1593615.1 | H22: =SUMIFS('Data Repository Table'!$I:$I,'Data Repository Table'!$C:$C,'Expenses Analysis'!$A22,'Data Repository Table'!$B:$B,'Expenses Analysis'!$B22,'Data Repository Table'!$F:$F,'Expenses Analysis'!$C22,'Data Repository Table'!$G:$G,'Expenses Analysis'!$D22,'Data Repository Table'!$D:$D,'Expenses Analysis'!H$12) -> 1247652.6 | I22: =SUMIFS('Data Repository Table'!$I:$I,'Data Repository Table'!$C:$C,'Expenses Analysis'!$A22,'Data Repository Table'!$B:$B,'Expenses Analysis'!$B22,'Data Repository Table'!$F:$F,'Expenses Analysis'!$C22,'Data Repository Table'!$G:$G,'Expenses Analysis'!$D22,'Data Repository Table'!$D:$D,'Expenses Analysis'!I$12) -> 1184226.8 | J22: =SUMIFS('Data Repository Table'!$I:$I,'Data Repository Table'!$C:$C,'Expenses Analysis'!$A22,'Data Repository Table'!$B:$B,'Expenses Analysis'!$B22,'Data Repository Table'!$F:$F,'Expenses Analysis'!$C22,'Data Repository Table'!$G:$G,'Expenses Analysis'!$D22,'Data Repository Table'!$D:$D,'Expenses Analysis'!J$12) -> 1216148.3 | K22: =SUMIFS('Data Repository Table'!$I:$I,'Data Repository Table'!$C:$C,'Expenses Analysis'!$A22,'Data Repository Table'!$B:$B,'Expenses Analysis'!$B22,'Data Repository Table'!$F:$F,'Expenses Analysis'!$C22,'Data Repository Table'!$G:$G,'Expenses Analysis'!$D22,'Data Repository Table'!$D:$D,'Expenses Analysis'!K$12) -> 1169684.1 | L22: =SUMIFS('Data Repository Table'!$I:$I,'Data Repository Table'!$C:$C,'Expenses Analysis'!$A22,'Data Repository Table'!$B:$B,'Expenses Analysis'!$B22,'Data Repository Table'!$F:$F,'Expenses Analysis'!$C22,'Data Repository Table'!$G:$G,'Expenses Analysis'!$D22,'Data Repository Table'!$D:$D,'Expenses Analysis'!L$12) -> 1469415.4 | M22: =SUMIFS('Data Repository Table'!$I:$I,'Data Repository Table'!$C:$C,'Expenses Analysis'!$A22,'Data Repository Table'!$B:$B,'Expenses Analysis'!$B22,'Data Repository Table'!$F:$F,'Expenses Analysis'!$C22,'Data Repository Table'!$G:$G,'Expenses Analysis'!$D22,'Data Repository Table'!$D:$D,'Expenses Analysis'!M$12) -> 1237092.1 | ... Q22: =SUMIFS('Data Repository Table'!$I:$I,'Data Repository Table'!$C:$C,'Expenses Analysis'!$A22,'Data Repository Table'!$B:$B,'Expenses Analysis'!$B22,'Data Repository Table'!$F:$F,'Expenses Analysis'!$C22,'Data Repository Table'!$G:$G,'Expenses Analysis'!$D22,'Data Repository Table'!$D:$D,'Expenses Analysis'!Q$12) -> 1497493.9 | R22: =SUM(F22:Q22) -> 15553428
A23: Total | D23: Total | F23: =SUM(F15:F22) -> 3458288.9 | G23: =SUM(G15:G22) -> 4778353.4 | H23: =SUM(H15:H22) -> 3741007.1 | I23: =SUM(I15:I22) -> 3550828.8 | J23: =SUM(J15:J22) -> 3646543.4 | K23: =SUM(K15:K22) -> 3507223.4 | L23: =SUM(L15:L22) -> 5249820.3 | M23: =SUM(M15:M22) -> 4419792.7 | ... R23: =SUM(R15:R22) -> 51223824
A25: Surjek | B25: Expenses | C25: Chemical Costs | D25: Chem-Exp (001) | F25: =SUMIFS('Data Repository Table'!$I:$I,'Data Repository Table'!$C:$C,'Expenses Analysis'!$A25,'Data Repository Table'!$B:$B,'Expenses Analysis'!$B25,'Data Repository Table'!$F:$F,'Expenses Analysis'!$C25,'Data Repository Table'!$G:$G,'Expenses Analysis'!$D25,'Data Repository Table'!$D:$D,'Expenses Analysis'!F$12) -> 2533034.5 | G25: =SUMIFS('Data Repository Table'!$I:$I,'Data Repository Table'!$C:$C,'Expenses Analysis'!$A25,'Data Repository Table'!$B:$B,'Expenses Analysis'!$B25,'Data Repository Table'!$F:$F,'Expenses Analysis'!$C25,'Data Repository Table'!$G:$G,'Expenses Analysis'!$D25,'Data Repository Table'!$D:$D,'Expenses Analysis'!G$12) -> 3051574.2 | H25: =SUMIFS('Data Repository Table'!$I:$I,'Data Repository Table'!$C:$C,'Expenses Analysis'!$A25,'Data Repository Table'!$B:$B,'Expenses Analysis'!$B25,'Data Repository Table'!$F:$F,'Expenses Analysis'!$C25,'Data Repository Table'!$G:$G,'Expenses Analysis'!$D25,'Data Repository Table'!$D:$D,'Expenses Analysis'!H$12) -> 3084202.8 | I25: =SUMIFS('Data Repository Table'!$I:$I,'Data Repository Table'!$C:$C,'Expenses Analysis'!$A25,'Data Repository Table'!$B:$B,'Expenses Analysis'!$B25,'Data Repository Table'!$F:$F,'Expenses Analysis'!$C25,'Data Repository Table'!$G:$G,'Expenses Analysis'!$D25,'Data Repository Table'!$D:$D,'Expenses Analysis'!I$12) -> 4135202.8 | J25: =SUMIFS('Data Repository Table'!$I:$I,'Data Repository Table'!$C:$C,'Expenses Analysis'!$A25,'Data Repository Table'!$B:$B,'Expenses Analysis'!$B25,'Data Repository Table'!$F:$F,'Expenses Analysis'!$C25,'Data Repository Table'!$G:$G,'Expenses Analysis'!$D25,'Data Repository Table'!$D:$D,'Expenses Analysis'!J$12) -> 4473275.9 | K25: =SUMIFS('Data Repository Table'!$I:$I,'Data Repository Table'!$C:$C,'Expenses Analysis'!$A25,'Data Repository Table'!$B:$B,'Expenses Analysis'!$B25,'Data Repository Table'!$F:$F,'Expenses Analysis'!$C25,'Data Repository Table'!$G:$G,'Expenses Analysis'!$D25,'Data Repository Table'!$D:$D,'Expenses Analysis'!K$12) -> 3464957.9 | L25: =SUMIFS('Data Repository Table'!$I:$I,'Data Repository Table'!$C:$C,'Expenses Analysis'!$A25,'Data Repository Table'!$B:$B,'Expenses Analysis'!$B25,'Data Repository Table'!$F:$F,'Expenses Analysis'!$C25,'Data Repository Table'!$G:$G,'Expenses Analysis'!$D25,'Data Repository Table'!$D:$D,'Expenses Analysis'!L$12) -> 4049642.8 | M25: =SUMIFS('Data Repository Table'!$I:$I,'Data Repository Table'!$C:$C,'Expenses Analysis'!$A25,'Data Repository Table'!$B:$B,'Expenses Analysis'!$B25,'Data Repository Table'!$F:$F,'Expenses Analysis'!$C25,'Data Repository Table'!$G:$G,'Expenses Analysis'!$D25,'Data Repository Table'!$D:$D,'Expenses Analysis'!M$12) -> 4767948.2 | ... Q25: =SUMIFS('Data Repository Table'!$I:$I,'Data Repository Table'!$C:$C,'Expenses Analysis'!$A25,'Data Repository Table'!$B:$B,'Expenses Analysis'!$B25,'Data Repository Table'!$F:$F,'Expenses Analysis'!$C25,'Data Repository Table'!$G:$G,'Expenses Analysis'!$D25,'Data Repository Table'!$D:$D,'Expenses Analysis'!Q$12) -> 2269805.2 | R25: =SUM(F25:Q25) -> 46326013
A26: Surjek | B26: Expenses | C26: Facility Costs | D26: Utility-Exp (002) - Heating | F26: =SUMIFS('Data Repository Table'!$I:$I,'Data Repository Table'!$C:$C,'Expenses Analysis'!$A26,'Data Repository Table'!$B:$B,'Expenses Analysis'!$B26,'Data Repository Table'!$F:$F,'Expenses Analysis'!$C26,'Data Repository Table'!$G:$G,'Expenses Analysis'!$D26,'Data Repository Table'!$D:$D,'Expenses Analysis'!F$12) -> 1266517.3 | G26: =SUMIFS('Data Repository Table'!$I:$I,'Data Repository Table'!$C:$C,'Expenses Analysis'!$A26,'Data Repository Table'!$B:$B,'Expenses Analysis'!$B26,'Data Repository Table'!$F:$F,'Expenses Analysis'!$C26,'Data Repository Table'!$G:$G,'Expenses Analysis'!$D26,'Data Repository Table'!$D:$D,'Expenses Analysis'!G$12) -> 1525787.1 | H26: =SUMIFS('Data Repository Table'!$I:$I,'Data Repository Table'!$C:$C,'Expenses Analysis'!$A26,'Data Repository Table'!$B:$B,'Expenses Analysis'!$B26,'Data Repository Table'!$F:$F,'Expenses Analysis'!$C26,'Data Repository Table'!$G:$G,'Expenses Analysis'!$D26,'Data Repository Table'!$D:$D,'Expenses Analysis'!H$12) -> 1542101.4 | I26: =SUMIFS('Data Repository Table'!$I:$I,'Data Repository Table'!$C:$C,'Expenses Analysis'!$A26,'Data Repository Table'!$B:$B,'Expenses Analysis'!$B26,'Data Repository Table'!$F:$F,'Expenses Analysis'!$C26,'Data Repository Table'!$G:$G,'Expenses Analysis'!$D26,'Data Repository Table'!$D:$D,'Expenses Analysis'!I$12) -> 2067601.4 | J26: =SUMIFS('Data Repository Table'!$I:$I,'Data Repository Table'!$C:$C,'Expenses Analysis'!$A26,'Data Repository Table'!$B:$B,'Expenses Analysis'!$B26,'Data Repository Table'!$F:$F,'Expenses Analysis'!$C26,'Data Repository Table'!$G:$G,'Expenses Analysis'!$D26,'Data Repository Table'!$D:$D,'Expenses Analysis'!J$12) -> 2236637.9 | K26: =SUMIFS('Data Repository Table'!$I:$I,'Data Repository Table'!$C:$C,'Expenses Analysis'!$A26,'Data Repository Table'!$B:$B,'Expenses Analysis'!$B26,'Data Repository Table'!$F:$F,'Expenses Analysis'!$C26,'Data Repository Table'!$G:$G,'Expenses Analysis'!$D26,'Data Repository Table'!$D:$D,'Expenses Analysis'!K$12) -> 1732479 | L26: =SUMIFS('Data Repository Table'!$I:$I,'Data Repository Table'!$C:$C,'Expenses Analysis'!$A26,'Data Repository Table'!$B:$B,'Expenses Analysis'!$B26,'Data Repository Table'!$F:$F,'Expenses Analysis'!$C26,'Data Repository Table'!$G:$G,'Expenses Analysis'!$D26,'Data Repository Table'!$D:$D,'Expenses Analysis'!L$12) -> 2024821.4 | M26: =SUMIFS('Data Repository Table'!$I:$I,'Data Repository Table'!$C:$C,'Expenses Analysis'!$A26,'Data Repository Table'!$B:$B,'Expenses Analysis'!$B26,'Data Repository Table'!$F:$F,'Expenses Analysis'!$C26,'Data Repository Table'!$G:$G,'Expenses Analysis'!$D26,'Data Repository Table'!$D:$D,'Expenses Analysis'!M$12) -> 2383974.1 | ... Q26: =SUMIFS('Data Repository Table'!$I:$I,'Data Repository Table'!$C:$C,'Expenses Analysis'!$A26,'Data Repository Table'!$B:$B,'Expenses Analysis'!$B26,'Data Repository Table'!$F:$F,'Expenses Analysis'!$C26,'Data Repository Table'!$G:$G,'Expenses Analysis'!$D26,'Data Repository Table'!$D:$D,'Expenses Analysis'!Q$12) -> 1134902.6 | R26: =SUM(F26:Q26) -> 23163006
A27: Surjek | B27: Expenses | C27: Facility Costs | D27: Utility-Exp (002) - Electricity | F27: =SUMIFS('Data Repository Table'!$I:$I,'Data Repository Table'!$C:$C,'Expenses Analysis'!$A27,'Data Repository Table'!$B:$B,'Expenses Analysis'!$B27,'Data Repository Table'!$F:$F,'Expenses Analysis'!$C27,'Data Repository Table'!$G:$G,'Expenses Analysis'!$D27,'Data Repository Table'!$D:$D,'Expenses Analysis'!F$12) -> 1055431 | G27: =SUMIFS('Data Repository Table'!$I:$I,'Data Repository Table'!$C:$C,'Expenses Analysis'!$A27,'Data Repository Table'!$B:$B,'Expenses Analysis'!$B27,'Data Repository Table'!$F:$F,'Expenses Analysis'!$C27,'Data Repository Table'!$G:$G,'Expenses Analysis'!$D27,'Data Repository Table'!$D:$D,'Expenses Analysis'!G$12) -> 1271489.2 | H27: =SUMIFS('Data Repository Table'!$I:$I,'Data Repository Table'!$C:$C,'Expenses Analysis'!$A27,'Data Repository Table'!$B:$B,'Expenses Analysis'!$B27,'Data Repository Table'!$F:$F,'Expenses Analysis'!$C27,'Data Repository Table'!$G:$G,'Expenses Analysis'!$D27,'Data Repository Table'!$D:$D,'Expenses Analysis'!H$12) -> 1285084.5 | I27: =SUMIFS('Data Repository Table'!$I:$I,'Data Repository Table'!$C:$C,'Expenses Analysis'!$A27,'Data Repository Table'!$B:$B,'Expenses Analysis'!$B27,'Data Repository Table'!$F:$F,'Expenses Analysis'!$C27,'Data Repository Table'!$G:$G,'Expenses Analysis'!$D27,'Data Repository Table'!$D:$D,'Expenses Analysis'!I$12) -> 1723001.2 | J27: =SUMIFS('Data Repository Table'!$I:$I,'Data Repository Table'!$C:$C,'Expenses Analysis'!$A27,'Data Repository Table'!$B:$B,'Expenses Analysis'!$B27,'Data Repository Table'!$F:$F,'Expenses Analysis'!$C27,'Data Repository Table'!$G:$G,'Expenses Analysis'!$D27,'Data Repository Table'!$D:$D,'Expenses Analysis'!J$12) -> 1863865 | K27: =SUMIFS('Data Repository Table'!$I:$I,'Data Repository Table'!$C:$C,'Expenses Analysis'!$A27,'Data Repository Table'!$B:$B,'Expenses Analysis'!$B27,'Data Repository Table'!$F:$F,'Expenses Analysis'!$C27,'Data Repository Table'!$G:$G,'Expenses Analysis'!$D27,'Data Repository Table'!$D:$D,'Expenses Analysis'!K$12) -> 1443732.5 | L27: =SUMIFS('Data Repository Table'!$I:$I,'Data Repository Table'!$C:$C,'Expenses Analysis'!$A27,'Data Repository Table'!$B:$B,'Expenses Analysis'!$B27,'Data Repository Table'!$F:$F,'Expenses Analysis'!$C27,'Data Repository Table'!$G:$G,'Expenses Analysis'!$D27,'Data Repository Table'!$D:$D,'Expenses Analysis'!L$12) -> 1687351.2 | M27: =SUMIFS('Data Repository Table'!$I:$I,'Data Repository Table'!$C:$C,'Expenses Analysis'!$A27,'Data Repository Table'!$B:$B,'Expenses Analysis'!$B27,'Data Repository Table'!$F:$F,'Expenses Analysis'!$C27,'Data Repository Table'!$G:$G,'Expenses Analysis'!$D27,'Data Repository Table'!$D:$D,'Expenses Analysis'!M$12) -> 1986645.1 | ... Q27: =SUMIFS('Data Repository Table'!$I:$I,'Data Repository Table'!$C:$C,'Expenses Analysis'!$A27,'Data Repository Table'!$B:$B,'Expenses Analysis'!$B27,'Data Repository Table'!$F:$F,'Expenses Analysis'!$C27,'Data Repository Table'!$G:$G,'Expenses Analysis'!$D27,'Data Repository Table'!$D:$D,'Expenses Analysis'!Q$12) -> 945752.15 | R27: =SUM(F27:Q27) -> 19302505
A28: Surjek | B28: Expenses | C28: Operational Maintenance Costs | D28: Plant Maintenance (001) | F28: =SUMIFS('Data Repository Table'!$I:$I,'Data Repository Table'!$C:$C,'Expenses Analysis'!$A28,'Data Repository Table'!$B:$B,'Expenses Analysis'!$B28,'Data Repository Table'!$F:$F,'Expenses Analysis'!$C28,'Data Repository Table'!$G:$G,'Expenses Analysis'!$D28,'Data Repository Table'!$D:$D,'Expenses Analysis'!F$12) -> 996326.91 | G28: =SUMIFS('Data Repository Table'!$I:$I,'Data Repository Table'!$C:$C,'Expenses Analysis'!$A28,'Data Repository Table'!$B:$B,'Expenses Analysis'!$B28,'Data Repository Table'!$F:$F,'Expenses Analysis'!$C28,'Data Repository Table'!$G:$G,'Expenses Analysis'!$D28,'Data Repository Table'!$D:$D,'Expenses Analysis'!G$12) -> 1200285.8 | H28: =SUMIFS('Data Repository Table'!$I:$I,'Data Repository Table'!$C:$C,'Expenses Analysis'!$A28,'Data Repository Table'!$B:$B,'Expenses Analysis'!$B28,'Data Repository Table'!$F:$F,'Expenses Analysis'!$C28,'Data Repository Table'!$G:$G,'Expenses Analysis'!$D28,'Data Repository Table'!$D:$D,'Expenses Analysis'!H$12) -> 1213119.8 | I28: =SUMIFS('Data Repository Table'!$I:$I,'Data Repository Table'!$C:$C,'Expenses Analysis'!$A28,'Data Repository Table'!$B:$B,'Expenses Analysis'!$B28,'Data Repository Table'!$F:$F,'Expenses Analysis'!$C28,'Data Repository Table'!$G:$G,'Expenses Analysis'!$D28,'Data Repository Table'!$D:$D,'Expenses Analysis'!I$12) -> 1626513.1 | J28: =SUMIFS('Data Repository Table'!$I:$I,'Data Repository Table'!$C:$C,'Expenses Analysis'!$A28,'Data Repository Table'!$B:$B,'Expenses Analysis'!$B28,'Data Repository Table'!$F:$F,'Expenses Analysis'!$C28,'Data Repository Table'!$G:$G,'Expenses Analysis'!$D28,'Data Repository Table'!$D:$D,'Expenses Analysis'!J$12) -> 1759488.5 | K28: =SUMIFS('Data Repository Table'!$I:$I,'Data Repository Table'!$C:$C,'Expenses Analysis'!$A28,'Data Repository Table'!$B:$B,'Expenses Analysis'!$B28,'Data Repository Table'!$F:$F,'Expenses Analysis'!$C28,'Data Repository Table'!$G:$G,'Expenses Analysis'!$D28,'Data Repository Table'!$D:$D,'Expenses Analysis'!K$12) -> 1362883.5 | L28: =SUMIFS('Data Repository Table'!$I:$I,'Data Repository Table'!$C:$C,'Expenses Analysis'!$A28,'Data Repository Table'!$B:$B,'Expenses Analysis'!$B28,'Data Repository Table'!$F:$F,'Expenses Analysis'!$C28,'Data Repository Table'!$G:$G,'Expenses Analysis'!$D28,'Data Repository Table'!$D:$D,'Expenses Analysis'!L$12) -> 1592859.5 | M28: =SUMIFS('Data Repository Table'!$I:$I,'Data Repository Table'!$C:$C,'Expenses Analysis'!$A28,'Data Repository Table'!$B:$B,'Expenses Analysis'!$B28,'Data Repository Table'!$F:$F,'Expenses Analysis'!$C28,'Data Repository Table'!$G:$G,'Expenses Analysis'!$D28,'Data Repository Table'!$D:$D,'Expenses Analysis'!M$12) -> 1875393 | ... Q28: =SUMIFS('Data Repository Table'!$I:$I,'Data Repository Table'!$C:$C,'Expenses Analysis'!$A28,'Data Repository Table'!$B:$B,'Expenses Analysis'!$B28,'Data Repository Table'!$F:$F,'Expenses Analysis'!$C28,'Data Repository Table'!$G:$G,'Expenses Analysis'!$D28,'Data Repository Table'!$D:$D,'Expenses Analysis'!Q$12) -> 892790.03 | R28: =SUM(F28:Q28) -> 18221565
A29: Surjek | B29: Expenses | C29: Operational Maintenance Costs | D29: Plant Outages (002) | F29: =SUMIFS('Data Repository Table'!$I:$I,'Data Repository Table'!$C:$C,'Expenses Analysis'!$A29,'Data Repository Table'!$B:$B,'Expenses Analysis'!$B29,'Data Repository Table'!$F:$F,'Expenses Analysis'!$C29,'Data Repository Table'!$G:$G,'Expenses Analysis'!$D29,'Data Repository Table'!$D:$D,'Expenses Analysis'!F$12) -> 869931.04 | G29: =SUMIFS('Data Repository Table'!$I:$I,'Data Repository Table'!$C:$C,'Expenses Analysis'!$A29,'Data Repository Table'!$B:$B,'Expenses Analysis'!$B29,'Data Repository Table'!$F:$F,'Expenses Analysis'!$C29,'Data Repository Table'!$G:$G,'Expenses Analysis'!$D29,'Data Repository Table'!$D:$D,'Expenses Analysis'!G$12) -> 1048015.4 | H29: =SUMIFS('Data Repository Table'!$I:$I,'Data Repository Table'!$C:$C,'Expenses Analysis'!$A29,'Data Repository Table'!$B:$B,'Expenses Analysis'!$B29,'Data Repository Table'!$F:$F,'Expenses Analysis'!$C29,'Data Repository Table'!$G:$G,'Expenses Analysis'!$D29,'Data Repository Table'!$D:$D,'Expenses Analysis'!H$12) -> 1059221.1 | I29: =SUMIFS('Data Repository Table'!$I:$I,'Data Repository Table'!$C:$C,'Expenses Analysis'!$A29,'Data Repository Table'!$B:$B,'Expenses Analysis'!$B29,'Data Repository Table'!$F:$F,'Expenses Analysis'!$C29,'Data Repository Table'!$G:$G,'Expenses Analysis'!$D29,'Data Repository Table'!$D:$D,'Expenses Analysis'!I$12) -> 1420170.6 | J29: =SUMIFS('Data Repository Table'!$I:$I,'Data Repository Table'!$C:$C,'Expenses Analysis'!$A29,'Data Repository Table'!$B:$B,'Expenses Analysis'!$B29,'Data Repository Table'!$F:$F,'Expenses Analysis'!$C29,'Data Repository Table'!$G:$G,'Expenses Analysis'!$D29,'Data Repository Table'!$D:$D,'Expenses Analysis'!J$12) -> 1536276.6 | K29: =SUMIFS('Data Repository Table'!$I:$I,'Data Repository Table'!$C:$C,'Expenses Analysis'!$A29,'Data Repository Table'!$B:$B,'Expenses Analysis'!$B29,'Data Repository Table'!$F:$F,'Expenses Analysis'!$C29,'Data Repository Table'!$G:$G,'Expenses Analysis'!$D29,'Data Repository Table'!$D:$D,'Expenses Analysis'!K$12) -> 785390.46 | L29: =SUMIFS('Data Repository Table'!$I:$I,'Data Repository Table'!$C:$C,'Expenses Analysis'!$A29,'Data Repository Table'!$B:$B,'Expenses Analysis'!$B29,'Data Repository Table'!$F:$F,'Expenses Analysis'!$C29,'Data Repository Table'!$G:$G,'Expenses Analysis'!$D29,'Data Repository Table'!$D:$D,'Expenses Analysis'!L$12) -> 734335.23 | M29: =SUMIFS('Data Repository Table'!$I:$I,'Data Repository Table'!$C:$C,'Expenses Analysis'!$A29,'Data Repository Table'!$B:$B,'Expenses Analysis'!$B29,'Data Repository Table'!$F:$F,'Expenses Analysis'!$C29,'Data Repository Table'!$G:$G,'Expenses Analysis'!$D29,'Data Repository Table'!$D:$D,'Expenses Analysis'!M$12) -> 864587.94 | ... Q29: =SUMIFS('Data Repository Table'!$I:$I,'Data Repository Table'!$C:$C,'Expenses Analysis'!$A29,'Data Repository Table'!$B:$B,'Expenses Analysis'!$B29,'Data Repository Table'!$F:$F,'Expenses Analysis'!$C29,'Data Repository Table'!$G:$G,'Expenses Analysis'!$D29,'Data Repository Table'!$D:$D,'Expenses Analysis'!Q$12) -> 514489.17 | R29: =SUM(F29:Q29) -> 11461092
A30: Surjek | B30: Expenses | C30: Operational Maintenance Costs | D30: Plant Op. Costs (003) | F30: =SUMIFS('Data Repository Table'!$I:$I,'Data Repository Table'!$C:$C,'Expenses Analysis'!$A30,'Data Repository Table'!$B:$B,'Expenses Analysis'!$B30,'Data Repository Table'!$F:$F,'Expenses Analysis'!$C30,'Data Repository Table'!$G:$G,'Expenses Analysis'!$D30,'Data Repository Table'!$D:$D,'Expenses Analysis'!F$12) -> 921103.46 | G30: =SUMIFS('Data Repository Table'!$I:$I,'Data Repository Table'!$C:$C,'Expenses Analysis'!$A30,'Data Repository Table'!$B:$B,'Expenses Analysis'!$B30,'Data Repository Table'!$F:$F,'Expenses Analysis'!$C30,'Data Repository Table'!$G:$G,'Expenses Analysis'!$D30,'Data Repository Table'!$D:$D,'Expenses Analysis'!G$12) -> 1109663.3 | H30: =SUMIFS('Data Repository Table'!$I:$I,'Data Repository Table'!$C:$C,'Expenses Analysis'!$A30,'Data Repository Table'!$B:$B,'Expenses Analysis'!$B30,'Data Repository Table'!$F:$F,'Expenses Analysis'!$C30,'Data Repository Table'!$G:$G,'Expenses Analysis'!$D30,'Data Repository Table'!$D:$D,'Expenses Analysis'!H$12) -> 1121528.3 | I30: =SUMIFS('Data Repository Table'!$I:$I,'Data Repository Table'!$C:$C,'Expenses Analysis'!$A30,'Data Repository Table'!$B:$B,'Expenses Analysis'!$B30,'Data Repository Table'!$F:$F,'Expenses Analysis'!$C30,'Data Repository Table'!$G:$G,'Expenses Analysis'!$D30,'Data Repository Table'!$D:$D,'Expenses Analysis'!I$12) -> 1503710.1 | J30: =SUMIFS('Data Repository Table'!$I:$I,'Data Repository Table'!$C:$C,'Expenses Analysis'!$A30,'Data Repository Table'!$B:$B,'Expenses Analysis'!$B30,'Data Repository Table'!$F:$F,'Expenses Analysis'!$C30,'Data Repository Table'!$G:$G,'Expenses Analysis'!$D30,'Data Repository Table'!$D:$D,'Expenses Analysis'!J$12) -> 1626645.8 | K30: =SUMIFS('Data Repository Table'!$I:$I,'Data Repository Table'!$C:$C,'Expenses Analysis'!$A30,'Data Repository Table'!$B:$B,'Expenses Analysis'!$B30,'Data Repository Table'!$F:$F,'Expenses Analysis'!$C30,'Data Repository Table'!$G:$G,'Expenses Analysis'!$D30,'Data Repository Table'!$D:$D,'Expenses Analysis'!K$12) -> 831589.9 | L30: =SUMIFS('Data Repository Table'!$I:$I,'Data Repository Table'!$C:$C,'Expenses Analysis'!$A30,'Data Repository Table'!$B:$B,'Expenses Analysis'!$B30,'Data Repository Table'!$F:$F,'Expenses Analysis'!$C30,'Data Repository Table'!$G:$G,'Expenses Analysis'!$D30,'Data Repository Table'!$D:$D,'Expenses Analysis'!L$12) -> 777531.42 | M30: =SUMIFS('Data Repository Table'!$I:$I,'Data Repository Table'!$C:$C,'Expenses Analysis'!$A30,'Data Repository Table'!$B:$B,'Expenses Analysis'!$B30,'Data Repository Table'!$F:$F,'Expenses Analysis'!$C30,'Data Repository Table'!$G:$G,'Expenses Analysis'!$D30,'Data Repository Table'!$D:$D,'Expenses Analysis'!M$12) -> 915446.06 | ... Q30: =SUMIFS('Data Repository Table'!$I:$I,'Data Repository Table'!$C:$C,'Expenses Analysis'!$A30,'Data Repository Table'!$B:$B,'Expenses Analysis'!$B30,'Data Repository Table'!$F:$F,'Expenses Analysis'!$C30,'Data Repository Table'!$G:$G,'Expenses Analysis'!$D30,'Data Repository Table'!$D:$D,'Expenses Analysis'!Q$12) -> 544753.24 | R30: =SUM(F30:Q30) -> 12135274
A31: Surjek | B31: Expenses | C31: Operational Maintenance Costs | D31: Plant Admin Costs (004) | F31: =SUMIFS('Data Repository Table'!$I:$I,'Data Repository Table'!$C:$C,'Expenses Analysis'!$A31,'Data Repository Table'!$B:$B,'Expenses Analysis'!$B31,'Data Repository Table'!$F:$F,'Expenses Analysis'!$C31,'Data Repository Table'!$G:$G,'Expenses Analysis'!$D31,'Data Repository Table'!$D:$D,'Expenses Analysis'!F$12) -> 498931.04 | G31: =SUMIFS('Data Repository Table'!$I:$I,'Data Repository Table'!$C:$C,'Expenses Analysis'!$A31,'Data Repository Table'!$B:$B,'Expenses Analysis'!$B31,'Data Repository Table'!$F:$F,'Expenses Analysis'!$C31,'Data Repository Table'!$G:$G,'Expenses Analysis'!$D31,'Data Repository Table'!$D:$D,'Expenses Analysis'!G$12) -> 601067.64 | H31: =SUMIFS('Data Repository Table'!$I:$I,'Data Repository Table'!$C:$C,'Expenses Analysis'!$A31,'Data Repository Table'!$B:$B,'Expenses Analysis'!$B31,'Data Repository Table'!$F:$F,'Expenses Analysis'!$C31,'Data Repository Table'!$G:$G,'Expenses Analysis'!$D31,'Data Repository Table'!$D:$D,'Expenses Analysis'!H$12) -> 607494.48 | I31: =SUMIFS('Data Repository Table'!$I:$I,'Data Repository Table'!$C:$C,'Expenses Analysis'!$A31,'Data Repository Table'!$B:$B,'Expenses Analysis'!$B31,'Data Repository Table'!$F:$F,'Expenses Analysis'!$C31,'Data Repository Table'!$G:$G,'Expenses Analysis'!$D31,'Data Repository Table'!$D:$D,'Expenses Analysis'!I$12) -> 814509.64 | J31: =SUMIFS('Data Repository Table'!$I:$I,'Data Repository Table'!$C:$C,'Expenses Analysis'!$A31,'Data Repository Table'!$B:$B,'Expenses Analysis'!$B31,'Data Repository Table'!$F:$F,'Expenses Analysis'!$C31,'Data Repository Table'!$G:$G,'Expenses Analysis'!$D31,'Data Repository Table'!$D:$D,'Expenses Analysis'!J$12) -> 881099.8 | K31: =SUMIFS('Data Repository Table'!$I:$I,'Data Repository Table'!$C:$C,'Expenses Analysis'!$A31,'Data Repository Table'!$B:$B,'Expenses Analysis'!$B31,'Data Repository Table'!$F:$F,'Expenses Analysis'!$C31,'Data Repository Table'!$G:$G,'Expenses Analysis'!$D31,'Data Repository Table'!$D:$D,'Expenses Analysis'!K$12) -> 450444.53 | L31: =SUMIFS('Data Repository Table'!$I:$I,'Data Repository Table'!$C:$C,'Expenses Analysis'!$A31,'Data Repository Table'!$B:$B,'Expenses Analysis'!$B31,'Data Repository Table'!$F:$F,'Expenses Analysis'!$C31,'Data Repository Table'!$G:$G,'Expenses Analysis'!$D31,'Data Repository Table'!$D:$D,'Expenses Analysis'!L$12) -> 421162.85 | M31: =SUMIFS('Data Repository Table'!$I:$I,'Data Repository Table'!$C:$C,'Expenses Analysis'!$A31,'Data Repository Table'!$B:$B,'Expenses Analysis'!$B31,'Data Repository Table'!$F:$F,'Expenses Analysis'!$C31,'Data Repository Table'!$G:$G,'Expenses Analysis'!$D31,'Data Repository Table'!$D:$D,'Expenses Analysis'!M$12) -> 495866.62 | ... Q31: =SUMIFS('Data Repository Table'!$I:$I,'Data Repository Table'!$C:$C,'Expenses Analysis'!$A31,'Data Repository Table'!$B:$B,'Expenses Analysis'!$B31,'Data Repository Table'!$F:$F,'Expenses Analysis'!$C31,'Data Repository Table'!$G:$G,'Expenses Analysis'!$D31,'Data Repository Table'!$D:$D,'Expenses Analysis'!Q$12) -> 295074.67 | R31: =SUM(F31:Q31) -> 6573273.6
A32: Surjek | B32: Expenses | C32: Labour Costs | D32: Labour-Costs (001) | F32: =SUMIFS('Data Repository Table'!$I:$I,'Data Repository Table'!$C:$C,'Expenses Analysis'!$A32,'Data Repository Table'!$B:$B,'Expenses Analysis'!$B32,'Data Repository Table'!$F:$F,'Expenses Analysis'!$C32,'Data Repository Table'!$G:$G,'Expenses Analysis'!$D32,'Data Repository Table'!$D:$D,'Expenses Analysis'!F$12) -> 3198275.9 | G32: =SUMIFS('Data Repository Table'!$I:$I,'Data Repository Table'!$C:$C,'Expenses Analysis'!$A32,'Data Repository Table'!$B:$B,'Expenses Analysis'!$B32,'Data Repository Table'!$F:$F,'Expenses Analysis'!$C32,'Data Repository Table'!$G:$G,'Expenses Analysis'!$D32,'Data Repository Table'!$D:$D,'Expenses Analysis'!G$12) -> 3852997.7 | H32: =SUMIFS('Data Repository Table'!$I:$I,'Data Repository Table'!$C:$C,'Expenses Analysis'!$A32,'Data Repository Table'!$B:$B,'Expenses Analysis'!$B32,'Data Repository Table'!$F:$F,'Expenses Analysis'!$C32,'Data Repository Table'!$G:$G,'Expenses Analysis'!$D32,'Data Repository Table'!$D:$D,'Expenses Analysis'!H$12) -> 3894195.4 | I32: =SUMIFS('Data Repository Table'!$I:$I,'Data Repository Table'!$C:$C,'Expenses Analysis'!$A32,'Data Repository Table'!$B:$B,'Expenses Analysis'!$B32,'Data Repository Table'!$F:$F,'Expenses Analysis'!$C32,'Data Repository Table'!$G:$G,'Expenses Analysis'!$D32,'Data Repository Table'!$D:$D,'Expenses Analysis'!I$12) -> 5221215.6 | J32: =SUMIFS('Data Repository Table'!$I:$I,'Data Repository Table'!$C:$C,'Expenses Analysis'!$A32,'Data Repository Table'!$B:$B,'Expenses Analysis'!$B32,'Data Repository Table'!$F:$F,'Expenses Analysis'!$C32,'Data Repository Table'!$G:$G,'Expenses Analysis'!$D32,'Data Repository Table'!$D:$D,'Expenses Analysis'!J$12) -> 5648075.6 | K32: =SUMIFS('Data Repository Table'!$I:$I,'Data Repository Table'!$C:$C,'Expenses Analysis'!$A32,'Data Repository Table'!$B:$B,'Expenses Analysis'!$B32,'Data Repository Table'!$F:$F,'Expenses Analysis'!$C32,'Data Repository Table'!$G:$G,'Expenses Analysis'!$D32,'Data Repository Table'!$D:$D,'Expenses Analysis'!K$12) -> 2887464.9 | L32: =SUMIFS('Data Repository Table'!$I:$I,'Data Repository Table'!$C:$C,'Expenses Analysis'!$A32,'Data Repository Table'!$B:$B,'Expenses Analysis'!$B32,'Data Repository Table'!$F:$F,'Expenses Analysis'!$C32,'Data Repository Table'!$G:$G,'Expenses Analysis'!$D32,'Data Repository Table'!$D:$D,'Expenses Analysis'!L$12) -> 2699761.9 | M32: =SUMIFS('Data Repository Table'!$I:$I,'Data Repository Table'!$C:$C,'Expenses Analysis'!$A32,'Data Repository Table'!$B:$B,'Expenses Analysis'!$B32,'Data Repository Table'!$F:$F,'Expenses Analysis'!$C32,'Data Repository Table'!$G:$G,'Expenses Analysis'!$D32,'Data Repository Table'!$D:$D,'Expenses Analysis'!M$12) -> 3178632.1 | ... Q32: =SUMIFS('Data Repository Table'!$I:$I,'Data Repository Table'!$C:$C,'Expenses Analysis'!$A32,'Data Repository Table'!$B:$B,'Expenses Analysis'!$B32,'Data Repository Table'!$F:$F,'Expenses Analysis'!$C32,'Data Repository Table'!$G:$G,'Expenses Analysis'!$D32,'Data Repository Table'!$D:$D,'Expenses Analysis'!Q$12) -> 1891504.3 | R32: =SUM(F32:Q32) -> 42136369
D33: Total | F33: =SUM(F25:F32) -> 11339551 | G33: =SUM(G25:G32) -> 13660880 | H33: =SUM(H25:H32) -> 13806948 | I33: =SUM(I25:I32) -> 18511924 | J33: =SUM(J25:J32) -> 20025365 | K33: =SUM(K25:K32) -> 12958943 | L33: =SUM(L25:L32) -> 13987466 | M33: =SUM(M25:M32) -> 16468493 | ... R33: =SUM(R25:R32) -> 1.793191e+08
R34: Total
A35: Jutik | B35: Expenses | C35: Chemical Costs | D35: Chem-Exp (001) | F35: =SUMIFS('Data Repository Table'!$I:$I,'Data Repository Table'!$C:$C,'Expenses Analysis'!$A35,'Data Repository Table'!$B:$B,'Expenses Analysis'!$B35,'Data Repository Table'!$F:$F,'Expenses Analysis'!$C35,'Data Repository Table'!$G:$G,'Expenses Analysis'!$D35,'Data Repository Table'!$D:$D,'Expenses Analysis'!F$12) -> 1625596.3 | G35: =SUMIFS('Data Repository Table'!$I:$I,'Data Repository Table'!$C:$C,'Expenses Analysis'!$A35,'Data Repository Table'!$B:$B,'Expenses Analysis'!$B35,'Data Repository Table'!$F:$F,'Expenses Analysis'!$C35,'Data Repository Table'!$G:$G,'Expenses Analysis'!$D35,'Data Repository Table'!$D:$D,'Expenses Analysis'!G$12) -> 1295067.8 | H35: =SUMIFS('Data Repository Table'!$I:$I,'Data Repository Table'!$C:$C,'Expenses Analysis'!$A35,'Data Repository Table'!$B:$B,'Expenses Analysis'!$B35,'Data Repository Table'!$F:$F,'Expenses Analysis'!$C35,'Data Repository Table'!$G:$G,'Expenses Analysis'!$D35,'Data Repository Table'!$D:$D,'Expenses Analysis'!H$12) -> 1750624.9 | I35: =SUMIFS('Data Repository Table'!$I:$I,'Data Repository Table'!$C:$C,'Expenses Analysis'!$A35,'Data Repository Table'!$B:$B,'Expenses Analysis'!$B35,'Data Repository Table'!$F:$F,'Expenses Analysis'!$C35,'Data Repository Table'!$G:$G,'Expenses Analysis'!$D35,'Data Repository Table'!$D:$D,'Expenses Analysis'!I$12) -> 1472529.4 | J35: =SUMIFS('Data Repository Table'!$I:$I,'Data Repository Table'!$C:$C,'Expenses Analysis'!$A35,'Data Repository Table'!$B:$B,'Expenses Analysis'!$B35,'Data Repository Table'!$F:$F,'Expenses Analysis'!$C35,'Data Repository Table'!$G:$G,'Expenses Analysis'!$D35,'Data Repository Table'!$D:$D,'Expenses Analysis'!J$12) -> 1252200.5 | K35: =SUMIFS('Data Repository Table'!$I:$I,'Data Repository Table'!$C:$C,'Expenses Analysis'!$A35,'Data Repository Table'!$B:$B,'Expenses Analysis'!$B35,'Data Repository Table'!$F:$F,'Expenses Analysis'!$C35,'Data Repository Table'!$G:$G,'Expenses Analysis'!$D35,'Data Repository Table'!$D:$D,'Expenses Analysis'!K$12) -> 1406782.7 | L35: =SUMIFS('Data Repository Table'!$I:$I,'Data Repository Table'!$C:$C,'Expenses Analysis'!$A35,'Data Repository Table'!$B:$B,'Expenses Analysis'!$B35,'Data Repository Table'!$F:$F,'Expenses Analysis'!$C35,'Data Repository Table'!$G:$G,'Expenses Analysis'!$D35,'Data Repository Table'!$D:$D,'Expenses Analysis'!L$12) -> 1877449.5 | M35: =SUMIFS('Data Repository Table'!$I:$I,'Data Repository Table'!$C:$C,'Expenses Analysis'!$A35,'Data Repository Table'!$B:$B,'Expenses Analysis'!$B35,'Data Repository Table'!$F:$F,'Expenses Analysis'!$C35,'Data Repository Table'!$G:$G,'Expenses Analysis'!$D35,'Data Repository Table'!$D:$D,'Expenses Analysis'!M$12) -> 1912219.2 | ... Q35: =SUMIFS('Data Repository Table'!$I:$I,'Data Repository Table'!$C:$C,'Expenses Analysis'!$A35,'Data Repository Table'!$B:$B,'Expenses Analysis'!$B35,'Data Repository Table'!$F:$F,'Expenses Analysis'!$C35,'Data Repository Table'!$G:$G,'Expenses Analysis'!$D35,'Data Repository Table'!$D:$D,'Expenses Analysis'!Q$12) -> 2274807.8 | R35: =SUM(F35:Q35) -> 21961819
A36: Jutik | B36: Expenses | C36: Facility Costs | D36: Utility-Exp (002) - Heating | F36: =SUMIFS('Data Repository Table'!$I:$I,'Data Repository Table'!$C:$C,'Expenses Analysis'!$A36,'Data Repository Table'!$B:$B,'Expenses Analysis'!$B36,'Data Repository Table'!$F:$F,'Expenses Analysis'!$C36,'Data Repository Table'!$G:$G,'Expenses Analysis'!$D36,'Data Repository Table'!$D:$D,'Expenses Analysis'!F$12) -> 895736.76 | G36: =SUMIFS('Data Repository Table'!$I:$I,'Data Repository Table'!$C:$C,'Expenses Analysis'!$A36,'Data Repository Table'!$B:$B,'Expenses Analysis'!$B36,'Data Repository Table'!$F:$F,'Expenses Analysis'!$C36,'Data Repository Table'!$G:$G,'Expenses Analysis'!$D36,'Data Repository Table'!$D:$D,'Expenses Analysis'!G$12) -> 713608.81 | H36: =SUMIFS('Data Repository Table'!$I:$I,'Data Repository Table'!$C:$C,'Expenses Analysis'!$A36,'Data Repository Table'!$B:$B,'Expenses Analysis'!$B36,'Data Repository Table'!$F:$F,'Expenses Analysis'!$C36,'Data Repository Table'!$G:$G,'Expenses Analysis'!$D36,'Data Repository Table'!$D:$D,'Expenses Analysis'!H$12) -> 964630.04 | I36: =SUMIFS('Data Repository Table'!$I:$I,'Data Repository Table'!$C:$C,'Expenses Analysis'!$A36,'Data Repository Table'!$B:$B,'Expenses Analysis'!$B36,'Data Repository Table'!$F:$F,'Expenses Analysis'!$C36,'Data Repository Table'!$G:$G,'Expenses Analysis'!$D36,'Data Repository Table'!$D:$D,'Expenses Analysis'!I$12) -> 811393.74 | J36: =SUMIFS('Data Repository Table'!$I:$I,'Data Repository Table'!$C:$C,'Expenses Analysis'!$A36,'Data Repository Table'!$B:$B,'Expenses Analysis'!$B36,'Data Repository Table'!$F:$F,'Expenses Analysis'!$C36,'Data Repository Table'!$G:$G,'Expenses Analysis'!$D36,'Data Repository Table'!$D:$D,'Expenses Analysis'!J$12) -> 689988.03 | K36: =SUMIFS('Data Repository Table'!$I:$I,'Data Repository Table'!$C:$C,'Expenses Analysis'!$A36,'Data Repository Table'!$B:$B,'Expenses Analysis'!$B36,'Data Repository Table'!$F:$F,'Expenses Analysis'!$C36,'Data Repository Table'!$G:$G,'Expenses Analysis'!$D36,'Data Repository Table'!$D:$D,'Expenses Analysis'!K$12) -> 775165.96 | L36: =SUMIFS('Data Repository Table'!$I:$I,'Data Repository Table'!$C:$C,'Expenses Analysis'!$A36,'Data Repository Table'!$B:$B,'Expenses Analysis'!$B36,'Data Repository Table'!$F:$F,'Expenses Analysis'!$C36,'Data Repository Table'!$G:$G,'Expenses Analysis'!$D36,'Data Repository Table'!$D:$D,'Expenses Analysis'!L$12) -> 1034513 | M36: =SUMIFS('Data Repository Table'!$I:$I,'Data Repository Table'!$C:$C,'Expenses Analysis'!$A36,'Data Repository Table'!$B:$B,'Expenses Analysis'!$B36,'Data Repository Table'!$F:$F,'Expenses Analysis'!$C36,'Data Repository Table'!$G:$G,'Expenses Analysis'!$D36,'Data Repository Table'!$D:$D,'Expenses Analysis'!M$12) -> 888365.67 | ... Q36: =SUMIFS('Data Repository Table'!$I:$I,'Data Repository Table'!$C:$C,'Expenses Analysis'!$A36,'Data Repository Table'!$B:$B,'Expenses Analysis'!$B36,'Data Repository Table'!$F:$F,'Expenses Analysis'!$C36,'Data Repository Table'!$G:$G,'Expenses Analysis'!$D36,'Data Repository Table'!$D:$D,'Expenses Analysis'!Q$12) -> 1253465.5 | R36: =SUM(F36:Q36) -> 10834064
A37: Jutik | B37: Expenses | C37: Facility Costs | D37: Utility-Exp (002) - Electricity | F37: =SUMIFS('Data Repository Table'!$I:$I,'Data Repository Table'!$C:$C,'Expenses Analysis'!$A37,'Data Repository Table'!$B:$B,'Expenses Analysis'!$B37,'Data Repository Table'!$F:$F,'Expenses Analysis'!$C37,'Data Repository Table'!$G:$G,'Expenses Analysis'!$D37,'Data Repository Table'!$D:$D,'Expenses Analysis'!F$12) -> 829385.89 | G37: =SUMIFS('Data Repository Table'!$I:$I,'Data Repository Table'!$C:$C,'Expenses Analysis'!$A37,'Data Repository Table'!$B:$B,'Expenses Analysis'!$B37,'Data Repository Table'!$F:$F,'Expenses Analysis'!$C37,'Data Repository Table'!$G:$G,'Expenses Analysis'!$D37,'Data Repository Table'!$D:$D,'Expenses Analysis'!G$12) -> 660748.9 | H37: =SUMIFS('Data Repository Table'!$I:$I,'Data Repository Table'!$C:$C,'Expenses Analysis'!$A37,'Data Repository Table'!$B:$B,'Expenses Analysis'!$B37,'Data Repository Table'!$F:$F,'Expenses Analysis'!$C37,'Data Repository Table'!$G:$G,'Expenses Analysis'!$D37,'Data Repository Table'!$D:$D,'Expenses Analysis'!H$12) -> 893175.96 | I37: =SUMIFS('Data Repository Table'!$I:$I,'Data Repository Table'!$C:$C,'Expenses Analysis'!$A37,'Data Repository Table'!$B:$B,'Expenses Analysis'!$B37,'Data Repository Table'!$F:$F,'Expenses Analysis'!$C37,'Data Repository Table'!$G:$G,'Expenses Analysis'!$D37,'Data Repository Table'!$D:$D,'Expenses Analysis'!I$12) -> 751290.5 | J37: =SUMIFS('Data Repository Table'!$I:$I,'Data Repository Table'!$C:$C,'Expenses Analysis'!$A37,'Data Repository Table'!$B:$B,'Expenses Analysis'!$B37,'Data Repository Table'!$F:$F,'Expenses Analysis'!$C37,'Data Repository Table'!$G:$G,'Expenses Analysis'!$D37,'Data Repository Table'!$D:$D,'Expenses Analysis'!J$12) -> 638877.8 | K37: =SUMIFS('Data Repository Table'!$I:$I,'Data Repository Table'!$C:$C,'Expenses Analysis'!$A37,'Data Repository Table'!$B:$B,'Expenses Analysis'!$B37,'Data Repository Table'!$F:$F,'Expenses Analysis'!$C37,'Data Repository Table'!$G:$G,'Expenses Analysis'!$D37,'Data Repository Table'!$D:$D,'Expenses Analysis'!K$12) -> 717746.26 | L37: =SUMIFS('Data Repository Table'!$I:$I,'Data Repository Table'!$C:$C,'Expenses Analysis'!$A37,'Data Repository Table'!$B:$B,'Expenses Analysis'!$B37,'Data Repository Table'!$F:$F,'Expenses Analysis'!$C37,'Data Repository Table'!$G:$G,'Expenses Analysis'!$D37,'Data Repository Table'!$D:$D,'Expenses Analysis'!L$12) -> 957882.4 | M37: =SUMIFS('Data Repository Table'!$I:$I,'Data Repository Table'!$C:$C,'Expenses Analysis'!$A37,'Data Repository Table'!$B:$B,'Expenses Analysis'!$B37,'Data Repository Table'!$F:$F,'Expenses Analysis'!$C37,'Data Repository Table'!$G:$G,'Expenses Analysis'!$D37,'Data Repository Table'!$D:$D,'Expenses Analysis'!M$12) -> 822560.8 | ... Q37: =SUMIFS('Data Repository Table'!$I:$I,'Data Repository Table'!$C:$C,'Expenses Analysis'!$A37,'Data Repository Table'!$B:$B,'Expenses Analysis'!$B37,'Data Repository Table'!$F:$F,'Expenses Analysis'!$C37,'Data Repository Table'!$G:$G,'Expenses Analysis'!$D37,'Data Repository Table'!$D:$D,'Expenses Analysis'!Q$12) -> 1160616.2 | R37: =SUM(F37:Q37) -> 10031541
A38: Jutik | B38: Expenses | C38: Operational Maintenance Costs | D38: Plant Maintenance (001) | F38: =SUMIFS('Data Repository Table'!$I:$I,'Data Repository Table'!$C:$C,'Expenses Analysis'!$A38,'Data Repository Table'!$B:$B,'Expenses Analysis'!$B38,'Data Repository Table'!$F:$F,'Expenses Analysis'!$C38,'Data Repository Table'!$G:$G,'Expenses Analysis'!$D38,'Data Repository Table'!$D:$D,'Expenses Analysis'!F$12) -> 716589.41 | G38: =SUMIFS('Data Repository Table'!$I:$I,'Data Repository Table'!$C:$C,'Expenses Analysis'!$A38,'Data Repository Table'!$B:$B,'Expenses Analysis'!$B38,'Data Repository Table'!$F:$F,'Expenses Analysis'!$C38,'Data Repository Table'!$G:$G,'Expenses Analysis'!$D38,'Data Repository Table'!$D:$D,'Expenses Analysis'!G$12) -> 570887.05 | H38: =SUMIFS('Data Repository Table'!$I:$I,'Data Repository Table'!$C:$C,'Expenses Analysis'!$A38,'Data Repository Table'!$B:$B,'Expenses Analysis'!$B38,'Data Repository Table'!$F:$F,'Expenses Analysis'!$C38,'Data Repository Table'!$G:$G,'Expenses Analysis'!$D38,'Data Repository Table'!$D:$D,'Expenses Analysis'!H$12) -> 771704.03 | I38: =SUMIFS('Data Repository Table'!$I:$I,'Data Repository Table'!$C:$C,'Expenses Analysis'!$A38,'Data Repository Table'!$B:$B,'Expenses Analysis'!$B38,'Data Repository Table'!$F:$F,'Expenses Analysis'!$C38,'Data Repository Table'!$G:$G,'Expenses Analysis'!$D38,'Data Repository Table'!$D:$D,'Expenses Analysis'!I$12) -> 649115 | J38: =SUMIFS('Data Repository Table'!$I:$I,'Data Repository Table'!$C:$C,'Expenses Analysis'!$A38,'Data Repository Table'!$B:$B,'Expenses Analysis'!$B38,'Data Repository Table'!$F:$F,'Expenses Analysis'!$C38,'Data Repository Table'!$G:$G,'Expenses Analysis'!$D38,'Data Repository Table'!$D:$D,'Expenses Analysis'!J$12) -> 551990.42 | K38: =SUMIFS('Data Repository Table'!$I:$I,'Data Repository Table'!$C:$C,'Expenses Analysis'!$A38,'Data Repository Table'!$B:$B,'Expenses Analysis'!$B38,'Data Repository Table'!$F:$F,'Expenses Analysis'!$C38,'Data Repository Table'!$G:$G,'Expenses Analysis'!$D38,'Data Repository Table'!$D:$D,'Expenses Analysis'!K$12) -> 620132.77 | L38: =SUMIFS('Data Repository Table'!$I:$I,'Data Repository Table'!$C:$C,'Expenses Analysis'!$A38,'Data Repository Table'!$B:$B,'Expenses Analysis'!$B38,'Data Repository Table'!$F:$F,'Expenses Analysis'!$C38,'Data Repository Table'!$G:$G,'Expenses Analysis'!$D38,'Data Repository Table'!$D:$D,'Expenses Analysis'!L$12) -> 827610.39 | M38: =SUMIFS('Data Repository Table'!$I:$I,'Data Repository Table'!$C:$C,'Expenses Analysis'!$A38,'Data Repository Table'!$B:$B,'Expenses Analysis'!$B38,'Data Repository Table'!$F:$F,'Expenses Analysis'!$C38,'Data Repository Table'!$G:$G,'Expenses Analysis'!$D38,'Data Repository Table'!$D:$D,'Expenses Analysis'!M$12) -> 710692.53 | ... Q38: =SUMIFS('Data Repository Table'!$I:$I,'Data Repository Table'!$C:$C,'Expenses Analysis'!$A38,'Data Repository Table'!$B:$B,'Expenses Analysis'!$B38,'Data Repository Table'!$F:$F,'Expenses Analysis'!$C38,'Data Repository Table'!$G:$G,'Expenses Analysis'!$D38,'Data Repository Table'!$D:$D,'Expenses Analysis'!Q$12) -> 1002772.4 | R38: =SUM(F38:Q38) -> 8667251
A39: Jutik | B39: Expenses | C39: Operational Maintenance Costs | D39: Plant Outages (002) | F39: =SUMIFS('Data Repository Table'!$I:$I,'Data Repository Table'!$C:$C,'Expenses Analysis'!$A39,'Data Repository Table'!$B:$B,'Expenses Analysis'!$B39,'Data Repository Table'!$F:$F,'Expenses Analysis'!$C39,'Data Repository Table'!$G:$G,'Expenses Analysis'!$D39,'Data Repository Table'!$D:$D,'Expenses Analysis'!F$12) -> 251329.06 | G39: =SUMIFS('Data Repository Table'!$I:$I,'Data Repository Table'!$C:$C,'Expenses Analysis'!$A39,'Data Repository Table'!$B:$B,'Expenses Analysis'!$B39,'Data Repository Table'!$F:$F,'Expenses Analysis'!$C39,'Data Repository Table'!$G:$G,'Expenses Analysis'!$D39,'Data Repository Table'!$D:$D,'Expenses Analysis'!G$12) -> 200226.94 | H39: =SUMIFS('Data Repository Table'!$I:$I,'Data Repository Table'!$C:$C,'Expenses Analysis'!$A39,'Data Repository Table'!$B:$B,'Expenses Analysis'!$B39,'Data Repository Table'!$F:$F,'Expenses Analysis'!$C39,'Data Repository Table'!$G:$G,'Expenses Analysis'!$D39,'Data Repository Table'!$D:$D,'Expenses Analysis'!H$12) -> 270659.38 | I39: =SUMIFS('Data Repository Table'!$I:$I,'Data Repository Table'!$C:$C,'Expenses Analysis'!$A39,'Data Repository Table'!$B:$B,'Expenses Analysis'!$B39,'Data Repository Table'!$F:$F,'Expenses Analysis'!$C39,'Data Repository Table'!$G:$G,'Expenses Analysis'!$D39,'Data Repository Table'!$D:$D,'Expenses Analysis'!I$12) -> 227663.79 | J39: =SUMIFS('Data Repository Table'!$I:$I,'Data Repository Table'!$C:$C,'Expenses Analysis'!$A39,'Data Repository Table'!$B:$B,'Expenses Analysis'!$B39,'Data Repository Table'!$F:$F,'Expenses Analysis'!$C39,'Data Repository Table'!$G:$G,'Expenses Analysis'!$D39,'Data Repository Table'!$D:$D,'Expenses Analysis'!J$12) -> 193599.33 | K39: =SUMIFS('Data Repository Table'!$I:$I,'Data Repository Table'!$C:$C,'Expenses Analysis'!$A39,'Data Repository Table'!$B:$B,'Expenses Analysis'!$B39,'Data Repository Table'!$F:$F,'Expenses Analysis'!$C39,'Data Repository Table'!$G:$G,'Expenses Analysis'!$D39,'Data Repository Table'!$D:$D,'Expenses Analysis'!K$12) -> 143549.25 | L39: =SUMIFS('Data Repository Table'!$I:$I,'Data Repository Table'!$C:$C,'Expenses Analysis'!$A39,'Data Repository Table'!$B:$B,'Expenses Analysis'!$B39,'Data Repository Table'!$F:$F,'Expenses Analysis'!$C39,'Data Repository Table'!$G:$G,'Expenses Analysis'!$D39,'Data Repository Table'!$D:$D,'Expenses Analysis'!L$12) -> 153261.18 | M39: =SUMIFS('Data Repository Table'!$I:$I,'Data Repository Table'!$C:$C,'Expenses Analysis'!$A39,'Data Repository Table'!$B:$B,'Expenses Analysis'!$B39,'Data Repository Table'!$F:$F,'Expenses Analysis'!$C39,'Data Repository Table'!$G:$G,'Expenses Analysis'!$D39,'Data Repository Table'!$D:$D,'Expenses Analysis'!M$12) -> 131609.73 | ... Q39: =SUMIFS('Data Repository Table'!$I:$I,'Data Repository Table'!$C:$C,'Expenses Analysis'!$A39,'Data Repository Table'!$B:$B,'Expenses Analysis'!$B39,'Data Repository Table'!$F:$F,'Expenses Analysis'!$C39,'Data Repository Table'!$G:$G,'Expenses Analysis'!$D39,'Data Repository Table'!$D:$D,'Expenses Analysis'!Q$12) -> 232123.24 | R39: =SUM(F39:Q39) -> 2219902.8
A40: Jutik | B40: Expenses | C40: Operational Maintenance Costs | D40: Plant Op. Costs (003) | F40: =SUMIFS('Data Repository Table'!$I:$I,'Data Repository Table'!$C:$C,'Expenses Analysis'!$A40,'Data Repository Table'!$B:$B,'Expenses Analysis'!$B40,'Data Repository Table'!$F:$F,'Expenses Analysis'!$C40,'Data Repository Table'!$G:$G,'Expenses Analysis'!$D40,'Data Repository Table'!$D:$D,'Expenses Analysis'!F$12) -> 623296.06 | G40: =SUMIFS('Data Repository Table'!$I:$I,'Data Repository Table'!$C:$C,'Expenses Analysis'!$A40,'Data Repository Table'!$B:$B,'Expenses Analysis'!$B40,'Data Repository Table'!$F:$F,'Expenses Analysis'!$C40,'Data Repository Table'!$G:$G,'Expenses Analysis'!$D40,'Data Repository Table'!$D:$D,'Expenses Analysis'!G$12) -> 496562.81 | H40: =SUMIFS('Data Repository Table'!$I:$I,'Data Repository Table'!$C:$C,'Expenses Analysis'!$A40,'Data Repository Table'!$B:$B,'Expenses Analysis'!$B40,'Data Repository Table'!$F:$F,'Expenses Analysis'!$C40,'Data Repository Table'!$G:$G,'Expenses Analysis'!$D40,'Data Repository Table'!$D:$D,'Expenses Analysis'!H$12) -> 671235.27 | I40: =SUMIFS('Data Repository Table'!$I:$I,'Data Repository Table'!$C:$C,'Expenses Analysis'!$A40,'Data Repository Table'!$B:$B,'Expenses Analysis'!$B40,'Data Repository Table'!$F:$F,'Expenses Analysis'!$C40,'Data Repository Table'!$G:$G,'Expenses Analysis'!$D40,'Data Repository Table'!$D:$D,'Expenses Analysis'!I$12) -> 564606.2 | J40: =SUMIFS('Data Repository Table'!$I:$I,'Data Repository Table'!$C:$C,'Expenses Analysis'!$A40,'Data Repository Table'!$B:$B,'Expenses Analysis'!$B40,'Data Repository Table'!$F:$F,'Expenses Analysis'!$C40,'Data Repository Table'!$G:$G,'Expenses Analysis'!$D40,'Data Repository Table'!$D:$D,'Expenses Analysis'!J$12) -> 480126.35 | K40: =SUMIFS('Data Repository Table'!$I:$I,'Data Repository Table'!$C:$C,'Expenses Analysis'!$A40,'Data Repository Table'!$B:$B,'Expenses Analysis'!$B40,'Data Repository Table'!$F:$F,'Expenses Analysis'!$C40,'Data Repository Table'!$G:$G,'Expenses Analysis'!$D40,'Data Repository Table'!$D:$D,'Expenses Analysis'!K$12) -> 356002.15 | L40: =SUMIFS('Data Repository Table'!$I:$I,'Data Repository Table'!$C:$C,'Expenses Analysis'!$A40,'Data Repository Table'!$B:$B,'Expenses Analysis'!$B40,'Data Repository Table'!$F:$F,'Expenses Analysis'!$C40,'Data Repository Table'!$G:$G,'Expenses Analysis'!$D40,'Data Repository Table'!$D:$D,'Expenses Analysis'!L$12) -> 380087.74 | M40: =SUMIFS('Data Repository Table'!$I:$I,'Data Repository Table'!$C:$C,'Expenses Analysis'!$A40,'Data Repository Table'!$B:$B,'Expenses Analysis'!$B40,'Data Repository Table'!$F:$F,'Expenses Analysis'!$C40,'Data Repository Table'!$G:$G,'Expenses Analysis'!$D40,'Data Repository Table'!$D:$D,'Expenses Analysis'!M$12) -> 326392.13 | ... Q40: =SUMIFS('Data Repository Table'!$I:$I,'Data Repository Table'!$C:$C,'Expenses Analysis'!$A40,'Data Repository Table'!$B:$B,'Expenses Analysis'!$B40,'Data Repository Table'!$F:$F,'Expenses Analysis'!$C40,'Data Repository Table'!$G:$G,'Expenses Analysis'!$D40,'Data Repository Table'!$D:$D,'Expenses Analysis'!Q$12) -> 575665.64 | R40: =SUM(F40:Q40) -> 5505359
A41: Jutik | B41: Expenses | C41: Operational Maintenance Costs | D41: Plant Admin Costs (004) | F41: =SUMIFS('Data Repository Table'!$I:$I,'Data Repository Table'!$C:$C,'Expenses Analysis'!$A41,'Data Repository Table'!$B:$B,'Expenses Analysis'!$B41,'Data Repository Table'!$F:$F,'Expenses Analysis'!$C41,'Data Repository Table'!$G:$G,'Expenses Analysis'!$D41,'Data Repository Table'!$D:$D,'Expenses Analysis'!F$12) -> 211116.41 | G41: =SUMIFS('Data Repository Table'!$I:$I,'Data Repository Table'!$C:$C,'Expenses Analysis'!$A41,'Data Repository Table'!$B:$B,'Expenses Analysis'!$B41,'Data Repository Table'!$F:$F,'Expenses Analysis'!$C41,'Data Repository Table'!$G:$G,'Expenses Analysis'!$D41,'Data Repository Table'!$D:$D,'Expenses Analysis'!G$12) -> 168190.63 | H41: =SUMIFS('Data Repository Table'!$I:$I,'Data Repository Table'!$C:$C,'Expenses Analysis'!$A41,'Data Repository Table'!$B:$B,'Expenses Analysis'!$B41,'Data Repository Table'!$F:$F,'Expenses Analysis'!$C41,'Data Repository Table'!$G:$G,'Expenses Analysis'!$D41,'Data Repository Table'!$D:$D,'Expenses Analysis'!H$12) -> 227353.88 | I41: =SUMIFS('Data Repository Table'!$I:$I,'Data Repository Table'!$C:$C,'Expenses Analysis'!$A41,'Data Repository Table'!$B:$B,'Expenses Analysis'!$B41,'Data Repository Table'!$F:$F,'Expenses Analysis'!$C41,'Data Repository Table'!$G:$G,'Expenses Analysis'!$D41,'Data Repository Table'!$D:$D,'Expenses Analysis'!I$12) -> 191237.58 | J41: =SUMIFS('Data Repository Table'!$I:$I,'Data Repository Table'!$C:$C,'Expenses Analysis'!$A41,'Data Repository Table'!$B:$B,'Expenses Analysis'!$B41,'Data Repository Table'!$F:$F,'Expenses Analysis'!$C41,'Data Repository Table'!$G:$G,'Expenses Analysis'!$D41,'Data Repository Table'!$D:$D,'Expenses Analysis'!J$12) -> 162623.44 | K41: =SUMIFS('Data Repository Table'!$I:$I,'Data Repository Table'!$C:$C,'Expenses Analysis'!$A41,'Data Repository Table'!$B:$B,'Expenses Analysis'!$B41,'Data Repository Table'!$F:$F,'Expenses Analysis'!$C41,'Data Repository Table'!$G:$G,'Expenses Analysis'!$D41,'Data Repository Table'!$D:$D,'Expenses Analysis'!K$12) -> 120581.37 | L41: =SUMIFS('Data Repository Table'!$I:$I,'Data Repository Table'!$C:$C,'Expenses Analysis'!$A41,'Data Repository Table'!$B:$B,'Expenses Analysis'!$B41,'Data Repository Table'!$F:$F,'Expenses Analysis'!$C41,'Data Repository Table'!$G:$G,'Expenses Analysis'!$D41,'Data Repository Table'!$D:$D,'Expenses Analysis'!L$12) -> 128739.39 | M41: =SUMIFS('Data Repository Table'!$I:$I,'Data Repository Table'!$C:$C,'Expenses Analysis'!$A41,'Data Repository Table'!$B:$B,'Expenses Analysis'!$B41,'Data Repository Table'!$F:$F,'Expenses Analysis'!$C41,'Data Repository Table'!$G:$G,'Expenses Analysis'!$D41,'Data Repository Table'!$D:$D,'Expenses Analysis'!M$12) -> 110552.17 | ... Q41: =SUMIFS('Data Repository Table'!$I:$I,'Data Repository Table'!$C:$C,'Expenses Analysis'!$A41,'Data Repository Table'!$B:$B,'Expenses Analysis'!$B41,'Data Repository Table'!$F:$F,'Expenses Analysis'!$C41,'Data Repository Table'!$G:$G,'Expenses Analysis'!$D41,'Data Repository Table'!$D:$D,'Expenses Analysis'!Q$12) -> 194983.52 | R41: =SUM(F41:Q41) -> 1864718.4
A42: Jutik | B42: Expenses | C42: Labour Costs | D42: Labour-Costs (001) | F42: =SUMIFS('Data Repository Table'!$I:$I,'Data Repository Table'!$C:$C,'Expenses Analysis'!$A42,'Data Repository Table'!$B:$B,'Expenses Analysis'!$B42,'Data Repository Table'!$F:$F,'Expenses Analysis'!$C42,'Data Repository Table'!$G:$G,'Expenses Analysis'!$D42,'Data Repository Table'!$D:$D,'Expenses Analysis'!F$12) -> 3015948.7 | G42: =SUMIFS('Data Repository Table'!$I:$I,'Data Repository Table'!$C:$C,'Expenses Analysis'!$A42,'Data Repository Table'!$B:$B,'Expenses Analysis'!$B42,'Data Repository Table'!$F:$F,'Expenses Analysis'!$C42,'Data Repository Table'!$G:$G,'Expenses Analysis'!$D42,'Data Repository Table'!$D:$D,'Expenses Analysis'!G$12) -> 2402723.3 | H42: =SUMIFS('Data Repository Table'!$I:$I,'Data Repository Table'!$C:$C,'Expenses Analysis'!$A42,'Data Repository Table'!$B:$B,'Expenses Analysis'!$B42,'Data Repository Table'!$F:$F,'Expenses Analysis'!$C42,'Data Repository Table'!$G:$G,'Expenses Analysis'!$D42,'Data Repository Table'!$D:$D,'Expenses Analysis'!H$12) -> 3247912.6 | I42: =SUMIFS('Data Repository Table'!$I:$I,'Data Repository Table'!$C:$C,'Expenses Analysis'!$A42,'Data Repository Table'!$B:$B,'Expenses Analysis'!$B42,'Data Repository Table'!$F:$F,'Expenses Analysis'!$C42,'Data Repository Table'!$G:$G,'Expenses Analysis'!$D42,'Data Repository Table'!$D:$D,'Expenses Analysis'!I$12) -> 2731965.5 | J42: =SUMIFS('Data Repository Table'!$I:$I,'Data Repository Table'!$C:$C,'Expenses Analysis'!$A42,'Data Repository Table'!$B:$B,'Expenses Analysis'!$B42,'Data Repository Table'!$F:$F,'Expenses Analysis'!$C42,'Data Repository Table'!$G:$G,'Expenses Analysis'!$D42,'Data Repository Table'!$D:$D,'Expenses Analysis'!J$12) -> 2323192 | K42: =SUMIFS('Data Repository Table'!$I:$I,'Data Repository Table'!$C:$C,'Expenses Analysis'!$A42,'Data Repository Table'!$B:$B,'Expenses Analysis'!$B42,'Data Repository Table'!$F:$F,'Expenses Analysis'!$C42,'Data Repository Table'!$G:$G,'Expenses Analysis'!$D42,'Data Repository Table'!$D:$D,'Expenses Analysis'!K$12) -> 1722591 | L42: =SUMIFS('Data Repository Table'!$I:$I,'Data Repository Table'!$C:$C,'Expenses Analysis'!$A42,'Data Repository Table'!$B:$B,'Expenses Analysis'!$B42,'Data Repository Table'!$F:$F,'Expenses Analysis'!$C42,'Data Repository Table'!$G:$G,'Expenses Analysis'!$D42,'Data Repository Table'!$D:$D,'Expenses Analysis'!L$12) -> 1839134.2 | M42: =SUMIFS('Data Repository Table'!$I:$I,'Data Repository Table'!$C:$C,'Expenses Analysis'!$A42,'Data Repository Table'!$B:$B,'Expenses Analysis'!$B42,'Data Repository Table'!$F:$F,'Expenses Analysis'!$C42,'Data Repository Table'!$G:$G,'Expenses Analysis'!$D42,'Data Repository Table'!$D:$D,'Expenses Analysis'!M$12) -> 2579316.7 | ... Q42: =SUMIFS('Data Repository Table'!$I:$I,'Data Repository Table'!$C:$C,'Expenses Analysis'!$A42,'Data Repository Table'!$B:$B,'Expenses Analysis'!$B42,'Data Repository Table'!$F:$F,'Expenses Analysis'!$C42,'Data Repository Table'!$G:$G,'Expenses Analysis'!$D42,'Data Repository Table'!$D:$D,'Expenses Analysis'!Q$12) -> 2785478.9 | R42: =SUM(F42:Q42) -> 29638834
D43: Total | F43: =SUM(F35:F42) -> 8168998.6 | G43: =SUM(G35:G42) -> 6508016.3 | H43: =SUM(H35:H42) -> 8797296 | I43: =SUM(I35:I42) -> 7399801.7 | J43: =SUM(J35:J42) -> 6292597.9 | K43: =SUM(K35:K42) -> 5862551.5 | L43: =SUM(L35:L42) -> 7198677.8 | M43: =SUM(M35:M42) -> 7481709 | ... R43: =SUM(R35:R42) -> 90723489
A44: You've now calculated the Expenses for each of the three desalination plants (Kootha, Surjek and Jutik). This has given you a micro-view of the trends, but let's take a look at the macro-expenses trends and view all this information aggregated together (Kootha + Surjek + Jutik) and then. Is there any particular trend(s) that we can pick up with respect to which water product(s) have the highest expenses overall?
A45: Q6. Complete the table below, aggregating all the costs for all units for the respective Accounting Code Centre and Accounting Code Centre Elements. Upon completion of this, create a column Chart using the Year-To-Date Total showing the aggregate costs per Accounting Code Centre Element (i.e. Chem-Exp (001), Utility Exp (002) - Heating etc.)
A46: Unit | B46: Value Driver | C46: Accounting Code Centre | D46: Accounting Code Centre Element | F46: 41456 | G46: 41487 | H46: 41518 | I46: 41548 | J46: 41579 | K46: 41609 | L46: 41640 | M46: 41671 | N46: 41699 | O46: 41730 | P46: 41760 | Q46: 41791
R47: Total
A48: All | B48: Expenses | C48: Chemical Costs | D48: Chem-Exp (001) | F48: =SUMIFS('Data Repository Table'!$I:$I,'Data Repository Table'!$B:$B,'Expenses Analysis'!$B48,'Data Repository Table'!$F:$F,'Expenses Analysis'!$C48,'Data Repository Table'!$G:$G,'Expenses Analysis'!$D48,'Data Repository Table'!$D:$D,'Expenses Analysis'!F$46) -> 4752382.7 | G48: =SUMIFS('Data Repository Table'!$I:$I,'Data Repository Table'!$B:$B,'Expenses Analysis'!$B48,'Data Repository Table'!$F:$F,'Expenses Analysis'!$C48,'Data Repository Table'!$G:$G,'Expenses Analysis'!$D48,'Data Repository Table'!$D:$D,'Expenses Analysis'!G$46) -> 5167035 | H48: =SUMIFS('Data Repository Table'!$I:$I,'Data Repository Table'!$B:$B,'Expenses Analysis'!$B48,'Data Repository Table'!$F:$F,'Expenses Analysis'!$C48,'Data Repository Table'!$G:$G,'Expenses Analysis'!$D48,'Data Repository Table'!$D:$D,'Expenses Analysis'!H$46) -> 5477119.2 | I48: =SUMIFS('Data Repository Table'!$I:$I,'Data Repository Table'!$B:$B,'Expenses Analysis'!$B48,'Data Repository Table'!$F:$F,'Expenses Analysis'!$C48,'Data Repository Table'!$G:$G,'Expenses Analysis'!$D48,'Data Repository Table'!$D:$D,'Expenses Analysis'!I$46) -> 6217372.1 | J48: =SUMIFS('Data Repository Table'!$I:$I,'Data Repository Table'!$B:$B,'Expenses Analysis'!$B48,'Data Repository Table'!$F:$F,'Expenses Analysis'!$C48,'Data Repository Table'!$G:$G,'Expenses Analysis'!$D48,'Data Repository Table'!$D:$D,'Expenses Analysis'!J$46) -> 6351549.6 | K48: =SUMIFS('Data Repository Table'!$I:$I,'Data Repository Table'!$B:$B,'Expenses Analysis'!$B48,'Data Repository Table'!$F:$F,'Expenses Analysis'!$C48,'Data Repository Table'!$G:$G,'Expenses Analysis'!$D48,'Data Repository Table'!$D:$D,'Expenses Analysis'!K$46) -> 5473894 | L48: =SUMIFS('Data Repository Table'!$I:$I,'Data Repository Table'!$B:$B,'Expenses Analysis'!$B48,'Data Repository Table'!$F:$F,'Expenses Analysis'!$C48,'Data Repository Table'!$G:$G,'Expenses Analysis'!$D48,'Data Repository Table'!$D:$D,'Expenses Analysis'!L$46) -> 7073236.3 | M48: =SUMIFS('Data Repository Table'!$I:$I,'Data Repository Table'!$B:$B,'Expenses Analysis'!$B48,'Data Repository Table'!$F:$F,'Expenses Analysis'!$C48,'Data Repository Table'!$G:$G,'Expenses Analysis'!$D48,'Data Repository Table'!$D:$D,'Expenses Analysis'!M$46) -> 7645099.2 | ... Q48: =SUMIFS('Data Repository Table'!$I:$I,'Data Repository Table'!$B:$B,'Expenses Analysis'!$B48,'Data Repository Table'!$F:$F,'Expenses Analysis'!$C48,'Data Repository Table'!$G:$G,'Expenses Analysis'!$D48,'Data Repository Table'!$D:$D,'Expenses Analysis'!Q$46) -> 5712658.2 | R48: =SUM(F48:Q48) -> 78413350
A49: All | B49: Expenses | C49: Facility Costs | D49: Utility-Exp (002) - Heating | F49: =SUMIFS('Data Repository Table'!$I:$I,'Data Repository Table'!$B:$B,'Expenses Analysis'!$B49,'Data Repository Table'!$F:$F,'Expenses Analysis'!$C49,'Data Repository Table'!$G:$G,'Expenses Analysis'!$D49,'Data Repository Table'!$D:$D,'Expenses Analysis'!F$46) -> 2439061.4 | G49: =SUMIFS('Data Repository Table'!$I:$I,'Data Repository Table'!$B:$B,'Expenses Analysis'!$B49,'Data Repository Table'!$F:$F,'Expenses Analysis'!$C49,'Data Repository Table'!$G:$G,'Expenses Analysis'!$D49,'Data Repository Table'!$D:$D,'Expenses Analysis'!G$46) -> 2621863.5 | H49: =SUMIFS('Data Repository Table'!$I:$I,'Data Repository Table'!$B:$B,'Expenses Analysis'!$B49,'Data Repository Table'!$F:$F,'Expenses Analysis'!$C49,'Data Repository Table'!$G:$G,'Expenses Analysis'!$D49,'Data Repository Table'!$D:$D,'Expenses Analysis'!H$46) -> 2806168.1 | I49: =SUMIFS('Data Repository Table'!$I:$I,'Data Repository Table'!$B:$B,'Expenses Analysis'!$B49,'Data Repository Table'!$F:$F,'Expenses Analysis'!$C49,'Data Repository Table'!$G:$G,'Expenses Analysis'!$D49,'Data Repository Table'!$D:$D,'Expenses Analysis'!I$46) -> 3163209.6 | J49: =SUMIFS('Data Repository Table'!$I:$I,'Data Repository Table'!$B:$B,'Expenses Analysis'!$B49,'Data Repository Table'!$F:$F,'Expenses Analysis'!$C49,'Data Repository Table'!$G:$G,'Expenses Analysis'!$D49,'Data Repository Table'!$D:$D,'Expenses Analysis'!J$46) -> 3218501.6 | K49: =SUMIFS('Data Repository Table'!$I:$I,'Data Repository Table'!$B:$B,'Expenses Analysis'!$B49,'Data Repository Table'!$F:$F,'Expenses Analysis'!$C49,'Data Repository Table'!$G:$G,'Expenses Analysis'!$D49,'Data Repository Table'!$D:$D,'Expenses Analysis'!K$46) -> 2788369.1 | L49: =SUMIFS('Data Repository Table'!$I:$I,'Data Repository Table'!$B:$B,'Expenses Analysis'!$B49,'Data Repository Table'!$F:$F,'Expenses Analysis'!$C49,'Data Repository Table'!$G:$G,'Expenses Analysis'!$D49,'Data Repository Table'!$D:$D,'Expenses Analysis'!L$46) -> 3593667.3 | M49: =SUMIFS('Data Repository Table'!$I:$I,'Data Repository Table'!$B:$B,'Expenses Analysis'!$B49,'Data Repository Table'!$F:$F,'Expenses Analysis'!$C49,'Data Repository Table'!$G:$G,'Expenses Analysis'!$D49,'Data Repository Table'!$D:$D,'Expenses Analysis'!M$46) -> 3722191.5 | ... Q49: =SUMIFS('Data Repository Table'!$I:$I,'Data Repository Table'!$B:$B,'Expenses Analysis'!$B49,'Data Repository Table'!$F:$F,'Expenses Analysis'!$C49,'Data Repository Table'!$G:$G,'Expenses Analysis'!$D49,'Data Repository Table'!$D:$D,'Expenses Analysis'!Q$46) -> 2932911.3 | R49: =SUM(F49:Q49) -> 38717591
A50: All | B50: Expenses | C50: Facility Costs | D50: Utility-Exp (002) - Electricity | F50: =SUMIFS('Data Repository Table'!$I:$I,'Data Repository Table'!$B:$B,'Expenses Analysis'!$B50,'Data Repository Table'!$F:$F,'Expenses Analysis'!$C50,'Data Repository Table'!$G:$G,'Expenses Analysis'!$D50,'Data Repository Table'!$D:$D,'Expenses Analysis'!F$46) -> 2300028 | G50: =SUMIFS('Data Repository Table'!$I:$I,'Data Repository Table'!$B:$B,'Expenses Analysis'!$B50,'Data Repository Table'!$F:$F,'Expenses Analysis'!$C50,'Data Repository Table'!$G:$G,'Expenses Analysis'!$D50,'Data Repository Table'!$D:$D,'Expenses Analysis'!G$46) -> 2505939.6 | H50: =SUMIFS('Data Repository Table'!$I:$I,'Data Repository Table'!$B:$B,'Expenses Analysis'!$B50,'Data Repository Table'!$F:$F,'Expenses Analysis'!$C50,'Data Repository Table'!$G:$G,'Expenses Analysis'!$D50,'Data Repository Table'!$D:$D,'Expenses Analysis'!H$46) -> 2627415.4 | I50: =SUMIFS('Data Repository Table'!$I:$I,'Data Repository Table'!$B:$B,'Expenses Analysis'!$B50,'Data Repository Table'!$F:$F,'Expenses Analysis'!$C50,'Data Repository Table'!$G:$G,'Expenses Analysis'!$D50,'Data Repository Table'!$D:$D,'Expenses Analysis'!I$46) -> 2900613.3 | J50: =SUMIFS('Data Repository Table'!$I:$I,'Data Repository Table'!$B:$B,'Expenses Analysis'!$B50,'Data Repository Table'!$F:$F,'Expenses Analysis'!$C50,'Data Repository Table'!$G:$G,'Expenses Analysis'!$D50,'Data Repository Table'!$D:$D,'Expenses Analysis'!J$46) -> 2940556.2 | K50: =SUMIFS('Data Repository Table'!$I:$I,'Data Repository Table'!$B:$B,'Expenses Analysis'!$B50,'Data Repository Table'!$F:$F,'Expenses Analysis'!$C50,'Data Repository Table'!$G:$G,'Expenses Analysis'!$D50,'Data Repository Table'!$D:$D,'Expenses Analysis'!K$46) -> 2582565 | L50: =SUMIFS('Data Repository Table'!$I:$I,'Data Repository Table'!$B:$B,'Expenses Analysis'!$B50,'Data Repository Table'!$F:$F,'Expenses Analysis'!$C50,'Data Repository Table'!$G:$G,'Expenses Analysis'!$D50,'Data Repository Table'!$D:$D,'Expenses Analysis'!L$46) -> 3446732.9 | M50: =SUMIFS('Data Repository Table'!$I:$I,'Data Repository Table'!$B:$B,'Expenses Analysis'!$B50,'Data Repository Table'!$F:$F,'Expenses Analysis'!$C50,'Data Repository Table'!$G:$G,'Expenses Analysis'!$D50,'Data Repository Table'!$D:$D,'Expenses Analysis'!M$46) -> 3483983.4 | ... Q50: =SUMIFS('Data Repository Table'!$I:$I,'Data Repository Table'!$B:$B,'Expenses Analysis'!$B50,'Data Repository Table'!$F:$F,'Expenses Analysis'!$C50,'Data Repository Table'!$G:$G,'Expenses Analysis'!$D50,'Data Repository Table'!$D:$D,'Expenses Analysis'!Q$46) -> 2923183.2 | R50: =SUM(F50:Q50) -> 36414828
A51: All | B51: Expenses | C51: Operational Maintenance Costs | D51: Plant Maintenance (001) | F51: =SUMIFS('Data Repository Table'!$I:$I,'Data Repository Table'!$B:$B,'Expenses Analysis'!$B51,'Data Repository Table'!$F:$F,'Expenses Analysis'!$C51,'Data Repository Table'!$G:$G,'Expenses Analysis'!$D51,'Data Repository Table'!$D:$D,'Expenses Analysis'!F$46) -> 2073604.7 | G51: =SUMIFS('Data Repository Table'!$I:$I,'Data Repository Table'!$B:$B,'Expenses Analysis'!$B51,'Data Repository Table'!$F:$F,'Expenses Analysis'!$C51,'Data Repository Table'!$G:$G,'Expenses Analysis'!$D51,'Data Repository Table'!$D:$D,'Expenses Analysis'!G$46) -> 2269539.8 | H51: =SUMIFS('Data Repository Table'!$I:$I,'Data Repository Table'!$B:$B,'Expenses Analysis'!$B51,'Data Repository Table'!$F:$F,'Expenses Analysis'!$C51,'Data Repository Table'!$G:$G,'Expenses Analysis'!$D51,'Data Repository Table'!$D:$D,'Expenses Analysis'!H$46) -> 2374998.8 | I51: =SUMIFS('Data Repository Table'!$I:$I,'Data Repository Table'!$B:$B,'Expenses Analysis'!$B51,'Data Repository Table'!$F:$F,'Expenses Analysis'!$C51,'Data Repository Table'!$G:$G,'Expenses Analysis'!$D51,'Data Repository Table'!$D:$D,'Expenses Analysis'!I$46) -> 2645968.1 | J51: =SUMIFS('Data Repository Table'!$I:$I,'Data Repository Table'!$B:$B,'Expenses Analysis'!$B51,'Data Repository Table'!$F:$F,'Expenses Analysis'!$C51,'Data Repository Table'!$G:$G,'Expenses Analysis'!$D51,'Data Repository Table'!$D:$D,'Expenses Analysis'!J$46) -> 2691801.7 | K51: =SUMIFS('Data Repository Table'!$I:$I,'Data Repository Table'!$B:$B,'Expenses Analysis'!$B51,'Data Repository Table'!$F:$F,'Expenses Analysis'!$C51,'Data Repository Table'!$G:$G,'Expenses Analysis'!$D51,'Data Repository Table'!$D:$D,'Expenses Analysis'!K$46) -> 2348808.3 | L51: =SUMIFS('Data Repository Table'!$I:$I,'Data Repository Table'!$B:$B,'Expenses Analysis'!$B51,'Data Repository Table'!$F:$F,'Expenses Analysis'!$C51,'Data Repository Table'!$G:$G,'Expenses Analysis'!$D51,'Data Repository Table'!$D:$D,'Expenses Analysis'!L$46) -> 2879996.2 | M51: =SUMIFS('Data Repository Table'!$I:$I,'Data Repository Table'!$B:$B,'Expenses Analysis'!$B51,'Data Repository Table'!$F:$F,'Expenses Analysis'!$C51,'Data Repository Table'!$G:$G,'Expenses Analysis'!$D51,'Data Repository Table'!$D:$D,'Expenses Analysis'!M$46) -> 2972957.9 | ... Q51: =SUMIFS('Data Repository Table'!$I:$I,'Data Repository Table'!$B:$B,'Expenses Analysis'!$B51,'Data Repository Table'!$F:$F,'Expenses Analysis'!$C51,'Data Repository Table'!$G:$G,'Expenses Analysis'!$D51,'Data Repository Table'!$D:$D,'Expenses Analysis'!Q$46) -> 2363869.6 | R51: =SUM(F51:Q51) -> 31752797
A52: All | B52: Expenses | C52: Operational Maintenance Costs | D52: Plant Outages (002) | F52: =SUMIFS('Data Repository Table'!$I:$I,'Data Repository Table'!$B:$B,'Expenses Analysis'!$B52,'Data Repository Table'!$F:$F,'Expenses Analysis'!$C52,'Data Repository Table'!$G:$G,'Expenses Analysis'!$D52,'Data Repository Table'!$D:$D,'Expenses Analysis'!F$46) -> 1347738.9 | G52: =SUMIFS('Data Repository Table'!$I:$I,'Data Repository Table'!$B:$B,'Expenses Analysis'!$B52,'Data Repository Table'!$F:$F,'Expenses Analysis'!$C52,'Data Repository Table'!$G:$G,'Expenses Analysis'!$D52,'Data Repository Table'!$D:$D,'Expenses Analysis'!G$46) -> 1561170.4 | H52: =SUMIFS('Data Repository Table'!$I:$I,'Data Repository Table'!$B:$B,'Expenses Analysis'!$B52,'Data Repository Table'!$F:$F,'Expenses Analysis'!$C52,'Data Repository Table'!$G:$G,'Expenses Analysis'!$D52,'Data Repository Table'!$D:$D,'Expenses Analysis'!H$46) -> 1574874.1 | I52: =SUMIFS('Data Repository Table'!$I:$I,'Data Repository Table'!$B:$B,'Expenses Analysis'!$B52,'Data Repository Table'!$F:$F,'Expenses Analysis'!$C52,'Data Repository Table'!$G:$G,'Expenses Analysis'!$D52,'Data Repository Table'!$D:$D,'Expenses Analysis'!I$46) -> 1880373.5 | J52: =SUMIFS('Data Repository Table'!$I:$I,'Data Repository Table'!$B:$B,'Expenses Analysis'!$B52,'Data Repository Table'!$F:$F,'Expenses Analysis'!$C52,'Data Repository Table'!$G:$G,'Expenses Analysis'!$D52,'Data Repository Table'!$D:$D,'Expenses Analysis'!J$46) -> 1968683.2 | K52: =SUMIFS('Data Repository Table'!$I:$I,'Data Repository Table'!$B:$B,'Expenses Analysis'!$B52,'Data Repository Table'!$F:$F,'Expenses Analysis'!$C52,'Data Repository Table'!$G:$G,'Expenses Analysis'!$D52,'Data Repository Table'!$D:$D,'Expenses Analysis'!K$46) -> 1158623.1 | L52: =SUMIFS('Data Repository Table'!$I:$I,'Data Repository Table'!$B:$B,'Expenses Analysis'!$B52,'Data Repository Table'!$F:$F,'Expenses Analysis'!$C52,'Data Repository Table'!$G:$G,'Expenses Analysis'!$D52,'Data Repository Table'!$D:$D,'Expenses Analysis'!L$46) -> 1176136.2 | M52: =SUMIFS('Data Repository Table'!$I:$I,'Data Repository Table'!$B:$B,'Expenses Analysis'!$B52,'Data Repository Table'!$F:$F,'Expenses Analysis'!$C52,'Data Repository Table'!$G:$G,'Expenses Analysis'!$D52,'Data Repository Table'!$D:$D,'Expenses Analysis'!M$46) -> 1239117.6 | ... Q52: =SUMIFS('Data Repository Table'!$I:$I,'Data Repository Table'!$B:$B,'Expenses Analysis'!$B52,'Data Repository Table'!$F:$F,'Expenses Analysis'!$C52,'Data Repository Table'!$G:$G,'Expenses Analysis'!$D52,'Data Repository Table'!$D:$D,'Expenses Analysis'!Q$46) -> 1040665.8 | R52: =SUM(F52:Q52) -> 16735123
A53: All | B53: Expenses | C53: Operational Maintenance Costs | D53: Plant Op. Costs (003) | F53: =SUMIFS('Data Repository Table'!$I:$I,'Data Repository Table'!$B:$B,'Expenses Analysis'!$B53,'Data Repository Table'!$F:$F,'Expenses Analysis'!$C53,'Data Repository Table'!$G:$G,'Expenses Analysis'!$D53,'Data Repository Table'!$D:$D,'Expenses Analysis'!F$46) -> 1800236.6 | G53: =SUMIFS('Data Repository Table'!$I:$I,'Data Repository Table'!$B:$B,'Expenses Analysis'!$B53,'Data Repository Table'!$F:$F,'Expenses Analysis'!$C53,'Data Repository Table'!$G:$G,'Expenses Analysis'!$D53,'Data Repository Table'!$D:$D,'Expenses Analysis'!G$46) -> 1959718.9 | H53: =SUMIFS('Data Repository Table'!$I:$I,'Data Repository Table'!$B:$B,'Expenses Analysis'!$B53,'Data Repository Table'!$F:$F,'Expenses Analysis'!$C53,'Data Repository Table'!$G:$G,'Expenses Analysis'!$D53,'Data Repository Table'!$D:$D,'Expenses Analysis'!H$46) -> 2069515.6 | I53: =SUMIFS('Data Repository Table'!$I:$I,'Data Repository Table'!$B:$B,'Expenses Analysis'!$B53,'Data Repository Table'!$F:$F,'Expenses Analysis'!$C53,'Data Repository Table'!$G:$G,'Expenses Analysis'!$D53,'Data Repository Table'!$D:$D,'Expenses Analysis'!I$46) -> 2330999.3 | J53: =SUMIFS('Data Repository Table'!$I:$I,'Data Repository Table'!$B:$B,'Expenses Analysis'!$B53,'Data Repository Table'!$F:$F,'Expenses Analysis'!$C53,'Data Repository Table'!$G:$G,'Expenses Analysis'!$D53,'Data Repository Table'!$D:$D,'Expenses Analysis'!J$46) -> 2376535.9 | K53: =SUMIFS('Data Repository Table'!$I:$I,'Data Repository Table'!$B:$B,'Expenses Analysis'!$B53,'Data Repository Table'!$F:$F,'Expenses Analysis'!$C53,'Data Repository Table'!$G:$G,'Expenses Analysis'!$D53,'Data Repository Table'!$D:$D,'Expenses Analysis'!K$46) -> 1447049.3 | L53: =SUMIFS('Data Repository Table'!$I:$I,'Data Repository Table'!$B:$B,'Expenses Analysis'!$B53,'Data Repository Table'!$F:$F,'Expenses Analysis'!$C53,'Data Repository Table'!$G:$G,'Expenses Analysis'!$D53,'Data Repository Table'!$D:$D,'Expenses Analysis'!L$46) -> 1483562.2 | M53: =SUMIFS('Data Repository Table'!$I:$I,'Data Repository Table'!$B:$B,'Expenses Analysis'!$B53,'Data Repository Table'!$F:$F,'Expenses Analysis'!$C53,'Data Repository Table'!$G:$G,'Expenses Analysis'!$D53,'Data Repository Table'!$D:$D,'Expenses Analysis'!M$46) -> 1516247.7 | ... Q53: =SUMIFS('Data Repository Table'!$I:$I,'Data Repository Table'!$B:$B,'Expenses Analysis'!$B53,'Data Repository Table'!$F:$F,'Expenses Analysis'!$C53,'Data Repository Table'!$G:$G,'Expenses Analysis'!$D53,'Data Repository Table'!$D:$D,'Expenses Analysis'!Q$46) -> 1452590.3 | R53: =SUM(F53:Q53) -> 21090667
A54: All | B54: Expenses | C54: Operational Maintenance Costs | D54: Plant Admin Costs (004) | F54: =SUMIFS('Data Repository Table'!$I:$I,'Data Repository Table'!$B:$B,'Expenses Analysis'!$B54,'Data Repository Table'!$F:$F,'Expenses Analysis'!$C54,'Data Repository Table'!$G:$G,'Expenses Analysis'!$D54,'Data Repository Table'!$D:$D,'Expenses Analysis'!F$46) -> 886197.6 | G54: =SUMIFS('Data Repository Table'!$I:$I,'Data Repository Table'!$B:$B,'Expenses Analysis'!$B54,'Data Repository Table'!$F:$F,'Expenses Analysis'!$C54,'Data Repository Table'!$G:$G,'Expenses Analysis'!$D54,'Data Repository Table'!$D:$D,'Expenses Analysis'!G$46) -> 1012646.7 | H54: =SUMIFS('Data Repository Table'!$I:$I,'Data Repository Table'!$B:$B,'Expenses Analysis'!$B54,'Data Repository Table'!$F:$F,'Expenses Analysis'!$C54,'Data Repository Table'!$G:$G,'Expenses Analysis'!$D54,'Data Repository Table'!$D:$D,'Expenses Analysis'!H$46) -> 1025398.9 | I54: =SUMIFS('Data Repository Table'!$I:$I,'Data Repository Table'!$B:$B,'Expenses Analysis'!$B54,'Data Repository Table'!$F:$F,'Expenses Analysis'!$C54,'Data Repository Table'!$G:$G,'Expenses Analysis'!$D54,'Data Repository Table'!$D:$D,'Expenses Analysis'!I$46) -> 1186611 | J54: =SUMIFS('Data Repository Table'!$I:$I,'Data Repository Table'!$B:$B,'Expenses Analysis'!$B54,'Data Repository Table'!$F:$F,'Expenses Analysis'!$C54,'Data Repository Table'!$G:$G,'Expenses Analysis'!$D54,'Data Repository Table'!$D:$D,'Expenses Analysis'!J$46) -> 1229462.3 | K54: =SUMIFS('Data Repository Table'!$I:$I,'Data Repository Table'!$B:$B,'Expenses Analysis'!$B54,'Data Repository Table'!$F:$F,'Expenses Analysis'!$C54,'Data Repository Table'!$G:$G,'Expenses Analysis'!$D54,'Data Repository Table'!$D:$D,'Expenses Analysis'!K$46) -> 749668.57 | L54: =SUMIFS('Data Repository Table'!$I:$I,'Data Repository Table'!$B:$B,'Expenses Analysis'!$B54,'Data Repository Table'!$F:$F,'Expenses Analysis'!$C54,'Data Repository Table'!$G:$G,'Expenses Analysis'!$D54,'Data Repository Table'!$D:$D,'Expenses Analysis'!L$46) -> 774322.05 | M54: =SUMIFS('Data Repository Table'!$I:$I,'Data Repository Table'!$B:$B,'Expenses Analysis'!$B54,'Data Repository Table'!$F:$F,'Expenses Analysis'!$C54,'Data Repository Table'!$G:$G,'Expenses Analysis'!$D54,'Data Repository Table'!$D:$D,'Expenses Analysis'!M$46) -> 795356.49 | ... Q54: =SUMIFS('Data Repository Table'!$I:$I,'Data Repository Table'!$B:$B,'Expenses Analysis'!$B54,'Data Repository Table'!$F:$F,'Expenses Analysis'!$C54,'Data Repository Table'!$G:$G,'Expenses Analysis'!$D54,'Data Repository Table'!$D:$D,'Expenses Analysis'!Q$46) -> 718766.35 | R54: =SUM(F54:Q54) -> 10813425
A55: All | B55: Expenses | C55: Labour Costs | D55: Labour-Costs (001) | F55: =SUMIFS('Data Repository Table'!$I:$I,'Data Repository Table'!$B:$B,'Expenses Analysis'!$B55,'Data Repository Table'!$F:$F,'Expenses Analysis'!$C55,'Data Repository Table'!$G:$G,'Expenses Analysis'!$D55,'Data Repository Table'!$D:$D,'Expenses Analysis'!F$46) -> 7367588.7 | G55: =SUMIFS('Data Repository Table'!$I:$I,'Data Repository Table'!$B:$B,'Expenses Analysis'!$B55,'Data Repository Table'!$F:$F,'Expenses Analysis'!$C55,'Data Repository Table'!$G:$G,'Expenses Analysis'!$D55,'Data Repository Table'!$D:$D,'Expenses Analysis'!G$46) -> 7849336 | H55: =SUMIFS('Data Repository Table'!$I:$I,'Data Repository Table'!$B:$B,'Expenses Analysis'!$B55,'Data Repository Table'!$F:$F,'Expenses Analysis'!$C55,'Data Repository Table'!$G:$G,'Expenses Analysis'!$D55,'Data Repository Table'!$D:$D,'Expenses Analysis'!H$46) -> 8389760.6 | I55: =SUMIFS('Data Repository Table'!$I:$I,'Data Repository Table'!$B:$B,'Expenses Analysis'!$B55,'Data Repository Table'!$F:$F,'Expenses Analysis'!$C55,'Data Repository Table'!$G:$G,'Expenses Analysis'!$D55,'Data Repository Table'!$D:$D,'Expenses Analysis'!I$46) -> 9137407.9 | J55: =SUMIFS('Data Repository Table'!$I:$I,'Data Repository Table'!$B:$B,'Expenses Analysis'!$B55,'Data Repository Table'!$F:$F,'Expenses Analysis'!$C55,'Data Repository Table'!$G:$G,'Expenses Analysis'!$D55,'Data Repository Table'!$D:$D,'Expenses Analysis'!J$46) -> 9187416 | K55: =SUMIFS('Data Repository Table'!$I:$I,'Data Repository Table'!$B:$B,'Expenses Analysis'!$B55,'Data Repository Table'!$F:$F,'Expenses Analysis'!$C55,'Data Repository Table'!$G:$G,'Expenses Analysis'!$D55,'Data Repository Table'!$D:$D,'Expenses Analysis'!K$46) -> 5779740.1 | L55: =SUMIFS('Data Repository Table'!$I:$I,'Data Repository Table'!$B:$B,'Expenses Analysis'!$B55,'Data Repository Table'!$F:$F,'Expenses Analysis'!$C55,'Data Repository Table'!$G:$G,'Expenses Analysis'!$D55,'Data Repository Table'!$D:$D,'Expenses Analysis'!L$46) -> 6008311.5 | M55: =SUMIFS('Data Repository Table'!$I:$I,'Data Repository Table'!$B:$B,'Expenses Analysis'!$B55,'Data Repository Table'!$F:$F,'Expenses Analysis'!$C55,'Data Repository Table'!$G:$G,'Expenses Analysis'!$D55,'Data Repository Table'!$D:$D,'Expenses Analysis'!M$46) -> 6995041 | ... Q55: =SUMIFS('Data Repository Table'!$I:$I,'Data Repository Table'!$B:$B,'Expenses Analysis'!$B55,'Data Repository Table'!$F:$F,'Expenses Analysis'!$C55,'Data Repository Table'!$G:$G,'Expenses Analysis'!$D55,'Data Repository Table'!$D:$D,'Expenses Analysis'!Q$46) -> 6174477.1 | R55: =SUM(F55:Q55) -> 87328632
A56: Total | B56: Total | C56: Total | D56: Total | F56: =SUM(F48:F55) -> 22966839 | G56: =SUM(G48:G55) -> 24947250 | H56: =SUM(H48:H55) -> 26345251 | I56: =SUM(I48:I55) -> 29462555 | J56: =SUM(J48:J55) -> 29964506 | K56: =SUM(K48:K55) -> 22328717 | L56: =SUM(L48:L55) -> 26435964 | M56: =SUM(M48:M55) -> 28369995 | ... Q56: =SUM(Q48:Q55) -> 23319122 | R56: =SUM(F56:Q56) -> 3.2126641e+08
A75: In the previous question we've now calculated the aggregate costs per month for all our desalination units (Kootha + Surjek+ Jutik).
A76: Let's now seek to visualize how the aggregate costs per month, compare to the individual unit costs per month.
A77: This helps us to better understand which units are contributing the most expenses.
A78: Q7. Create one line chart that displays for the Jul-13 to Jun-14 Period, the total costs per month for each unit, Kootha, Surjek and Jutik, as well as the Overall Total per month.
A79: Visualizing the data in this manner - do you see any particular unit that appears to contribute the majority of the costs? (i.e. One unit should emerge as the major contributor.)
A81: Unit | B81: Value Driver | C81: Accounting Code Centre | D81: Accounting Code Centre Element | F81: 41456 | G81: 41487 | H81: 41518 | I81: 41548 | J81: 41579 | K81: 41609 | L81: 41640 | M81: 41671 | N81: 41699 | O81: 41730 | P81: 41760 | Q81: 41791 | R81: Total
A82: Kootha | D82: Total | F82: =SUMIFS('Data Repository Table'!$I:$I,'Data Repository Table'!$C:$C,'Expenses Analysis'!$A82,'Data Repository Table'!$B:$B,'Expenses Analysis'!$B55,'Data Repository Table'!$D:$D,F$81) -> 3458288.9 | G82: =SUMIFS('Data Repository Table'!$I:$I,'Data Repository Table'!$C:$C,'Expenses Analysis'!$A82,'Data Repository Table'!$B:$B,'Expenses Analysis'!$B55,'Data Repository Table'!$D:$D,G$81) -> 4778353.4 | H82: =SUMIFS('Data Repository Table'!$I:$I,'Data Repository Table'!$C:$C,'Expenses Analysis'!$A82,'Data Repository Table'!$B:$B,'Expenses Analysis'!$B55,'Data Repository Table'!$D:$D,H$81) -> 3741007.1 | I82: =SUMIFS('Data Repository Table'!$I:$I,'Data Repository Table'!$C:$C,'Expenses Analysis'!$A82,'Data Repository Table'!$B:$B,'Expenses Analysis'!$B55,'Data Repository Table'!$D:$D,I$81) -> 3550828.8 | J82: =SUMIFS('Data Repository Table'!$I:$I,'Data Repository Table'!$C:$C,'Expenses Analysis'!$A82,'Data Repository Table'!$B:$B,'Expenses Analysis'!$B55,'Data Repository Table'!$D:$D,J$81) -> 3646543.4 | K82: =SUMIFS('Data Repository Table'!$I:$I,'Data Repository Table'!$C:$C,'Expenses Analysis'!$A82,'Data Repository Table'!$B:$B,'Expenses Analysis'!$B55,'Data Repository Table'!$D:$D,K$81) -> 3507223.4 | L82: =SUMIFS('Data Repository Table'!$I:$I,'Data Repository Table'!$C:$C,'Expenses Analysis'!$A82,'Data Repository Table'!$B:$B,'Expenses Analysis'!$B55,'Data Repository Table'!$D:$D,L$81) -> 5249820.3 | M82: =SUMIFS('Data Repository Table'!$I:$I,'Data Repository Table'!$C:$C,'Expenses Analysis'!$A82,'Data Repository Table'!$B:$B,'Expenses Analysis'!$B55,'Data Repository Table'!$D:$D,M$81) -> 4419792.7 | ... Q82: =SUMIFS('Data Repository Table'!$I:$I,'Data Repository Table'!$C:$C,'Expenses Analysis'!$A82,'Data Repository Table'!$B:$B,'Expenses Analysis'!$B55,'Data Repository Table'!$D:$D,Q$81) -> 5350137.2 | R82: 51223824
A83: Surjek | D83: Total | F83: =SUMIFS('Data Repository Table'!$I:$I,'Data Repository Table'!$C:$C,'Expenses Analysis'!$A83,'Data Repository Table'!$B:$B,'Expenses Analysis'!$B55,'Data Repository Table'!$D:$D,F$81) -> 11339551 | G83: =SUMIFS('Data Repository Table'!$I:$I,'Data Repository Table'!$C:$C,'Expenses Analysis'!$A83,'Data Repository Table'!$B:$B,'Expenses Analysis'!$B55,'Data Repository Table'!$D:$D,G$81) -> 13660880 | H83: =SUMIFS('Data Repository Table'!$I:$I,'Data Repository Table'!$C:$C,'Expenses Analysis'!$A83,'Data Repository Table'!$B:$B,'Expenses Analysis'!$B55,'Data Repository Table'!$D:$D,H$81) -> 13806948 | I83: =SUMIFS('Data Repository Table'!$I:$I,'Data Repository Table'!$C:$C,'Expenses Analysis'!$A83,'Data Repository Table'!$B:$B,'Expenses Analysis'!$B55,'Data Repository Table'!$D:$D,I$81) -> 18511924 | J83: =SUMIFS('Data Repository Table'!$I:$I,'Data Repository Table'!$C:$C,'Expenses Analysis'!$A83,'Data Repository Table'!$B:$B,'Expenses Analysis'!$B55,'Data Repository Table'!$D:$D,J$81) -> 20025365 | K83: =SUMIFS('Data Repository Table'!$I:$I,'Data Repository Table'!$C:$C,'Expenses Analysis'!$A83,'Data Repository Table'!$B:$B,'Expenses Analysis'!$B55,'Data Repository Table'!$D:$D,K$81) -> 12958943 | L83: =SUMIFS('Data Repository Table'!$I:$I,'Data Repository Table'!$C:$C,'Expenses Analysis'!$A83,'Data Repository Table'!$B:$B,'Expenses Analysis'!$B55,'Data Repository Table'!$D:$D,L$81) -> 13987466 | M83: =SUMIFS('Data Repository Table'!$I:$I,'Data Repository Table'!$C:$C,'Expenses Analysis'!$A83,'Data Repository Table'!$B:$B,'Expenses Analysis'!$B55,'Data Repository Table'!$D:$D,M$81) -> 16468493 | ... Q83: =SUMIFS('Data Repository Table'!$I:$I,'Data Repository Table'!$C:$C,'Expenses Analysis'!$A83,'Data Repository Table'!$B:$B,'Expenses Analysis'!$B55,'Data Repository Table'!$D:$D,Q$81) -> 8489071.3 | R83: 1.793191e+08
A84: Jutik | D84: Total | F84: =SUMIFS('Data Repository Table'!$I:$I,'Data Repository Table'!$C:$C,'Expenses Analysis'!$A84,'Data Repository Table'!$B:$B,'Expenses Analysis'!$B55,'Data Repository Table'!$D:$D,F$81) -> 8168998.6 | G84: =SUMIFS('Data Repository Table'!$I:$I,'Data Repository Table'!$C:$C,'Expenses Analysis'!$A84,'Data Repository Table'!$B:$B,'Expenses Analysis'!$B55,'Data Repository Table'!$D:$D,G$81) -> 6508016.3 | H84: =SUMIFS('Data Repository Table'!$I:$I,'Data Repository Table'!$C:$C,'Expenses Analysis'!$A84,'Data Repository Table'!$B:$B,'Expenses Analysis'!$B55,'Data Repository Table'!$D:$D,H$81) -> 8797296 | I84: =SUMIFS('Data Repository Table'!$I:$I,'Data Repository Table'!$C:$C,'Expenses Analysis'!$A84,'Data Repository Table'!$B:$B,'Expenses Analysis'!$B55,'Data Repository Table'!$D:$D,I$81) -> 7399801.7 | J84: =SUMIFS('Data Repository Table'!$I:$I,'Data Repository Table'!$C:$C,'Expenses Analysis'!$A84,'Data Repository Table'!$B:$B,'Expenses Analysis'!$B55,'Data Repository Table'!$D:$D,J$81) -> 6292597.9 | K84: =SUMIFS('Data Repository Table'!$I:$I,'Data Repository Table'!$C:$C,'Expenses Analysis'!$A84,'Data Repository Table'!$B:$B,'Expenses Analysis'!$B55,'Data Repository Table'!$D:$D,K$81) -> 5862551.5 | L84: =SUMIFS('Data Repository Table'!$I:$I,'Data Repository Table'!$C:$C,'Expenses Analysis'!$A84,'Data Repository Table'!$B:$B,'Expenses Analysis'!$B55,'Data Repository Table'!$D:$D,L$81) -> 7198677.8 | M84: =SUMIFS('Data Repository Table'!$I:$I,'Data Repository Table'!$C:$C,'Expenses Analysis'!$A84,'Data Repository Table'!$B:$B,'Expenses Analysis'!$B55,'Data Repository Table'!$D:$D,M$81) -> 7481709 | ... Q84: =SUMIFS('Data Repository Table'!$I:$I,'Data Repository Table'!$C:$C,'Expenses Analysis'!$A84,'Data Repository Table'!$B:$B,'Expenses Analysis'!$B55,'Data Repository Table'!$D:$D,Q$81) -> 9479913.3 | R84: 90723489
A85: Overall | D85: Total | F85: =SUM(F82:F84) -> 22966839 | G85: =SUM(G82:G84) -> 24947250 | H85: =SUM(H82:H84) -> 26345251 | I85: =SUM(I82:I84) -> 29462555 | J85: =SUM(J82:J84) -> 29964506 | K85: =SUM(K82:K84) -> 22328717 | L85: =SUM(L82:L84) -> 26435964 | M85: =SUM(M82:M84) -> 28369995 | ... Q85: =SUM(Q82:Q84) -> 23319122 | R85: 3.2126641e+08
A105: In the previous question, we've calculated the expenses at an aggregate level. You would have noticed some particularly high-costs for certain units that you'd be keen to dive into in more detail from a visual stand point. Let's do so!
A106: Q8. Using the Totals for the Year Column (Column R) for each Unit (Kootha, Surjek and Jutik), create a chart which clearly shows the Total Costs for each Cost Element. You will end up with three (3) Column Charts that will let you see which of the Units Accounting Code Centre Elements drive the majority of costs. What trends have you noticed?
A124: We've analysed the expenses data and we have a few questions. The costs for two of our Cost Elements is particularly high - could this potentially be related to the periods of high water production?
A125: We can answer this question by using the Water Production Data that is available in the Data Repository Table.
A126: However, it is important to note that for the water production data, it has been aggregated. This means we cannot see the separation between Soft / Hard Water Production.
A127: This means in the analysis you will complete below, you can only make logical assumptions.
A128: As a Data Analyst, you will not always have all the data you need to make a conclusion.
A129: In cases like the one below, you will have to draw on logical conclusions from the data available to you and make a conclusion.
A130: Q9. For each of the three units (Kootha, Surjek, Jutik), complete the table below that will show the monthly water production for each Unit as well as the monthly chemical expenditure. Once the table is complete, create two charts for each unit, showing the Chemical Costs and Water Production. What trends emerge when looking at the data in this manner? We've included an example for you so you can see what the Chart should look like!
A132: Account Type | B132: Unit | C132: Value Driver | D132: Accounting Code Centre | E132: Accounting Code Centre Element | F132: 41456 | G132: 41487 | H132: 41518 | I132: 41548 | J132: 41579 | K132: 41609 | L132: 41640 | M132: 41671 | N132: 41699 | O132: 41730 | P132: 41760 | Q132: 41791
A133: Financial Actual | B133: Kootha | C133: Expenses | D133: Chemical Costs | E133: Chem-Exp (001) | F133: =SUMIFS('Data Repository Table'!$I:$I,'Data Repository Table'!$A:$A,'Expenses Analysis'!$A133,'Data Repository Table'!$C:$C,'Expenses Analysis'!$B133,'Data Repository Table'!$B:$B,'Expenses Analysis'!$C133,'Data Repository Table'!$F:$F,'Expenses Analysis'!$D133,'Data Repository Table'!$G:$G,'Expenses Analysis'!$E133,'Data Repository Table'!$D:$D,'Expenses Analysis'!F$132) -> 593751.84 | G133: =SUMIFS('Data Repository Table'!$I:$I,'Data Repository Table'!$A:$A,'Expenses Analysis'!$A133,'Data Repository Table'!$C:$C,'Expenses Analysis'!$B133,'Data Repository Table'!$B:$B,'Expenses Analysis'!$C133,'Data Repository Table'!$F:$F,'Expenses Analysis'!$D133,'Data Repository Table'!$G:$G,'Expenses Analysis'!$E133,'Data Repository Table'!$D:$D,'Expenses Analysis'!G$132) -> 820393.03 | H133: =SUMIFS('Data Repository Table'!$I:$I,'Data Repository Table'!$A:$A,'Expenses Analysis'!$A133,'Data Repository Table'!$C:$C,'Expenses Analysis'!$B133,'Data Repository Table'!$B:$B,'Expenses Analysis'!$C133,'Data Repository Table'!$F:$F,'Expenses Analysis'!$D133,'Data Repository Table'!$G:$G,'Expenses Analysis'!$E133,'Data Repository Table'!$D:$D,'Expenses Analysis'!H$132) -> 642291.58 | I133: =SUMIFS('Data Repository Table'!$I:$I,'Data Repository Table'!$A:$A,'Expenses Analysis'!$A133,'Data Repository Table'!$C:$C,'Expenses Analysis'!$B133,'Data Repository Table'!$B:$B,'Expenses Analysis'!$C133,'Data Repository Table'!$F:$F,'Expenses Analysis'!$D133,'Data Repository Table'!$G:$G,'Expenses Analysis'!$E133,'Data Repository Table'!$D:$D,'Expenses Analysis'!I$132) -> 609639.97 | J133: =SUMIFS('Data Repository Table'!$I:$I,'Data Repository Table'!$A:$A,'Expenses Analysis'!$A133,'Data Repository Table'!$C:$C,'Expenses Analysis'!$B133,'Data Repository Table'!$B:$B,'Expenses Analysis'!$C133,'Data Repository Table'!$F:$F,'Expenses Analysis'!$D133,'Data Repository Table'!$G:$G,'Expenses Analysis'!$E133,'Data Repository Table'!$D:$D,'Expenses Analysis'!J$132) -> 626073.17 | K133: =SUMIFS('Data Repository Table'!$I:$I,'Data Repository Table'!$A:$A,'Expenses Analysis'!$A133,'Data Repository Table'!$C:$C,'Expenses Analysis'!$B133,'Data Repository Table'!$B:$B,'Expenses Analysis'!$C133,'Data Repository Table'!$F:$F,'Expenses Analysis'!$D133,'Data Repository Table'!$G:$G,'Expenses Analysis'!$E133,'Data Repository Table'!$D:$D,'Expenses Analysis'!K$132) -> 602153.38 | L133: =SUMIFS('Data Repository Table'!$I:$I,'Data Repository Table'!$A:$A,'Expenses Analysis'!$A133,'Data Repository Table'!$C:$C,'Expenses Analysis'!$B133,'Data Repository Table'!$B:$B,'Expenses Analysis'!$C133,'Data Repository Table'!$F:$F,'Expenses Analysis'!$D133,'Data Repository Table'!$G:$G,'Expenses Analysis'!$E133,'Data Repository Table'!$D:$D,'Expenses Analysis'!L$132) -> 1146144 | M133: =SUMIFS('Data Repository Table'!$I:$I,'Data Repository Table'!$A:$A,'Expenses Analysis'!$A133,'Data Repository Table'!$C:$C,'Expenses Analysis'!$B133,'Data Repository Table'!$B:$B,'Expenses Analysis'!$C133,'Data Repository Table'!$F:$F,'Expenses Analysis'!$D133,'Data Repository Table'!$G:$G,'Expenses Analysis'!$E133,'Data Repository Table'!$D:$D,'Expenses Analysis'!M$132) -> 964931.84 | ... Q133: =SUMIFS('Data Repository Table'!$I:$I,'Data Repository Table'!$A:$A,'Expenses Analysis'!$A133,'Data Repository Table'!$C:$C,'Expenses Analysis'!$B133,'Data Repository Table'!$B:$B,'Expenses Analysis'!$C133,'Data Repository Table'!$F:$F,'Expenses Analysis'!$D133,'Data Repository Table'!$G:$G,'Expenses Analysis'!$E133,'Data Repository Table'!$D:$D,'Expenses Analysis'!Q$132) -> 1168045.2
A134: Water Production Actuals | B134: Kootha | C134: None | D134: None | E134: None | F134: =SUMIFS('Data Repository Table'!$I:$I,'Data Repository Table'!$A:$A,'Expenses Analysis'!$A134,'Data Repository Table'!$C:$C,'Expenses Analysis'!$B134,'Data Repository Table'!$B:$B,'Expenses Analysis'!$C134,'Data Repository Table'!$F:$F,'Expenses Analysis'!$D134,'Data Repository Table'!$G:$G,'Expenses Analysis'!$E134,'Data Repository Table'!$D:$D,'Expenses Analysis'!F$132) -> 181.93329 | G134: =SUMIFS('Data Repository Table'!$I:$I,'Data Repository Table'!$A:$A,'Expenses Analysis'!$A134,'Data Repository Table'!$C:$C,'Expenses Analysis'!$B134,'Data Repository Table'!$B:$B,'Expenses Analysis'!$C134,'Data Repository Table'!$F:$F,'Expenses Analysis'!$D134,'Data Repository Table'!$G:$G,'Expenses Analysis'!$E134,'Data Repository Table'!$D:$D,'Expenses Analysis'!G$132) -> 187.44394 | H134: =SUMIFS('Data Repository Table'!$I:$I,'Data Repository Table'!$A:$A,'Expenses Analysis'!$A134,'Data Repository Table'!$C:$C,'Expenses Analysis'!$B134,'Data Repository Table'!$B:$B,'Expenses Analysis'!$C134,'Data Repository Table'!$F:$F,'Expenses Analysis'!$D134,'Data Repository Table'!$G:$G,'Expenses Analysis'!$E134,'Data Repository Table'!$D:$D,'Expenses Analysis'!H$132) -> 184.77366 | I134: =SUMIFS('Data Repository Table'!$I:$I,'Data Repository Table'!$A:$A,'Expenses Analysis'!$A134,'Data Repository Table'!$C:$C,'Expenses Analysis'!$B134,'Data Repository Table'!$B:$B,'Expenses Analysis'!$C134,'Data Repository Table'!$F:$F,'Expenses Analysis'!$D134,'Data Repository Table'!$G:$G,'Expenses Analysis'!$E134,'Data Repository Table'!$D:$D,'Expenses Analysis'!I$132) -> 191.54109 | J134: =SUMIFS('Data Repository Table'!$I:$I,'Data Repository Table'!$A:$A,'Expenses Analysis'!$A134,'Data Repository Table'!$C:$C,'Expenses Analysis'!$B134,'Data Repository Table'!$B:$B,'Expenses Analysis'!$C134,'Data Repository Table'!$F:$F,'Expenses Analysis'!$D134,'Data Repository Table'!$G:$G,'Expenses Analysis'!$E134,'Data Repository Table'!$D:$D,'Expenses Analysis'!J$132) -> 98.096062 | K134: =SUMIFS('Data Repository Table'!$I:$I,'Data Repository Table'!$A:$A,'Expenses Analysis'!$A134,'Data Repository Table'!$C:$C,'Expenses Analysis'!$B134,'Data Repository Table'!$B:$B,'Expenses Analysis'!$C134,'Data Repository Table'!$F:$F,'Expenses Analysis'!$D134,'Data Repository Table'!$G:$G,'Expenses Analysis'!$E134,'Data Repository Table'!$D:$D,'Expenses Analysis'!K$132) -> 185.30685 | L134: =SUMIFS('Data Repository Table'!$I:$I,'Data Repository Table'!$A:$A,'Expenses Analysis'!$A134,'Data Repository Table'!$C:$C,'Expenses Analysis'!$B134,'Data Repository Table'!$B:$B,'Expenses Analysis'!$C134,'Data Repository Table'!$F:$F,'Expenses Analysis'!$D134,'Data Repository Table'!$G:$G,'Expenses Analysis'!$E134,'Data Repository Table'!$D:$D,'Expenses Analysis'!L$132) -> 186.90144 | M134: =SUMIFS('Data Repository Table'!$I:$I,'Data Repository Table'!$A:$A,'Expenses Analysis'!$A134,'Data Repository Table'!$C:$C,'Expenses Analysis'!$B134,'Data Repository Table'!$B:$B,'Expenses Analysis'!$C134,'Data Repository Table'!$F:$F,'Expenses Analysis'!$D134,'Data Repository Table'!$G:$G,'Expenses Analysis'!$E134,'Data Repository Table'!$D:$D,'Expenses Analysis'!M$132) -> 158.58677 | ... Q134: =SUMIFS('Data Repository Table'!$I:$I,'Data Repository Table'!$A:$A,'Expenses Analysis'!$A134,'Data Repository Table'!$C:$C,'Expenses Analysis'!$B134,'Data Repository Table'!$B:$B,'Expenses Analysis'!$C134,'Data Repository Table'!$F:$F,'Expenses Analysis'!$D134,'Data Repository Table'!$G:$G,'Expenses Analysis'!$E134,'Data Repository Table'!$D:$D,'Expenses Analysis'!Q$132) -> 142.50872
A135: Financial Actual | B135: Surjek | C135: Expenses | D135: Chemical Costs | E135: Chem-Exp (001) | F135: =SUMIFS('Data Repository Table'!$I:$I,'Data Repository Table'!$A:$A,'Expenses Analysis'!$A135,'Data Repository Table'!$C:$C,'Expenses Analysis'!$B135,'Data Repository Table'!$B:$B,'Expenses Analysis'!$C135,'Data Repository Table'!$F:$F,'Expenses Analysis'!$D135,'Data Repository Table'!$G:$G,'Expenses Analysis'!$E135,'Data Repository Table'!$D:$D,'Expenses Analysis'!F$132) -> 2533034.5 | G135: =SUMIFS('Data Repository Table'!$I:$I,'Data Repository Table'!$A:$A,'Expenses Analysis'!$A135,'Data Repository Table'!$C:$C,'Expenses Analysis'!$B135,'Data Repository Table'!$B:$B,'Expenses Analysis'!$C135,'Data Repository Table'!$F:$F,'Expenses Analysis'!$D135,'Data Repository Table'!$G:$G,'Expenses Analysis'!$E135,'Data Repository Table'!$D:$D,'Expenses Analysis'!G$132) -> 3051574.2 | H135: =SUMIFS('Data Repository Table'!$I:$I,'Data Repository Table'!$A:$A,'Expenses Analysis'!$A135,'Data Repository Table'!$C:$C,'Expenses Analysis'!$B135,'Data Repository Table'!$B:$B,'Expenses Analysis'!$C135,'Data Repository Table'!$F:$F,'Expenses Analysis'!$D135,'Data Repository Table'!$G:$G,'Expenses Analysis'!$E135,'Data Repository Table'!$D:$D,'Expenses Analysis'!H$132) -> 3084202.8 | I135: =SUMIFS('Data Repository Table'!$I:$I,'Data Repository Table'!$A:$A,'Expenses Analysis'!$A135,'Data Repository Table'!$C:$C,'Expenses Analysis'!$B135,'Data Repository Table'!$B:$B,'Expenses Analysis'!$C135,'Data Repository Table'!$F:$F,'Expenses Analysis'!$D135,'Data Repository Table'!$G:$G,'Expenses Analysis'!$E135,'Data Repository Table'!$D:$D,'Expenses Analysis'!I$132) -> 4135202.8 | J135: =SUMIFS('Data Repository Table'!$I:$I,'Data Repository Table'!$A:$A,'Expenses Analysis'!$A135,'Data Repository Table'!$C:$C,'Expenses Analysis'!$B135,'Data Repository Table'!$B:$B,'Expenses Analysis'!$C135,'Data Repository Table'!$F:$F,'Expenses Analysis'!$D135,'Data Repository Table'!$G:$G,'Expenses Analysis'!$E135,'Data Repository Table'!$D:$D,'Expenses Analysis'!J$132) -> 4473275.9 | K135: =SUMIFS('Data Repository Table'!$I:$I,'Data Repository Table'!$A:$A,'Expenses Analysis'!$A135,'Data Repository Table'!$C:$C,'Expenses Analysis'!$B135,'Data Repository Table'!$B:$B,'Expenses Analysis'!$C135,'Data Repository Table'!$F:$F,'Expenses Analysis'!$D135,'Data Repository Table'!$G:$G,'Expenses Analysis'!$E135,'Data Repository Table'!$D:$D,'Expenses Analysis'!K$132) -> 3464957.9 | L135: =SUMIFS('Data Repository Table'!$I:$I,'Data Repository Table'!$A:$A,'Expenses Analysis'!$A135,'Data Repository Table'!$C:$C,'Expenses Analysis'!$B135,'Data Repository Table'!$B:$B,'Expenses Analysis'!$C135,'Data Repository Table'!$F:$F,'Expenses Analysis'!$D135,'Data Repository Table'!$G:$G,'Expenses Analysis'!$E135,'Data Repository Table'!$D:$D,'Expenses Analysis'!L$132) -> 4049642.8 | M135: =SUMIFS('Data Repository Table'!$I:$I,'Data Repository Table'!$A:$A,'Expenses Analysis'!$A135,'Data Repository Table'!$C:$C,'Expenses Analysis'!$B135,'Data Repository Table'!$B:$B,'Expenses Analysis'!$C135,'Data Repository Table'!$F:$F,'Expenses Analysis'!$D135,'Data Repository Table'!$G:$G,'Expenses Analysis'!$E135,'Data Repository Table'!$D:$D,'Expenses Analysis'!M$132) -> 4767948.2 | ... Q135: =SUMIFS('Data Repository Table'!$I:$I,'Data Repository Table'!$A:$A,'Expenses Analysis'!$A135,'Data Repository Table'!$C:$C,'Expenses Analysis'!$B135,'Data Repository Table'!$B:$B,'Expenses Analysis'!$C135,'Data Repository Table'!$F:$F,'Expenses Analysis'!$D135,'Data Repository Table'!$G:$G,'Expenses Analysis'!$E135,'Data Repository Table'!$D:$D,'Expenses Analysis'!Q$132) -> 2269805.2
